Workbook
Name Lookup3: #REF!
Name Lookup3: #REF!
Name Lookup4: #REF!
Name Lookup4: #REF!
Name Lookup5: #REF!
Name Lookup5: #REF!
Name Lookup8: #REF!
Name Lookup8: #REF!
Name MY_FUNCTION1: LAMBDA(COUNTIF(#REF!,"P, GS, NS, AS")+COUNTIF(#REF!,"HFL")/2)
Name MY_FUNCTION1: LAMBDA(COUNTIF(#REF!,"P, GS, NS, AS")+COUNTIF(#REF!,"HFL")/2)

Sheet Anchors_Feb'26
O1: 28 | AB1: EMPLOYEE CONTRIBUTION | AE1: EMPLOYER CONTRIBUTION | AH1: DEDUCTIONS
A2: Sl.No. | B2: EMP ID | C2: DOJ | D2: Employee Name | E2: Department | F2: Bank A/c No | G2: IFSC | H2: UAN | I2: PAN | J2: ESI NO | K2: DOB | L2: Gender | M2: Bifurcation of Employees | N2: DOE | O2: Payable Days | P2: Standed Month Salary | Q2: Current Month Salary | R2: Basic | S2: HRA | T2: LTA | U2: Special Allowances | V2: Gross Salary | W2: One time Bonus | X2: Gratuity | Y2: Final Gross | Z2: Gross for PF | AA2: EPF Wages | AB2: P.F.(12%) | AC2: VPF | AD2: ESI (0.75%) | AE2: E.P.F. (8.33%) | AF2: P.F. (3.67%) | AG2: ESI (3.25%) | AH2: TDS | AI2: Any Others / Advance | AJ2: Insurance Advance | AK2: Profession Tax | AL2: LWF | AM2: (PF+ESI+LWF) | AN2: Net Salary | AO2: Commnets | AP2: No. of completed year of service (Gratuity) | AQ2: Last drwan Basic Salary | AR2: Gratutiy Amount
A3: 1 | B3: JAI-042 | C3: 43983 | E3: Anchor | F3: 50100302993158 | G3: HDFC0001635 | H3: 101548467393 | I3: FENPM4917N | J3: 5216260893 | K3: 35560 | L3: Female | M3: Semi-skilled | N3: =VLOOKUP(B3,'Anchor-Attendance'!$B$4:$K$84,10,0) -> 46072 | O3: =VLOOKUP(B3,'Anchor-Attendance'!$B$4:$BB$84,53,0) -> 19 | P3: 12360 | Q3: =P3/$O$1*O3 -> 8387.1429 | R3: =Q3*100% -> 8387.1429 | S3: 0 | T3: 0 | U3: 0 | V3: =ROUND(SUM(R3:U3),0) -> 8387 | W3: =12360-V3 -> 3973 | X3: =AR3 -> 42785 | Y3: =SUM(V3:X3) -> 55145 | Z3: =ROUND(SUM(R3:U3)-S3,0) -> 8387 | AA3: =ROUND(IF(Z3>15000,15000,Z3),0) -> 8387 | AB3: =ROUND(IF(Z3>15000,1800,Z3*12%),0) -> 1006 | AC3: 0 | AD3: =ROUNDUP(IF(P3>21000,0,(Y3-X3)*0.75%),0) -> 93 | AE3: =ROUND(AB3/12%*8.33%,0) -> 698 | AF3: =+AB3-AE3 -> 308 | AG3: =IF(P3>21000,0,(Y3-X3)*3.25%) -> 401.7 | AH3: 0 | AI3: 0 | AJ3: 0 | AK3: =IF((Y3-X3)>=20001,200,IF((Y3-X3)>=15001,150,0)) -> 0 | AL3: 0 | AM3: =AB3+AD3+AL3 -> 1099 | AN3: =SUM(ROUND((Y3)-(AH3+AI3+AJ3+AK3+AM3),0),0) -> 54046 | AO3: Full month salary to be paid | AP3: =ROUND((N3-C3)/365,0) -> 6 | AQ3: =P3 -> 12360 | AR3: =ROUND(AQ3*15/26*AP3,0) -> 42785
A4: =A3+1 -> 2 | B4: JAI-060 | C4: 43983 | E4: Anchor | F4: 50100326226811 | G4: HDFC0001635 | H4: 101548467653 | I4: BPTPN8806A | J4: 5216240667 | K4: 34141 | L4: Female | M4: Semi-skilled | N4: =VLOOKUP(B4,'Anchor-Attendance'!$B$4:$K$84,10,0) -> 46072 | O4: =VLOOKUP(B4,'Anchor-Attendance'!$B$4:$BB$84,53,0) -> 19 | P4: 12360 | Q4: =P4/$O$1*O4 -> 8387.1429 | R4: =Q4*100% -> 8387.1429 | S4: 0 | T4: 0 | U4: 0 | V4: =ROUND(SUM(R4:U4),0) -> 8387 | W4: =12360-V4 -> 3973 | X4: =AR4 -> 42785 | Y4: =SUM(V4:X4) -> 55145 | Z4: =ROUND(SUM(R4:U4)-S4,0) -> 8387 | AA4: =ROUND(IF(Z4>15000,15000,Z4),0) -> 8387 | AB4: =ROUND(IF(Z4>15000,1800,Z4*12%),0) -> 1006 | AC4: 0 | AD4: =ROUNDUP(IF(P4>21000,0,(Y4-X4)*0.75%),0) -> 93 | AE4: =ROUND(AB4/12%*8.33%,0) -> 698 | AF4: =+AB4-AE4 -> 308 | AG4: =IF(P4>21000,0,(Y4-X4)*3.25%) -> 401.7 | AH4: 0 | AI4: 0 | AJ4: 0 | AK4: =IF((Y4-X4)>=20001,200,IF((Y4-X4)>=15001,150,0)) -> 0 | AL4: 0 | AM4: =AB4+AD4+AL4 -> 1099 | AN4: =SUM(ROUND((Y4)-(AH4+AI4+AJ4+AK4+AM4),0),0) -> 54046 | AO4: Full month salary to be paid | AP4: =ROUND((N4-C4)/365,0) -> 6 | AQ4: =P4 -> 12360 | AR4: =ROUND(AQ4*15/26*AP4,0) -> 42785
A5: =A4+1 -> 3 | B5: JAI-081 | C5: 43983 | E5: Anchor | F5: 50100302993145 | G5: HDFC0001635 | H5: 101589851810 | I5: JNFPK9704N | J5: 5216601062 | K5: 35958 | L5: Female | M5: Semi-skilled | N5: No | O5: =VLOOKUP(B5,'Anchor-Attendance'!$B$4:$BB$84,53,0) -> 28 | P5: 12360 | Q5: =P5/$O$1*O5 -> 12360 | R5: =Q5*100% -> 12360 | S5: 0 | T5: 0 | U5: 0 | V5: =ROUND(SUM(R5:U5),0) -> 12360 | W5: 0 | X5: 0 | Y5: =SUM(V5:X5) -> 12360 | Z5: =ROUND(SUM(R5:U5)-S5,0) -> 12360 | AA5: =ROUND(IF(Z5>15000,15000,Z5),0) -> 12360 | AB5: =ROUND(IF(Z5>15000,1800,Z5*12%),0) -> 1483 | AC5: 0 | AD5: =ROUNDUP(IF(P5>21000,0,(Y5-X5)*0.75%),0) -> 93 | AE5: =ROUND(AB5/12%*8.33%,0) -> 1029 | AF5: =+AB5-AE5 -> 454 | AG5: =IF(P5>21000,0,(Y5-X5)*3.25%) -> 401.7 | AH5: 0 | AI5: 0 | AJ5: 0 | AK5: =IF((Y5-X5)>=20001,200,IF((Y5-X5)>=15001,150,0)) -> 0 | AL5: 0 | AM5: =AB5+AD5+AL5 -> 1576 | AN5: =SUM(ROUND((Y5)-(AH5+AI5+AJ5+AK5+AM5),0),0) -> 10784
A6: =A5+1 -> 4 | B6: JAI-098 | C6: 43983 | E6: Anchor | F6: 50100302993694 | G6: HDFC0001635 | H6: 101548467892 | I6: FNTPP6732H | J6: 5216242698 | K6: 35266 | L6: Female | M6: Semi-skilled | N6: No | O6: =VLOOKUP(B6,'Anchor-Attendance'!$B$4:$BB$84,53,0) -> 28 | P6: 12360 | Q6: =P6/$O$1*O6 -> 12360 | R6: =Q6*100% -> 12360 | S6: 0 | T6: 0 | U6: 0 | V6: =ROUND(SUM(R6:U6),0) -> 12360 | W6: 0 | X6: 0 | Y6: =SUM(V6:X6) -> 12360 | Z6: =ROUND(SUM(R6:U6)-S6,0) -> 12360 | AA6: =ROUND(IF(Z6>15000,15000,Z6),0) -> 12360 | AB6: =ROUND(IF(Z6>15000,1800,Z6*12%),0) -> 1483 | AC6: 0 | AD6: =ROUNDUP(IF(P6>21000,0,(Y6-X6)*0.75%),0) -> 93 | AE6: =ROUND(AB6/12%*8.33%,0) -> 1029 | AF6: =+AB6-AE6 -> 454 | AG6: =IF(P6>21000,0,(Y6-X6)*3.25%) -> 401.7 | AH6: 0 | AI6: 0 | AJ6: 0 | AK6: =IF((Y6-X6)>=20001,200,IF((Y6-X6)>=15001,150,0)) -> 0 | AL6: 0 | AM6: =AB6+AD6+AL6 -> 1576 | AN6: =SUM(ROUND((Y6)-(AH6+AI6+AJ6+AK6+AM6),0),0) -> 10784
A7: =A6+1 -> 5 | B7: JAI-144 | C7: 44075 | E7: Anchor | F7: 50100373849809 | G7: HDFC0001635 | H7: 101620639348 | I7: DJDPM2220M | J7: 5216743492 | K7: 35292 | L7: Female | M7: Semi-skilled | N7: No | O7: =VLOOKUP(B7,'Anchor-Attendance'!$B$4:$BB$84,53,0) -> 28 | P7: 12360 | Q7: =P7/$O$1*O7 -> 12360 | R7: =Q7*100% -> 12360 | S7: 0 | T7: 0 | U7: 0 | V7: =ROUND(SUM(R7:U7),0) -> 12360 | W7: 0 | X7: 0 | Y7: =SUM(V7:X7) -> 12360 | Z7: =ROUND(SUM(R7:U7)-S7,0) -> 12360 | AA7: =ROUND(IF(Z7>15000,15000,Z7),0) -> 12360 | AB7: =ROUND(IF(Z7>15000,1800,Z7*12%),0) -> 1483 | AC7: 0 | AD7: =ROUNDUP(IF(P7>21000,0,(Y7-X7)*0.75%),0) -> 93 | AE7: =ROUND(AB7/12%*8.33%,0) -> 1029 | AF7: =+AB7-AE7 -> 454 | AG7: =IF(P7>21000,0,(Y7-X7)*3.25%) -> 401.7 | AH7: 0 | AI7: 0 | AJ7: 0 | AK7: =IF((Y7-X7)>=20001,200,IF((Y7-X7)>=15001,150,0)) -> 0 | AL7: 0 | AM7: =AB7+AD7+AL7 -> 1576 | AN7: =SUM(ROUND((Y7)-(AH7+AI7+AJ7+AK7+AM7),0),0) -> 10784
A8: =A7+1 -> 6 | B8: JAI-148 | C8: 44075 | E8: Anchor | F8: 50100373849555 | G8: HDFC0001635 | H8: 101641624231 | I8: IFSPP2656L | J8: 5216745322 | K8: 36741 | L8: Female | M8: Semi-skilled | N8: No | O8: =VLOOKUP(B8,'Anchor-Attendance'!$B$4:$BB$84,53,0) -> 28 | P8: 12360 | Q8: =P8/$O$1*O8 -> 12360 | R8: =Q8*100% -> 12360 | S8: 0 | T8: 0 | U8: 0 | V8: =ROUND(SUM(R8:U8),0) -> 12360 | W8: 0 | X8: 0 | Y8: =SUM(V8:X8) -> 12360 | Z8: =ROUND(SUM(R8:U8)-S8,0) -> 12360 | AA8: =ROUND(IF(Z8>15000,15000,Z8),0) -> 12360 | AB8: =ROUND(IF(Z8>15000,1800,Z8*12%),0) -> 1483 | AC8: 0 | AD8: =ROUNDUP(IF(P8>21000,0,(Y8-X8)*0.75%),0) -> 93 | AE8: =ROUND(AB8/12%*8.33%,0) -> 1029 | AF8: =+AB8-AE8 -> 454 | AG8: =IF(P8>21000,0,(Y8-X8)*3.25%) -> 401.7 | AH8: 0 | AI8: 0 | AJ8: 0 | AK8: =IF((Y8-X8)>=20001,200,IF((Y8-X8)>=15001,150,0)) -> 0 | AL8: 0 | AM8: =AB8+AD8+AL8 -> 1576 | AN8: =SUM(ROUND((Y8)-(AH8+AI8+AJ8+AK8+AM8),0),0) -> 10784
A9: =A8+1 -> 7 | B9: JAI-173 | C9: 44131 | E9: Anchor | F9: 50100389932244 | G9: HDFC0000240 | H9: 101641624220 | I9: COLPJ2745G | J9: 5216892953 | K9: 35455 | L9: Female | M9: Semi-skilled | N9: No | O9: =VLOOKUP(B9,'Anchor-Attendance'!$B$4:$BB$84,53,0) -> 28 | P9: 12360 | Q9: =P9/$O$1*O9 -> 12360 | R9: =Q9*100% -> 12360 | S9: 0 | T9: 0 | U9: 0 | V9: =ROUND(SUM(R9:U9),0) -> 12360 | W9: 0 | X9: 0 | Y9: =SUM(V9:X9) -> 12360 | Z9: =ROUND(SUM(R9:U9)-S9,0) -> 12360 | AA9: =ROUND(IF(Z9>15000,15000,Z9),0) -> 12360 | AB9: =ROUND(IF(Z9>15000,1800,Z9*12%),0) -> 1483 | AC9: 0 | AD9: =ROUNDUP(IF(P9>21000,0,(Y9-X9)*0.75%),0) -> 93 | AE9: =ROUND(AB9/12%*8.33%,0) -> 1029 | AF9: =+AB9-AE9 -> 454 | AG9: =IF(P9>21000,0,(Y9-X9)*3.25%) -> 401.7 | AH9: 0 | AI9: 0 | AJ9: 0 | AK9: =IF((Y9-X9)>=20001,200,IF((Y9-X9)>=15001,150,0)) -> 0 | AL9: 0 | AM9: =AB9+AD9+AL9 -> 1576 | AN9: =SUM(ROUND((Y9)-(AH9+AI9+AJ9+AK9+AM9),0),0) -> 10784
A10: =A9+1 -> 8 | B10: JAI-246 | C10: 44326 | E10: Anchor | F10: 50100426485354 | G10: HDFC0000240 | H10: 101693034754 | I10: DUCPA7598L | J10: 5217396231 | K10: 36160 | L10: Female | M10: Semi-skilled | N10: No | O10: =VLOOKUP(B10,'Anchor-Attendance'!$B$4:$BB$84,53,0) -> 28 | P10: 12360 | Q10: =P10/$O$1*O10 -> 12360 | R10: =Q10*100% -> 12360 | S10: 0 | T10: 0 | U10: 0 | V10: =ROUND(SUM(R10:U10),0) -> 12360 | W10: 0 | X10: 0 | Y10: =SUM(V10:X10) -> 12360 | Z10: =ROUND(SUM(R10:U10)-S10,0) -> 12360 | AA10: =ROUND(IF(Z10>15000,15000,Z10),0) -> 12360 | AB10: =ROUND(IF(Z10>15000,1800,Z10*12%),0) -> 1483 | AC10: 0 | AD10: =ROUNDUP(IF(P10>21000,0,(Y10-X10)*0.75%),0) -> 93 | AE10: =ROUND(AB10/12%*8.33%,0) -> 1029 | AF10: =+AB10-AE10 -> 454 | AG10: =IF(P10>21000,0,(Y10-X10)*3.25%) -> 401.7 | AH10: 0 | AI10: 0 | AJ10: 0 | AK10: =IF((Y10-X10)>=20001,200,IF((Y10-X10)>=15001,150,0)) -> 0 | AL10: 0 | AM10: =AB10+AD10+AL10 -> 1576 | AN10: =SUM(ROUND((Y10)-(AH10+AI10+AJ10+AK10+AM10),0),0) -> 10784
A11: =A10+1 -> 9 | B11: JAI-248 | C11: 44326 | E11: Anchor | F11: 50100421884544 | G11: HDFC0000240 | H11: 101693033653 | I11: FPPPB7330B | J11: 5217395947 | K11: 33201 | L11: Female | M11: Semi-skilled | N11: No | O11: =VLOOKUP(B11,'Anchor-Attendance'!$B$4:$BB$84,53,0) -> 28 | P11: 12360 | Q11: =P11/$O$1*O11 -> 12360 | R11: =Q11*100% -> 12360 | S11: 0 | T11: 0 | U11: 0 | V11: =ROUND(SUM(R11:U11),0) -> 12360 | W11: 0 | X11: 0 | Y11: =SUM(V11:X11) -> 12360 | Z11: =ROUND(SUM(R11:U11)-S11,0) -> 12360 | AA11: =ROUND(IF(Z11>15000,15000,Z11),0) -> 12360 | AB11: =ROUND(IF(Z11>15000,1800,Z11*12%),0) -> 1483 | AC11: 0 | AD11: =ROUNDUP(IF(P11>21000,0,(Y11-X11)*0.75%),0) -> 93 | AE11: =ROUND(AB11/12%*8.33%,0) -> 1029 | AF11: =+AB11-AE11 -> 454 | AG11: =IF(P11>21000,0,(Y11-X11)*3.25%) -> 401.7 | AH11: 0 | AI11: 0 | AJ11: 0 | AK11: =IF((Y11-X11)>=20001,200,IF((Y11-X11)>=15001,150,0)) -> 0 | AL11: 0 | AM11: =AB11+AD11+AL11 -> 1576 | AN11: =SUM(ROUND((Y11)-(AH11+AI11+AJ11+AK11+AM11),0),0) -> 10784
A12: =A11+1 -> 10 | B12: JAI-260 | C12: 44326 | E12: Anchor | F12: 50100426485519 | G12: HDFC0000240 | H12: 101693033109 | I12: FFGPR2158Q | J12: 5217398845 | K12: 35586 | L12: Female | M12: Semi-skilled | N12: No | O12: =VLOOKUP(B12,'Anchor-Attendance'!$B$4:$BB$84,53,0) -> 12 | P12: 12360 | Q12: =P12/$O$1*O12 -> 5297.1429 | R12: =Q12*100% -> 5297.1429 | S12: 0 | T12: 0 | U12: 0 | V12: =ROUND(SUM(R12:U12),0) -> 5297 | W12: 0 | X12: 0 | Y12: =SUM(V12:X12) -> 5297 | Z12: =ROUND(SUM(R12:U12)-S12,0) -> 5297 | AA12: =ROUND(IF(Z12>15000,15000,Z12),0) -> 5297 | AB12: =ROUND(IF(Z12>15000,1800,Z12*12%),0) -> 636 | AC12: 0 | AD12: =ROUNDUP(IF(P12>21000,0,(Y12-X12)*0.75%),0) -> 40 | AE12: =ROUND(AB12/12%*8.33%,0) -> 441 | AF12: =+AB12-AE12 -> 195 | AG12: =IF(P12>21000,0,(Y12-X12)*3.25%) -> 172.1525 | AH12: 0 | AI12: 0 | AJ12: 0 | AK12: =IF((Y12-X12)>=20001,200,IF((Y12-X12)>=15001,150,0)) -> 0 | AL12: 0 | AM12: =AB12+AD12+AL12 -> 676 | AN12: =SUM(ROUND((Y12)-(AH12+AI12+AJ12+AK12+AM12),0),0) -> 4621
A13: =A12+1 -> 11 | B13: JAI-264 | C13: 44326 | E13: Anchor | F13: 50100419974035 | G13: HDFC0001635 | H13: 101693033121 | I13: OEQPS9295D | J13: 5217404380 | K13: 36137 | L13: Female | M13: Semi-skilled | N13: No | O13: =VLOOKUP(B13,'Anchor-Attendance'!$B$4:$BB$84,53,0) -> 0 | P13: 12360 | Q13: =P13/$O$1*O13 -> 0 | R13: =Q13*100% -> 0 | S13: 0 | T13: 0 | U13: 0 | V13: =ROUND(SUM(R13:U13),0) -> 0 | W13: 0 | X13: 0 | Y13: =SUM(V13:X13) -> 0 | Z13: =ROUND(SUM(R13:U13)-S13,0) -> 0 | AA13: =ROUND(IF(Z13>15000,15000,Z13),0) -> 0 | AB13: =ROUND(IF(Z13>15000,1800,Z13*12%),0) -> 0 | AC13: 0 | AD13: =ROUNDUP(IF(P13>21000,0,(Y13-X13)*0.75%),0) -> 0 | AE13: =ROUND(AB13/12%*8.33%,0) -> 0 | AF13: =+AB13-AE13 -> 0 | AG13: =IF(P13>21000,0,(Y13-X13)*3.25%) -> 0 | AH13: 0 | AI13: 0 | AJ13: 0 | AK13: =IF((Y13-X13)>=20001,200,IF((Y13-X13)>=15001,150,0)) -> 0 | AL13: 0 | AM13: =AB13+AD13+AL13 -> 0 | AN13: =SUM(ROUND((Y13)-(AH13+AI13+AJ13+AK13+AM13),0),0) -> 0
A14: =A13+1 -> 12 | B14: JAI-265 | C14: 44326 | E14: Anchor | F14: 50100419974686 | G14: HDFC0001635 | H14: 101693033676 | I14: OENPS6494M | J14: 5217396008 | K14: 37108 | L14: Female | M14: Semi-skilled | N14: No | O14: =VLOOKUP(B14,'Anchor-Attendance'!$B$4:$BB$84,53,0) -> 28 | P14: 12360 | Q14: =P14/$O$1*O14 -> 12360 | R14: =Q14*100% -> 12360 | S14: 0 | T14: 0 | U14: 0 | V14: =ROUND(SUM(R14:U14),0) -> 12360 | W14: 0 | X14: 0 | Y14: =SUM(V14:X14) -> 12360 | Z14: =ROUND(SUM(R14:U14)-S14,0) -> 12360 | AA14: =ROUND(IF(Z14>15000,15000,Z14),0) -> 12360 | AB14: =ROUND(IF(Z14>15000,1800,Z14*12%),0) -> 1483 | AC14: 0 | AD14: =ROUNDUP(IF(P14>21000,0,(Y14-X14)*0.75%),0) -> 93 | AE14: =ROUND(AB14/12%*8.33%,0) -> 1029 | AF14: =+AB14-AE14 -> 454 | AG14: =IF(P14>21000,0,(Y14-X14)*3.25%) -> 401.7 | AH14: 0 | AI14: 0 | AJ14: 0 | AK14: =IF((Y14-X14)>=20001,200,IF((Y14-X14)>=15001,150,0)) -> 0 | AL14: 0 | AM14: =AB14+AD14+AL14 -> 1576 | AN14: =SUM(ROUND((Y14)-(AH14+AI14+AJ14+AK14+AM14),0),0) -> 10784
A15: =A14+1 -> 13 | B15: JAI-268 | C15: 44326 | E15: Anchor | F15: 50100426462022 | G15: HDFC0000240 | H15: 101693034708 | I15: ODGPS5639G | J15: 5217395028 | K15: 34097 | L15: Female | M15: Semi-skilled | N15: No | O15: =VLOOKUP(B15,'Anchor-Attendance'!$B$4:$BB$84,53,0) -> 28 | P15: 12360 | Q15: =P15/$O$1*O15 -> 12360 | R15: =Q15*100% -> 12360 | S15: 0 | T15: 0 | U15: 0 | V15: =ROUND(SUM(R15:U15),0) -> 12360 | W15: 0 | X15: 0 | Y15: =SUM(V15:X15) -> 12360 | Z15: =ROUND(SUM(R15:U15)-S15,0) -> 12360 | AA15: =ROUND(IF(Z15>15000,15000,Z15),0) -> 12360 | AB15: =ROUND(IF(Z15>15000,1800,Z15*12%),0) -> 1483 | AC15: 0 | AD15: =ROUNDUP(IF(P15>21000,0,(Y15-X15)*0.75%),0) -> 93 | AE15: =ROUND(AB15/12%*8.33%,0) -> 1029 | AF15: =+AB15-AE15 -> 454 | AG15: =IF(P15>21000,0,(Y15-X15)*3.25%) -> 401.7 | AH15: 0 | AI15: 0 | AJ15: 0 | AK15: =IF((Y15-X15)>=20001,200,IF((Y15-X15)>=15001,150,0)) -> 0 | AL15: 0 | AM15: =AB15+AD15+AL15 -> 1576 | AN15: =SUM(ROUND((Y15)-(AH15+AI15+AJ15+AK15+AM15),0),0) -> 10784
A16: =A15+1 -> 14 | B16: JAI-270 | C16: 44326 | E16: Anchor | F16: 50100419974009 | G16: HDFC0001635 | H16: 101693033703 | I16: NFXPS9700G | J16: 5217396164 | K16: 36748 | L16: Female | M16: Semi-skilled | N16: No | O16: =VLOOKUP(B16,'Anchor-Attendance'!$B$4:$BB$84,53,0) -> 28 | P16: 12360 | Q16: =P16/$O$1*O16 -> 12360 | R16: =Q16*100% -> 12360 | S16: 0 | T16: 0 | U16: 0 | V16: =ROUND(SUM(R16:U16),0) -> 12360 | W16: 0 | X16: 0 | Y16: =SUM(V16:X16) -> 12360 | Z16: =ROUND(SUM(R16:U16)-S16,0) -> 12360 | AA16: =ROUND(IF(Z16>15000,15000,Z16),0) -> 12360 | AB16: =ROUND(IF(Z16>15000,1800,Z16*12%),0) -> 1483 | AC16: 0 | AD16: =ROUNDUP(IF(P16>21000,0,(Y16-X16)*0.75%),0) -> 93 | AE16: =ROUND(AB16/12%*8.33%,0) -> 1029 | AF16: =+AB16-AE16 -> 454 | AG16: =IF(P16>21000,0,(Y16-X16)*3.25%) -> 401.7 | AH16: 0 | AI16: 0 | AJ16: 0 | AK16: =IF((Y16-X16)>=20001,200,IF((Y16-X16)>=15001,150,0)) -> 0 | AL16: 0 | AM16: =AB16+AD16+AL16 -> 1576 | AN16: =SUM(ROUND((Y16)-(AH16+AI16+AJ16+AK16+AM16),0),0) -> 10784
A17: =A16+1 -> 15 | B17: JAI-275 | C17: 44342 | E17: Anchor | F17: 50100422491859 | G17: HDFC0000472 | H17: 101693033761 | I17: FCWPD2945A | J17: 5217417695 | K17: 34570 | L17: Female | M17: Semi-skilled | N17: =VLOOKUP(B17,'Anchor-Attendance'!$B$4:$K$84,10,0) -> 46059 | O17: =VLOOKUP(B17,'Anchor-Attendance'!$B$4:$BB$84,53,0) -> 5 | P17: 12360 | Q17: =P17/$O$1*O17 -> 2207.1429 | R17: =Q17*100% -> 2207.1429 | S17: 0 | T17: 0 | U17: 0 | V17: =ROUND(SUM(R17:U17),0) -> 2207 | W17: 0 | X17: =AR17 -> 35654 | Y17: =SUM(V17:X17) -> 37861 | Z17: =ROUND(SUM(R17:U17)-S17,0) -> 2207 | AA17: =ROUND(IF(Z17>15000,15000,Z17),0) -> 2207 | AB17: =ROUND(IF(Z17>15000,1800,Z17*12%),0) -> 265 | AC17: 0 | AD17: =ROUNDUP(IF(P17>21000,0,(Y17-X17)*0.75%),0) -> 17 | AE17: =ROUND(AB17/12%*8.33%,0) -> 184 | AF17: =+AB17-AE17 -> 81 | AG17: =IF(P17>21000,0,(Y17-X17)*3.25%) -> 71.7275 | AH17: 0 | AI17: 0 | AJ17: 0 | AK17: =IF((Y17-X17)>=20001,200,IF((Y17-X17)>=15001,150,0)) -> 0 | AL17: 0 | AM17: =AB17+AD17+AL17 -> 282 | AN17: =SUM(ROUND((Y17)-(AH17+AI17+AJ17+AK17+AM17),0),0) -> 37579 | AP17: =ROUND((N17-C17)/365,0) -> 5 | AQ17: =P17 -> 12360 | AR17: =ROUND(AQ17*15/26*AP17,0) -> 35654
A18: =A17+1 -> 16 | B18: JAI-277 | C18: 44342 | E18: Anchor | F18: 50100428958172 | G18: HDFC0002352 | H18: 101693032161 | I18: AFFPE6498C | J18: 5217418388 | K18: 36126 | L18: Female | M18: Semi-skilled | N18: =VLOOKUP(B18,'Anchor-Attendance'!$B$4:$K$84,10,0) -> 46072 | O18: =VLOOKUP(B18,'Anchor-Attendance'!$B$4:$BB$84,53,0) -> 19 | P18: 12360 | Q18: =P18/$O$1*O18 -> 8387.1429 | R18: =Q18*100% -> 8387.1429 | S18: 0 | T18: 0 | U18: 0 | V18: =ROUND(SUM(R18:U18),0) -> 8387 | W18: =12360-V18 -> 3973 | X18: =AR18 -> 35654 | Y18: =SUM(V18:X18) -> 48014 | Z18: =ROUND(SUM(R18:U18)-S18,0) -> 8387 | AA18: =ROUND(IF(Z18>15000,15000,Z18),0) -> 8387 | AB18: =ROUND(IF(Z18>15000,1800,Z18*12%),0) -> 1006 | AC18: 0 | AD18: =ROUNDUP(IF(P18>21000,0,(Y18-X18)*0.75%),0) -> 93 | AE18: =ROUND(AB18/12%*8.33%,0) -> 698 | AF18: =+AB18-AE18 -> 308 | AG18: =IF(P18>21000,0,(Y18-X18)*3.25%) -> 401.7 | AH18: 0 | AI18: 0 | AJ18: 0 | AK18: =IF((Y18-X18)>=20001,200,IF((Y18-X18)>=15001,150,0)) -> 0 | AL18: 0 | AM18: =AB18+AD18+AL18 -> 1099 | AN18: =SUM(ROUND((Y18)-(AH18+AI18+AJ18+AK18+AM18),0),0) -> 46915 | AO18: Full month salary to be paid | AP18: =ROUND((N18-C18)/365,0) -> 5 | AQ18: =P18 -> 12360 | AR18: =ROUND(AQ18*15/26*AP18,0) -> 35654
A19: =A18+1 -> 17 | B19: JAI-301 | C19: 44426 | E19: Anchor | F19: 50100453957155 | G19: HDFC0001635 | H19: 101722628512 | I19: EFXPA7539L | J19: 5217668558 | K19: 36765 | L19: Female | M19: Semi-skilled | N19: No | O19: =VLOOKUP(B19,'Anchor-Attendance'!$B$4:$BB$84,53,0) -> 26 | P19: 12360 | Q19: =P19/$O$1*O19 -> 11477.143 | R19: =Q19*100% -> 11477.143 | S19: 0 | T19: 0 | U19: 0 | V19: =ROUND(SUM(R19:U19),0) -> 11477 | W19: 0 | X19: 0 | Y19: =SUM(V19:X19) -> 11477 | Z19: =ROUND(SUM(R19:U19)-S19,0) -> 11477 | AA19: =ROUND(IF(Z19>15000,15000,Z19),0) -> 11477 | AB19: =ROUND(IF(Z19>15000,1800,Z19*12%),0) -> 1377 | AC19: 0 | AD19: =ROUNDUP(IF(P19>21000,0,(Y19-X19)*0.75%),0) -> 87 | AE19: =ROUND(AB19/12%*8.33%,0) -> 956 | AF19: =+AB19-AE19 -> 421 | AG19: =IF(P19>21000,0,(Y19-X19)*3.25%) -> 373.0025 | AH19: 0 | AI19: 0 | AJ19: 0 | AK19: =IF((Y19-X19)>=20001,200,IF((Y19-X19)>=15001,150,0)) -> 0 | AL19: 0 | AM19: =AB19+AD19+AL19 -> 1464 | AN19: =SUM(ROUND((Y19)-(AH19+AI19+AJ19+AK19+AM19),0),0) -> 10013
A20: =A19+1 -> 18 | B20: JAI-310 | C20: 44426 | E20: Anchor | F20: 50100452150045 | G20: HDFC0003916 | H20: 101727707088 | I20: DKAPR8305G | J20: 5217663143 | K20: 34561 | L20: Female | M20: Semi-skilled | N20: No | O20: =VLOOKUP(B20,'Anchor-Attendance'!$B$4:$BB$84,53,0) -> 28 | P20: 12360 | Q20: =P20/$O$1*O20 -> 12360 | R20: =Q20*100% -> 12360 | S20: 0 | T20: 0 | U20: 0 | V20: =ROUND(SUM(R20:U20),0) -> 12360 | W20: 0 | X20: 0 | Y20: =SUM(V20:X20) -> 12360 | Z20: =ROUND(SUM(R20:U20)-S20,0) -> 12360 | AA20: =ROUND(IF(Z20>15000,15000,Z20),0) -> 12360 | AB20: =ROUND(IF(Z20>15000,1800,Z20*12%),0) -> 1483 | AC20: 0 | AD20: =ROUNDUP(IF(P20>21000,0,(Y20-X20)*0.75%),0) -> 93 | AE20: =ROUND(AB20/12%*8.33%,0) -> 1029 | AF20: =+AB20-AE20 -> 454 | AG20: =IF(P20>21000,0,(Y20-X20)*3.25%) -> 401.7 | AH20: 0 | AI20: 0 | AJ20: 0 | AK20: =IF((Y20-X20)>=20001,200,IF((Y20-X20)>=15001,150,0)) -> 0 | AL20: 0 | AM20: =AB20+AD20+AL20 -> 1576 | AN20: =SUM(ROUND((Y20)-(AH20+AI20+AJ20+AK20+AM20),0),0) -> 10784
A21: =A20+1 -> 19 | B21: JAI-314 | C21: 44426 | E21: Anchor | F21: 50100453956929 | G21: HDFC0001635 | H21: 101727707116 | I21: KZOPK0189K | J21: 5217664617 | K21: 36387 | L21: Female | M21: Semi-skilled | N21: No | O21: =VLOOKUP(B21,'Anchor-Attendance'!$B$4:$BB$84,53,0) -> 28 | P21: 12360 | Q21: =P21/$O$1*O21 -> 12360 | R21: =Q21*100% -> 12360 | S21: 0 | T21: 0 | U21: 0 | V21: =ROUND(SUM(R21:U21),0) -> 12360 | W21: 0 | X21: 0 | Y21: =SUM(V21:X21) -> 12360 | Z21: =ROUND(SUM(R21:U21)-S21,0) -> 12360 | AA21: =ROUND(IF(Z21>15000,15000,Z21),0) -> 12360 | AB21: =ROUND(IF(Z21>15000,1800,Z21*12%),0) -> 1483 | AC21: 0 | AD21: =ROUNDUP(IF(P21>21000,0,(Y21-X21)*0.75%),0) -> 93 | AE21: =ROUND(AB21/12%*8.33%,0) -> 1029 | AF21: =+AB21-AE21 -> 454 | AG21: =IF(P21>21000,0,(Y21-X21)*3.25%) -> 401.7 | AH21: 0 | AI21: 0 | AJ21: 0 | AK21: =IF((Y21-X21)>=20001,200,IF((Y21-X21)>=15001,150,0)) -> 0 | AL21: 0 | AM21: =AB21+AD21+AL21 -> 1576 | AN21: =SUM(ROUND((Y21)-(AH21+AI21+AJ21+AK21+AM21),0),0) -> 10784
A22: =A21+1 -> 20 | B22: JAI-321 | C22: 44426 | E22: Anchor | F22: 50100446212114 | G22: HDFC0001635 | H22: 101727707144 | I22: IUUPK5573G | J22: 5217664816 | K22: 35595 | L22: Female | M22: Semi-skilled | N22: =VLOOKUP(B22,'Anchor-Attendance'!$B$4:$K$84,10,0) -> 46059 | O22: =VLOOKUP(B22,'Anchor-Attendance'!$B$4:$BB$84,53,0) -> 6 | P22: 12360 | Q22: =P22/$O$1*O22 -> 2648.5714 | R22: =Q22*100% -> 2648.5714 | S22: 0 | T22: 0 | U22: 0 | V22: =ROUND(SUM(R22:U22),0) -> 2649 | W22: 0 | X22: =AR22 -> 0 | Y22: =SUM(V22:X22) -> 2649 | Z22: =ROUND(SUM(R22:U22)-S22,0) -> 2649 | AA22: =ROUND(IF(Z22>15000,15000,Z22),0) -> 2649 | AB22: =ROUND(IF(Z22>15000,1800,Z22*12%),0) -> 318 | AC22: 0 | AD22: =ROUNDUP(IF(P22>21000,0,(Y22-X22)*0.75%),0) -> 20 | AE22: =ROUND(AB22/12%*8.33%,0) -> 221 | AF22: =+AB22-AE22 -> 97 | AG22: =IF(P22>21000,0,(Y22-X22)*3.25%) -> 86.0925 | AH22: 0 | AI22: 0 | AJ22: 0 | AK22: =IF((Y22-X22)>=20001,200,IF((Y22-X22)>=15001,150,0)) -> 0 | AL22: 0 | AM22: =AB22+AD22+AL22 -> 338 | AN22: =SUM(ROUND((Y22)-(AH22+AI22+AJ22+AK22+AM22),0),0) -> 2311 | AP22: =ROUND((N22-C22)/365,0) -> 4
A23: =A22+1 -> 21 | B23: JAI-333 | C23: 44426 | E23: Anchor | F23: 50100453956892 | G23: HDFC0001635 | H23: 101728745071 | I23: NADPS4388P | J23: 5217668709 | K23: 35934 | L23: Female | M23: Semi-skilled | N23: No | O23: =VLOOKUP(B23,'Anchor-Attendance'!$B$4:$BB$84,53,0) -> 28 | P23: 12360 | Q23: =P23/$O$1*O23 -> 12360 | R23: =Q23*100% -> 12360 | S23: 0 | T23: 0 | U23: 0 | V23: =ROUND(SUM(R23:U23),0) -> 12360 | W23: 0 | X23: 0 | Y23: =SUM(V23:X23) -> 12360 | Z23: =ROUND(SUM(R23:U23)-S23,0) -> 12360 | AA23: =ROUND(IF(Z23>15000,15000,Z23),0) -> 12360 | AB23: =ROUND(IF(Z23>15000,1800,Z23*12%),0) -> 1483 | AC23: 0 | AD23: =ROUNDUP(IF(P23>21000,0,(Y23-X23)*0.75%),0) -> 93 | AE23: =ROUND(AB23/12%*8.33%,0) -> 1029 | AF23: =+AB23-AE23 -> 454 | AG23: =IF(P23>21000,0,(Y23-X23)*3.25%) -> 401.7 | AH23: 0 | AI23: 0 | AJ23: 0 | AK23: =IF((Y23-X23)>=20001,200,IF((Y23-X23)>=15001,150,0)) -> 0 | AL23: 0 | AM23: =AB23+AD23+AL23 -> 1576 | AN23: =SUM(ROUND((Y23)-(AH23+AI23+AJ23+AK23+AM23),0),0) -> 10784
A24: =A23+1 -> 22 | B24: JAI-338 | C24: 44431 | E24: Anchor | F24: 50100453956994 | G24: HDFC0001635 | H24: 101727707349 | I24: FWMPB6525E | J24: 5217671547 | K24: 38047 | L24: Female | M24: Semi-skilled | N24: =VLOOKUP(B24,'Anchor-Attendance'!$B$4:$K$84,10,0) -> 46073 | O24: =VLOOKUP(B24,'Anchor-Attendance'!$B$4:$BB$84,53,0) -> 20 | P24: 12360 | Q24: =P24/$O$1*O24 -> 8828.5714 | R24: =Q24*100% -> 8828.5714 | S24: 0 | T24: 0 | U24: 0 | V24: =ROUND(SUM(R24:U24),0) -> 8829 | W24: =12360-V24 -> 3531 | X24: =AR24 -> 0 | Y24: =SUM(V24:X24) -> 12360 | Z24: =ROUND(SUM(R24:U24)-S24,0) -> 8829 | AA24: =ROUND(IF(Z24>15000,15000,Z24),0) -> 8829 | AB24: =ROUND(IF(Z24>15000,1800,Z24*12%),0) -> 1059 | AC24: 0 | AD24: =ROUNDUP(IF(P24>21000,0,(Y24-X24)*0.75%),0) -> 93 | AE24: =ROUND(AB24/12%*8.33%,0) -> 735 | AF24: =+AB24-AE24 -> 324 | AG24: =IF(P24>21000,0,(Y24-X24)*3.25%) -> 401.7 | AH24: 0 | AI24: 0 | AJ24: 0 | AK24: =IF((Y24-X24)>=20001,200,IF((Y24-X24)>=15001,150,0)) -> 0 | AL24: 0 | AM24: =AB24+AD24+AL24 -> 1152 | AN24: =SUM(ROUND((Y24)-(AH24+AI24+AJ24+AK24+AM24),0),0) -> 11208 | AO24: Full month salary to be paid | AP24: =ROUND((N24-C24)/365,0) -> 4
A25: =A24+1 -> 23 | B25: JAI-342 | C25: 44431 | E25: Anchor | F25: 50100453957027 | G25: HDFC0003916 | H25: 101721443487 | I25: GKOPP8991P | J25: 5217671469 | K25: 34898 | L25: Female | M25: Semi-skilled | N25: No | O25: =VLOOKUP(B25,'Anchor-Attendance'!$B$4:$BB$84,53,0) -> 28 | P25: 12360 | Q25: =P25/$O$1*O25 -> 12360 | R25: =Q25*100% -> 12360 | S25: 0 | T25: 0 | U25: 0 | V25: =ROUND(SUM(R25:U25),0) -> 12360 | W25: 0 | X25: 0 | Y25: =SUM(V25:X25) -> 12360 | Z25: =ROUND(SUM(R25:U25)-S25,0) -> 12360 | AA25: =ROUND(IF(Z25>15000,15000,Z25),0) -> 12360 | AB25: =ROUND(IF(Z25>15000,1800,Z25*12%),0) -> 1483 | AC25: 0 | AD25: =ROUNDUP(IF(P25>21000,0,(Y25-X25)*0.75%),0) -> 93 | AE25: =ROUND(AB25/12%*8.33%,0) -> 1029 | AF25: =+AB25-AE25 -> 454 | AG25: =IF(P25>21000,0,(Y25-X25)*3.25%) -> 401.7 | AH25: 0 | AI25: 0 | AJ25: 0 | AK25: =IF((Y25-X25)>=20001,200,IF((Y25-X25)>=15001,150,0)) -> 0 | AL25: 0 | AM25: =AB25+AD25+AL25 -> 1576 | AN25: =SUM(ROUND((Y25)-(AH25+AI25+AJ25+AK25+AM25),0),0) -> 10784
A26: =A25+1 -> 24 | B26: JAI-377 | C26: 44522 | E26: Anchor | F26: 50100453958616 | G26: HDFC0001635 | H26: 101758025155 | I26: CPEPN3528R | J26: 5217964768 | K26: 36557 | L26: Female | M26: Semi-skilled | N26: No | O26: =VLOOKUP(B26,'Anchor-Attendance'!$B$4:$BB$84,53,0) -> 28 | P26: 12360 | Q26: =P26/$O$1*O26 -> 12360 | R26: =Q26*100% -> 12360 | S26: 0 | T26: 0 | U26: 0 | V26: =ROUND(SUM(R26:U26),0) -> 12360 | W26: 0 | X26: 0 | Y26: =SUM(V26:X26) -> 12360 | Z26: =ROUND(SUM(R26:U26)-S26,0) -> 12360 | AA26: =ROUND(IF(Z26>15000,15000,Z26),0) -> 12360 | AB26: =ROUND(IF(Z26>15000,1800,Z26*12%),0) -> 1483 | AC26: 0 | AD26: =ROUNDUP(IF(P26>21000,0,(Y26-X26)*0.75%),0) -> 93 | AE26: =ROUND(AB26/12%*8.33%,0) -> 1029 | AF26: =+AB26-AE26 -> 454 | AG26: =IF(P26>21000,0,(Y26-X26)*3.25%) -> 401.7 | AH26: 0 | AI26: 0 | AJ26: 0 | AK26: =IF((Y26-X26)>=20001,200,IF((Y26-X26)>=15001,150,0)) -> 0 | AL26: 0 | AM26: =AB26+AD26+AL26 -> 1576 | AN26: =SUM(ROUND((Y26)-(AH26+AI26+AJ26+AK26+AM26),0),0) -> 10784
A27: =A26+1 -> 25 | B27: JAI-382 | C27: 44522 | E27: Anchor | F27: 50100453957461 | G27: HDFC0001635 | H27: 101758030367 | I27: FMRPR4408H | J27: 5217967622 | K27: 36525 | L27: Female | M27: Semi-skilled | N27: No | O27: =VLOOKUP(B27,'Anchor-Attendance'!$B$4:$BB$84,53,0) -> 28 | P27: 12360 | Q27: =P27/$O$1*O27 -> 12360 | R27: =Q27*100% -> 12360 | S27: 0 | T27: 0 | U27: 0 | V27: =ROUND(SUM(R27:U27),0) -> 12360 | W27: 0 | X27: 0 | Y27: =SUM(V27:X27) -> 12360 | Z27: =ROUND(SUM(R27:U27)-S27,0) -> 12360 | AA27: =ROUND(IF(Z27>15000,15000,Z27),0) -> 12360 | AB27: =ROUND(IF(Z27>15000,1800,Z27*12%),0) -> 1483 | AC27: 0 | AD27: =ROUNDUP(IF(P27>21000,0,(Y27-X27)*0.75%),0) -> 93 | AE27: =ROUND(AB27/12%*8.33%,0) -> 1029 | AF27: =+AB27-AE27 -> 454 | AG27: =IF(P27>21000,0,(Y27-X27)*3.25%) -> 401.7 | AH27: 0 | AI27: 0 | AJ27: 0 | AK27: =IF((Y27-X27)>=20001,200,IF((Y27-X27)>=15001,150,0)) -> 0 | AL27: 0 | AM27: =AB27+AD27+AL27 -> 1576 | AN27: =SUM(ROUND((Y27)-(AH27+AI27+AJ27+AK27+AM27),0),0) -> 10784
A28: =A27+1 -> 26 | B28: JAI-383 | C28: 44522 | E28: Anchor | F28: 50100453958441 | G28: HDFC0001635 | H28: 101758031212 | I28: CDNPT0680B | J28: 5217968917 | K28: 35108 | L28: Female | M28: Semi-skilled | N28: No | O28: =VLOOKUP(B28,'Anchor-Attendance'!$B$4:$BB$84,53,0) -> 28 | P28: 12360 | Q28: =P28/$O$1*O28 -> 12360 | R28: =Q28*100% -> 12360 | S28: 0 | T28: 0 | U28: 0 | V28: =ROUND(SUM(R28:U28),0) -> 12360 | W28: 0 | X28: 0 | Y28: =SUM(V28:X28) -> 12360 | Z28: =ROUND(SUM(R28:U28)-S28,0) -> 12360 | AA28: =ROUND(IF(Z28>15000,15000,Z28),0) -> 12360 | AB28: =ROUND(IF(Z28>15000,1800,Z28*12%),0) -> 1483 | AC28: 0 | AD28: =ROUNDUP(IF(P28>21000,0,(Y28-X28)*0.75%),0) -> 93 | AE28: =ROUND(AB28/12%*8.33%,0) -> 1029 | AF28: =+AB28-AE28 -> 454 | AG28: =IF(P28>21000,0,(Y28-X28)*3.25%) -> 401.7 | AH28: 0 | AI28: 0 | AJ28: 0 | AK28: =IF((Y28-X28)>=20001,200,IF((Y28-X28)>=15001,150,0)) -> 0 | AL28: 0 | AM28: =AB28+AD28+AL28 -> 1576 | AN28: =SUM(ROUND((Y28)-(AH28+AI28+AJ28+AK28+AM28),0),0) -> 10784
A29: =A28+1 -> 27 | B29: JAI-394 | C29: 44522 | E29: Anchor | F29: 50100453957613 | G29: HDFC0001635 | H29: 101758038715 | I29: NPKPS3503A | J29: 5217971852 | K29: 36481 | L29: Female | M29: Semi-skilled | N29: No | O29: =VLOOKUP(B29,'Anchor-Attendance'!$B$4:$BB$84,53,0) -> 28 | P29: 12360 | Q29: =P29/$O$1*O29 -> 12360 | R29: =Q29*100% -> 12360 | S29: 0 | T29: 0 | U29: 0 | V29: =ROUND(SUM(R29:U29),0) -> 12360 | W29: 0 | X29: 0 | Y29: =SUM(V29:X29) -> 12360 | Z29: =ROUND(SUM(R29:U29)-S29,0) -> 12360 | AA29: =ROUND(IF(Z29>15000,15000,Z29),0) -> 12360 | AB29: =ROUND(IF(Z29>15000,1800,Z29*12%),0) -> 1483 | AC29: 0 | AD29: =ROUNDUP(IF(P29>21000,0,(Y29-X29)*0.75%),0) -> 93 | AE29: =ROUND(AB29/12%*8.33%,0) -> 1029 | AF29: =+AB29-AE29 -> 454 | AG29: =IF(P29>21000,0,(Y29-X29)*3.25%) -> 401.7 | AH29: 0 | AI29: 0 | AJ29: 0 | AK29: =IF((Y29-X29)>=20001,200,IF((Y29-X29)>=15001,150,0)) -> 0 | AL29: 0 | AM29: =AB29+AD29+AL29 -> 1576 | AN29: =SUM(ROUND((Y29)-(AH29+AI29+AJ29+AK29+AM29),0),0) -> 10784
A30: =A29+1 -> 28 | B30: JAI-470 | C30: 44845 | E30: Anchor | F30: 50100515744043 | G30: HDFC0009087 | H30: 101877719011 | I30: DNJPG4658D | J30: 5218492977 | K30: 36958 | L30: Female | M30: Semi-skilled | N30: =VLOOKUP(B30,'Anchor-Attendance'!$B$4:$K$84,10,0) -> 46076 | O30: =VLOOKUP(B30,'Anchor-Attendance'!$B$4:$BB$84,53,0) -> 13.5 | P30: 12360 | Q30: =P30/$O$1*O30 -> 5959.2857 | R30: =Q30*100% -> 5959.2857 | S30: =Q30*0% -> 0 | T30: 0 | U30: 0 | V30: =ROUND(SUM(R30:U30),0) -> 5959 | W30: =12360-V30 -> 6401 | X30: =AR30 -> 0 | Y30: =SUM(V30:X30) -> 12360 | Z30: =ROUND(SUM(R30:U30)-S30,0) -> 5959 | AA30: =ROUND(IF(Z30>15000,15000,Z30),0) -> 5959 | AB30: =ROUND(IF(Z30>15000,1800,Z30*12%),0) -> 715 | AC30: 0 | AD30: =ROUNDUP(IF(P30>21000,0,(Y30-X30)*0.75%),0) -> 93 | AE30: =ROUND(AB30/12%*8.33%,0) -> 496 | AF30: =+AB30-AE30 -> 219 | AG30: =IF(P30>21000,0,(Y30-X30)*3.25%) -> 401.7 | AH30: 0 | AI30: 0 | AJ30: 0 | AK30: =IF((Y30-X30)>=20001,200,IF((Y30-X30)>=15001,150,0)) -> 0 | AL30: 0 | AM30: =AB30+AD30+AL30 -> 808 | AN30: =SUM(ROUND((Y30)-(AH30+AI30+AJ30+AK30+AM30),0),0) -> 11552 | AO30: Full month salary to be paid | AP30: =ROUND((N30-C30)/365,0) -> 3
A31: =A30+1 -> 29 | B31: JAI-502 | C31: 44845 | E31: Anchor | F31: 50100515744501 | G31: HDFC0009087 | H31: 101877718954 | I31: KZLPS3922P | J31: 5218511775 | K31: 35316 | L31: Female | M31: Semi-skilled | N31: No | O31: =VLOOKUP(B31,'Anchor-Attendance'!$B$4:$BB$84,53,0) -> 28 | P31: 12360 | Q31: =P31/$O$1*O31 -> 12360 | R31: =Q31*100% -> 12360 | S31: 0 | T31: 0 | U31: 0 | V31: =ROUND(SUM(R31:U31),0) -> 12360 | W31: 0 | X31: 0 | Y31: =SUM(V31:X31) -> 12360 | Z31: =ROUND(SUM(R31:U31)-S31,0) -> 12360 | AA31: =ROUND(IF(Z31>15000,15000,Z31),0) -> 12360 | AB31: =ROUND(IF(Z31>15000,1800,Z31*12%),0) -> 1483 | AC31: 0 | AD31: =ROUNDUP(IF(P31>21000,0,(Y31-X31)*0.75%),0) -> 93 | AE31: =ROUND(AB31/12%*8.33%,0) -> 1029 | AF31: =+AB31-AE31 -> 454 | AG31: =IF(P31>21000,0,(Y31-X31)*3.25%) -> 401.7 | AH31: 0 | AI31: 0 | AJ31: 0 | AK31: =IF((Y31-X31)>=20001,200,IF((Y31-X31)>=15001,150,0)) -> 0 | AL31: 0 | AM31: =AB31+AD31+AL31 -> 1576 | AN31: =SUM(ROUND((Y31)-(AH31+AI31+AJ31+AK31+AM31),0),0) -> 10784
A32: =A31+1 -> 30 | B32: JAI-725 | C32: 44909 | E32: Anchor | F32: 50100593151791 | G32: HDFC0001635 | H32: 101907229534 | I32: HFLPP7604N | J32: 5219228476 | K32: 36246 | L32: Female | M32: Semi-skilled | N32: No | O32: =VLOOKUP(B32,'Anchor-Attendance'!$B$4:$BB$84,53,0) -> 28 | P32: 12360 | Q32: =P32/$O$1*O32 -> 12360 | R32: =Q32*100% -> 12360 | S32: 0 | T32: 0 | U32: 0 | V32: =ROUND(SUM(R32:U32),0) -> 12360 | W32: 0 | X32: 0 | Y32: =SUM(V32:X32) -> 12360 | Z32: =ROUND(SUM(R32:U32)-S32,0) -> 12360 | AA32: =ROUND(IF(Z32>15000,15000,Z32),0) -> 12360 | AB32: =ROUND(IF(Z32>15000,1800,Z32*12%),0) -> 1483 | AC32: 0 | AD32: =ROUNDUP(IF(P32>21000,0,(Y32-X32)*0.75%),0) -> 93 | AE32: =ROUND(AB32/12%*8.33%,0) -> 1029 | AF32: =+AB32-AE32 -> 454 | AG32: =IF(P32>21000,0,(Y32-X32)*3.25%) -> 401.7 | AH32: 0 | AI32: 0 | AJ32: 0 | AK32: =IF((Y32-X32)>=20001,200,IF((Y32-X32)>=15001,150,0)) -> 0 | AL32: 0 | AM32: =AB32+AD32+AL32 -> 1576 | AN32: =SUM(ROUND((Y32)-(AH32+AI32+AJ32+AK32+AM32),0),0) -> 10784
A33: =A32+1 -> 31 | B33: JAI-747 | C33: 44909 | E33: AMIA | F33: 50100588150401 | G33: HDFC0001635 | H33: 101907229552 | I33: BIGPY4450F | J33: 5219233496 | K33: 37765 | L33: Female | M33: Semi-skilled | N33: No | O33: =VLOOKUP(B33,'Anchor-Attendance'!$B$4:$BB$84,53,0) -> 28 | P33: 17000 | Q33: =P33/$O$1*O33 -> 17000 | R33: =Q33*90% -> 15300 | S33: =Q33*10% -> 1700 | T33: 0 | U33: 0 | V33: =ROUND(SUM(R33:U33),0) -> 17000 | W33: 0 | X33: 0 | Y33: =SUM(V33:X33) -> 17000 | Z33: =ROUND(SUM(R33:U33)-S33,0) -> 15300 | AA33: =ROUND(IF(Z33>15000,15000,Z33),0) -> 15000 | AB33: =ROUND(IF(Z33>15000,1800,Z33*12%),0) -> 1800 | AC33: 0 | AD33: =ROUNDUP(IF(P33>21000,0,(Y33-X33)*0.75%),0) -> 128 | AE33: =ROUND(AB33/12%*8.33%,0) -> 1250 | AF33: =+AB33-AE33 -> 550 | AG33: =IF(P33>21000,0,(Y33-X33)*3.25%) -> 552.5 | AH33: 0 | AI33: 0 | AJ33: 0 | AK33: =IF((Y33-X33)>=20001,200,IF((Y33-X33)>=15001,150,0)) -> 150 | AL33: 0 | AM33: =AB33+AD33+AL33 -> 1928 | AN33: =SUM(ROUND((Y33)-(AH33+AI33+AJ33+AK33+AM33),0),0) -> 14922
A34: =A33+1 -> 32 | B34: JAI-860 | C34: 45033 | E34: AMIA | F34: 50100593127712 | G34: HDFC0001635 | H34: 101926502058 | I34: EWPPA0721P | J34: 5219251248 | K34: 37795 | L34: Female | M34: Semi-skilled | N34: No | O34: =VLOOKUP(B34,'Anchor-Attendance'!$B$4:$BB$84,53,0) -> 28 | P34: 17000 | Q34: =P34/$O$1*O34 -> 17000 | R34: =Q34*90% -> 15300 | S34: =Q34*10% -> 1700 | T34: 0 | U34: 0 | V34: =ROUND(SUM(R34:U34),0) -> 17000 | W34: 0 | X34: 0 | Y34: =SUM(V34:X34) -> 17000 | Z34: =ROUND(SUM(R34:U34)-S34,0) -> 15300 | AA34: =ROUND(IF(Z34>15000,15000,Z34),0) -> 15000 | AB34: =ROUND(IF(Z34>15000,1800,Z34*12%),0) -> 1800 | AC34: 0 | AD34: =ROUNDUP(IF(P34>21000,0,(Y34-X34)*0.75%),0) -> 128 | AE34: =ROUND(AB34/12%*8.33%,0) -> 1250 | AF34: =+AB34-AE34 -> 550 | AG34: =IF(P34>21000,0,(Y34-X34)*3.25%) -> 552.5 | AH34: 0 | AI34: 0 | AJ34: 0 | AK34: =IF((Y34-X34)>=20001,200,IF((Y34-X34)>=15001,150,0)) -> 150 | AL34: 0 | AM34: =AB34+AD34+AL34 -> 1928 | AN34: =SUM(ROUND((Y34)-(AH34+AI34+AJ34+AK34+AM34),0),0) -> 14922
A35: =A34+1 -> 33 | B35: JAI-1038 | C35: 45033 | E35: Anchor | F35: 50100594492073 | G35: HDFC0009087 | H35: 101916216840 | I35: QMTPS7428R | J35: 5219301318 | K35: 37261 | L35: Female | M35: Semi-skilled | N35: No | O35: =VLOOKUP(B35,'Anchor-Attendance'!$B$4:$BB$84,53,0) -> 28 | P35: 12360 | Q35: =P35/$O$1*O35 -> 12360 | R35: =Q35*100% -> 12360 | S35: 0 | T35: 0 | U35: 0 | V35: =ROUND(SUM(R35:U35),0) -> 12360 | W35: 0 | X35: 0 | Y35: =SUM(V35:X35) -> 12360 | Z35: =ROUND(SUM(R35:U35)-S35,0) -> 12360 | AA35: =ROUND(IF(Z35>15000,15000,Z35),0) -> 12360 | AB35: =ROUND(IF(Z35>15000,1800,Z35*12%),0) -> 1483 | AC35: 0 | AD35: =ROUNDUP(IF(P35>21000,0,(Y35-X35)*0.75%),0) -> 93 | AE35: =ROUND(AB35/12%*8.33%,0) -> 1029 | AF35: =+AB35-AE35 -> 454 | AG35: =IF(P35>21000,0,(Y35-X35)*3.25%) -> 401.7 | AH35: 0 | AI35: 0 | AJ35: 0 | AK35: =IF((Y35-X35)>=20001,200,IF((Y35-X35)>=15001,150,0)) -> 0 | AL35: 0 | AM35: =AB35+AD35+AL35 -> 1576 | AN35: =SUM(ROUND((Y35)-(AH35+AI35+AJ35+AK35+AM35),0),0) -> 10784
A36: =A35+1 -> 34 | B36: JAI-1121 | C36: 45086 | E36: Anchor | F36: 50100662377172 | G36: HDFC0009087 | H36: 101970000680 | I36: IGSPM9947Q | J36: 5219753348 | K36: 37735 | L36: Female | M36: Semi-skilled | N36: No | O36: =VLOOKUP(B36,'Anchor-Attendance'!$B$4:$BB$84,53,0) -> 28 | P36: 12360 | Q36: =P36/$O$1*O36 -> 12360 | R36: =Q36*100% -> 12360 | S36: 0 | T36: 0 | U36: 0 | V36: =ROUND(SUM(R36:U36),0) -> 12360 | W36: 0 | X36: 0 | Y36: =SUM(V36:X36) -> 12360 | Z36: =ROUND(SUM(R36:U36)-S36,0) -> 12360 | AA36: =ROUND(IF(Z36>15000,15000,Z36),0) -> 12360 | AB36: =ROUND(IF(Z36>15000,1800,Z36*12%),0) -> 1483 | AC36: 0 | AD36: =ROUNDUP(IF(P36>21000,0,(Y36-X36)*0.75%),0) -> 93 | AE36: =ROUND(AB36/12%*8.33%,0) -> 1029 | AF36: =+AB36-AE36 -> 454 | AG36: =IF(P36>21000,0,(Y36-X36)*3.25%) -> 401.7 | AH36: 0 | AI36: 0 | AJ36: 0 | AK36: =IF((Y36-X36)>=20001,200,IF((Y36-X36)>=15001,150,0)) -> 0 | AL36: 0 | AM36: =AB36+AD36+AL36 -> 1576 | AN36: =SUM(ROUND((Y36)-(AH36+AI36+AJ36+AK36+AM36),0),0) -> 10784
A37: =A36+1 -> 35 | B37: JAI-1136 | C37: 45086 | E37: Anchor | F37: 50100662377376 | G37: HDFC0009087 | H37: 101970000410 | I37: GMGPR3649J | J37: 5219753019 | K37: 37846 | L37: Female | M37: Semi-skilled | N37: No | O37: =VLOOKUP(B37,'Anchor-Attendance'!$B$4:$BB$84,53,0) -> 27.5 | P37: 12360 | Q37: =P37/$O$1*O37 -> 12139.286 | R37: =Q37*100% -> 12139.286 | S37: 0 | T37: 0 | U37: 0 | V37: =ROUND(SUM(R37:U37),0) -> 12139 | W37: 0 | X37: 0 | Y37: =SUM(V37:X37) -> 12139 | Z37: =ROUND(SUM(R37:U37)-S37,0) -> 12139 | AA37: =ROUND(IF(Z37>15000,15000,Z37),0) -> 12139 | AB37: =ROUND(IF(Z37>15000,1800,Z37*12%),0) -> 1457 | AC37: 0 | AD37: =ROUNDUP(IF(P37>21000,0,(Y37-X37)*0.75%),0) -> 92 | AE37: =ROUND(AB37/12%*8.33%,0) -> 1011 | AF37: =+AB37-AE37 -> 446 | AG37: =IF(P37>21000,0,(Y37-X37)*3.25%) -> 394.5175 | AH37: 0 | AI37: 0 | AJ37: 0 | AK37: =IF((Y37-X37)>=20001,200,IF((Y37-X37)>=15001,150,0)) -> 0 | AL37: 0 | AM37: =AB37+AD37+AL37 -> 1549 | AN37: =SUM(ROUND((Y37)-(AH37+AI37+AJ37+AK37+AM37),0),0) -> 10590
A38: =A37+1 -> 36 | B38: JAI-1139 | C38: 45086 | E38: Anchor | F38: 50100662377324 | G38: HDFC0009087 | H38: 101970000447 | I38: NWGPS1152E | J38: 5219753255 | K38: 36644 | L38: Female | M38: Semi-skilled | N38: No | O38: =VLOOKUP(B38,'Anchor-Attendance'!$B$4:$BB$84,53,0) -> 28 | P38: 12360 | Q38: =P38/$O$1*O38 -> 12360 | R38: =Q38*100% -> 12360 | S38: 0 | T38: 0 | U38: 0 | V38: =ROUND(SUM(R38:U38),0) -> 12360 | W38: 0 | X38: 0 | Y38: =SUM(V38:X38) -> 12360 | Z38: =ROUND(SUM(R38:U38)-S38,0) -> 12360 | AA38: =ROUND(IF(Z38>15000,15000,Z38),0) -> 12360 | AB38: =ROUND(IF(Z38>15000,1800,Z38*12%),0) -> 1483 | AC38: 0 | AD38: =ROUNDUP(IF(P38>21000,0,(Y38-X38)*0.75%),0) -> 93 | AE38: =ROUND(AB38/12%*8.33%,0) -> 1029 | AF38: =+AB38-AE38 -> 454 | AG38: =IF(P38>21000,0,(Y38-X38)*3.25%) -> 401.7 | AH38: 0 | AI38: 0 | AJ38: 0 | AK38: =IF((Y38-X38)>=20001,200,IF((Y38-X38)>=15001,150,0)) -> 0 | AL38: 0 | AM38: =AB38+AD38+AL38 -> 1576 | AN38: =SUM(ROUND((Y38)-(AH38+AI38+AJ38+AK38+AM38),0),0) -> 10784
A39: =A38+1 -> 37 | B39: JAI-1145 | C39: 45086 | E39: Anchor | F39: 50100613610990 | G39: HDFC0001635 | H39: 101969999988 | I39: NKMPK1037C | J39: 5219754257 | K39: 37266 | L39: Female | M39: Semi-skilled | N39: No | O39: =VLOOKUP(B39,'Anchor-Attendance'!$B$4:$BB$84,53,0) -> 28 | P39: 12360 | Q39: =P39/$O$1*O39 -> 12360 | R39: =Q39*100% -> 12360 | S39: =Q39*0% -> 0 | T39: 0 | U39: 0 | V39: =ROUND(SUM(R39:U39),0) -> 12360 | W39: 0 | X39: 0 | Y39: =SUM(V39:X39) -> 12360 | Z39: =ROUND(SUM(R39:U39)-S39,0) -> 12360 | AA39: =ROUND(IF(Z39>15000,15000,Z39),0) -> 12360 | AB39: =ROUND(IF(Z39>15000,1800,Z39*12%),0) -> 1483 | AC39: 0 | AD39: =ROUNDUP(IF(P39>21000,0,(Y39-X39)*0.75%),0) -> 93 | AE39: =ROUND(AB39/12%*8.33%,0) -> 1029 | AF39: =+AB39-AE39 -> 454 | AG39: =IF(P39>21000,0,(Y39-X39)*3.25%) -> 401.7 | AH39: 0 | AI39: 0 | AJ39: 0 | AK39: =IF((Y39-X39)>=20001,200,IF((Y39-X39)>=15001,150,0)) -> 0 | AL39: 0 | AM39: =AB39+AD39+AL39 -> 1576 | AN39: =SUM(ROUND((Y39)-(AH39+AI39+AJ39+AK39+AM39),0),0) -> 10784
A40: =A39+1 -> 38 | B40: JAI-1149 | C40: 45086 | E40: Anchor | F40: 50100662377248 | G40: HDFC0009087 | H40: 101970000423 | I40: PZFPS2268D | J40: 5219755347 | K40: 37084 | L40: Female | M40: Semi-skilled | N40: No | O40: =VLOOKUP(B40,'Anchor-Attendance'!$B$4:$BB$84,53,0) -> 28 | P40: 12360 | Q40: =P40/$O$1*O40 -> 12360 | R40: =Q40*100% -> 12360 | S40: 0 | T40: 0 | U40: 0 | V40: =ROUND(SUM(R40:U40),0) -> 12360 | W40: 0 | X40: 0 | Y40: =SUM(V40:X40) -> 12360 | Z40: =ROUND(SUM(R40:U40)-S40,0) -> 12360 | AA40: =ROUND(IF(Z40>15000,15000,Z40),0) -> 12360 | AB40: =ROUND(IF(Z40>15000,1800,Z40*12%),0) -> 1483 | AC40: 0 | AD40: =ROUNDUP(IF(P40>21000,0,(Y40-X40)*0.75%),0) -> 93 | AE40: =ROUND(AB40/12%*8.33%,0) -> 1029 | AF40: =+AB40-AE40 -> 454 | AG40: =IF(P40>21000,0,(Y40-X40)*3.25%) -> 401.7 | AH40: 0 | AI40: 0 | AJ40: 0 | AK40: =IF((Y40-X40)>=20001,200,IF((Y40-X40)>=15001,150,0)) -> 0 | AL40: 0 | AM40: =AB40+AD40+AL40 -> 1576 | AN40: =SUM(ROUND((Y40)-(AH40+AI40+AJ40+AK40+AM40),0),0) -> 10784
A41: =A40+1 -> 39 | B41: JAI-1153 | C41: 45086 | E41: Anchor | F41: 50100662377290 | G41: HDFC0009087 | H41: 101970000239 | I41: CIRPV6752K | J41: 5219755685 | K41: 38029 | L41: Female | M41: Semi-skilled | N41: No | O41: =VLOOKUP(B41,'Anchor-Attendance'!$B$4:$BB$84,53,0) -> 26.5 | P41: 12360 | Q41: =P41/$O$1*O41 -> 11697.857 | R41: =Q41*100% -> 11697.857 | S41: 0 | T41: 0 | U41: 0 | V41: =ROUND(SUM(R41:U41),0) -> 11698 | W41: 0 | X41: 0 | Y41: =SUM(V41:X41) -> 11698 | Z41: =ROUND(SUM(R41:U41)-S41,0) -> 11698 | AA41: =ROUND(IF(Z41>15000,15000,Z41),0) -> 11698 | AB41: =ROUND(IF(Z41>15000,1800,Z41*12%),0) -> 1404 | AC41: 0 | AD41: =ROUNDUP(IF(P41>21000,0,(Y41-X41)*0.75%),0) -> 88 | AE41: =ROUND(AB41/12%*8.33%,0) -> 975 | AF41: =+AB41-AE41 -> 429 | AG41: =IF(P41>21000,0,(Y41-X41)*3.25%) -> 380.185 | AH41: 0 | AI41: 0 | AJ41: 0 | AK41: =IF((Y41-X41)>=20001,200,IF((Y41-X41)>=15001,150,0)) -> 0 | AL41: 0 | AM41: =AB41+AD41+AL41 -> 1492 | AN41: =SUM(ROUND((Y41)-(AH41+AI41+AJ41+AK41+AM41),0),0) -> 10206
A42: =A41+1 -> 40 | B42: JAI-1158 | C42: 45101 | E42: Anchor | F42: 50100662377159 | G42: HDFC0009087 | H42: 101969999893 | I42: BNTPH 9030C | J42: 5219795688 | K42: 38127 | L42: Female | M42: Semi-skilled | N42: No | O42: =VLOOKUP(B42,'Anchor-Attendance'!$B$4:$BB$84,53,0) -> 28 | P42: 12360 | Q42: =P42/$O$1*O42 -> 12360 | R42: =Q42*100% -> 12360 | S42: 0 | T42: 0 | U42: 0 | V42: =ROUND(SUM(R42:U42),0) -> 12360 | W42: 0 | X42: 0 | Y42: =SUM(V42:X42) -> 12360 | Z42: =ROUND(SUM(R42:U42)-S42,0) -> 12360 | AA42: =ROUND(IF(Z42>15000,15000,Z42),0) -> 12360 | AB42: =ROUND(IF(Z42>15000,1800,Z42*12%),0) -> 1483 | AC42: 0 | AD42: =ROUNDUP(IF(P42>21000,0,(Y42-X42)*0.75%),0) -> 93 | AE42: =ROUND(AB42/12%*8.33%,0) -> 1029 | AF42: =+AB42-AE42 -> 454 | AG42: =IF(P42>21000,0,(Y42-X42)*3.25%) -> 401.7 | AH42: 0 | AI42: 0 | AJ42: 0 | AK42: =IF((Y42-X42)>=20001,200,IF((Y42-X42)>=15001,150,0)) -> 0 | AL42: 0 | AM42: =AB42+AD42+AL42 -> 1576 | AN42: =SUM(ROUND((Y42)-(AH42+AI42+AJ42+AK42+AM42),0),0) -> 10784
A43: =A42+1 -> 41 | B43: JAI-757 | C43: 44909 | E43: Anchor | F43: 50100588150680 | G43: HDFC0001635 | H43: 101908102863 | I43: EANPG7868F | J43: 5219235823 | K43: 37839 | L43: Female | M43: Semi-skilled | N43: No | O43: =VLOOKUP(B43,'Anchor-Attendance'!$B$4:$BB$84,53,0) -> 28 | P43: 12360 | Q43: =P43/$O$1*O43 -> 12360 | R43: =Q43*100% -> 12360 | S43: 0 | T43: 0 | U43: 0 | V43: =ROUND(SUM(R43:U43),0) -> 12360 | W43: 0 | X43: 0 | Y43: =SUM(V43:X43) -> 12360 | Z43: =ROUND(SUM(R43:U43)-S43,0) -> 12360 | AA43: =ROUND(IF(Z43>15000,15000,Z43),0) -> 12360 | AB43: =ROUND(IF(Z43>15000,1800,Z43*12%),0) -> 1483 | AC43: 0 | AD43: =ROUNDUP(IF(P43>21000,0,(Y43-X43)*0.75%),0) -> 93 | AE43: =ROUND(AB43/12%*8.33%,0) -> 1029 | AF43: =+AB43-AE43 -> 454 | AG43: =IF(P43>21000,0,(Y43-X43)*3.25%) -> 401.7 | AH43: 0 | AI43: 0 | AJ43: 0 | AK43: =IF((Y43-X43)>=20001,200,IF((Y43-X43)>=15001,150,0)) -> 0 | AL43: 0 | AM43: =AB43+AD43+AL43 -> 1576 | AN43: =SUM(ROUND((Y43)-(AH43+AI43+AJ43+AK43+AM43),0),0) -> 10784
A44: =A43+1 -> 42 | B44: JAI-892 | C44: 45033 | E44: Anchor | F44: 50100588150220 | G44: HDFC0001635 | H44: 101916715226 | I44: BNHPY5660H | J44: 5219252277 | K44: 37085 | L44: Female | M44: Semi-skilled | N44: =VLOOKUP(B44,'Anchor-Attendance'!$B$4:$K$84,10,0) -> 46072 | O44: =VLOOKUP(B44,'Anchor-Attendance'!$B$4:$BB$84,53,0) -> 19 | P44: 12360 | Q44: =P44/$O$1*O44 -> 8387.1429 | R44: =Q44*100% -> 8387.1429 | S44: 0 | T44: 0 | U44: 0 | V44: =ROUND(SUM(R44:U44),0) -> 8387 | W44: =12360-V44 -> 3973 | X44: =AR44 -> 0 | Y44: =SUM(V44:X44) -> 12360 | Z44: =ROUND(SUM(R44:U44)-S44,0) -> 8387 | AA44: =ROUND(IF(Z44>15000,15000,Z44),0) -> 8387 | AB44: =ROUND(IF(Z44>15000,1800,Z44*12%),0) -> 1006 | AC44: 0 | AD44: =ROUNDUP(IF(P44>21000,0,(Y44-X44)*0.75%),0) -> 93 | AE44: =ROUND(AB44/12%*8.33%,0) -> 698 | AF44: =+AB44-AE44 -> 308 | AG44: =IF(P44>21000,0,(Y44-X44)*3.25%) -> 401.7 | AH44: 0 | AI44: 0 | AJ44: 0 | AK44: =IF((Y44-X44)>=20001,200,IF((Y44-X44)>=15001,150,0)) -> 0 | AL44: 0 | AM44: =AB44+AD44+AL44 -> 1099 | AN44: =SUM(ROUND((Y44)-(AH44+AI44+AJ44+AK44+AM44),0),0) -> 11261 | AO44: Full month salary to be paid | AP44: =ROUND((N44-C44)/365,0) -> 3
A45: =A44+1 -> 43 | B45: JAI-306 | C45: 44426 | E45: Anchor | F45: 50100452151061 | G45: HDFC0003916 | H45: 101727707222 | I45: CNDPC1537N | J45: 5217668503 | K45: 36613 | L45: Female | M45: Semi-skilled | N45: No | O45: =VLOOKUP(B45,'Anchor-Attendance'!$B$4:$BB$84,53,0) -> 28 | P45: 12360 | Q45: =P45/$O$1*O45 -> 12360 | R45: =Q45*100% -> 12360 | S45: 0 | T45: 0 | U45: 0 | V45: =ROUND(SUM(R45:U45),0) -> 12360 | W45: 0 | X45: 0 | Y45: =SUM(V45:X45) -> 12360 | Z45: =ROUND(SUM(R45:U45)-S45,0) -> 12360 | AA45: =ROUND(IF(Z45>15000,15000,Z45),0) -> 12360 | AB45: =ROUND(IF(Z45>15000,1800,Z45*12%),0) -> 1483 | AC45: 0 | AD45: =ROUNDUP(IF(P45>21000,0,(Y45-X45)*0.75%),0) -> 93 | AE45: =ROUND(AB45/12%*8.33%,0) -> 1029 | AF45: =+AB45-AE45 -> 454 | AG45: =IF(P45>21000,0,(Y45-X45)*3.25%) -> 401.7 | AH45: 0 | AI45: 0 | AJ45: 0 | AK45: =IF((Y45-X45)>=20001,200,IF((Y45-X45)>=15001,150,0)) -> 0 | AL45: 0 | AM45: =AB45+AD45+AL45 -> 1576 | AN45: =SUM(ROUND((Y45)-(AH45+AI45+AJ45+AK45+AM45),0),0) -> 10784
A46: =A45+1 -> 44 | B46: JAI-308 | C46: 44426 | E46: Anchor | F46: 50100453956932 | G46: HDFC0001635 | H46: 101557262676 | I46: DPUPG9647M | J46: 5217671356 | K46: 35236 | L46: Female | M46: Semi-skilled | N46: No | O46: =VLOOKUP(B46,'Anchor-Attendance'!$B$4:$BB$84,53,0) -> 28 | P46: 12360 | Q46: =P46/$O$1*O46 -> 12360 | R46: =Q46*100% -> 12360 | S46: 0 | T46: 0 | U46: 0 | V46: =ROUND(SUM(R46:U46),0) -> 12360 | W46: 0 | X46: 0 | Y46: =SUM(V46:X46) -> 12360 | Z46: =ROUND(SUM(R46:U46)-S46,0) -> 12360 | AA46: =ROUND(IF(Z46>15000,15000,Z46),0) -> 12360 | AB46: =ROUND(IF(Z46>15000,1800,Z46*12%),0) -> 1483 | AC46: 0 | AD46: =ROUNDUP(IF(P46>21000,0,(Y46-X46)*0.75%),0) -> 93 | AE46: =ROUND(AB46/12%*8.33%,0) -> 1029 | AF46: =+AB46-AE46 -> 454 | AG46: =IF(P46>21000,0,(Y46-X46)*3.25%) -> 401.7 | AH46: 0 | AI46: 0 | AJ46: 0 | AK46: =IF((Y46-X46)>=20001,200,IF((Y46-X46)>=15001,150,0)) -> 0 | AL46: 0 | AM46: =AB46+AD46+AL46 -> 1576 | AN46: =SUM(ROUND((Y46)-(AH46+AI46+AJ46+AK46+AM46),0),0) -> 10784
A47: =A46+1 -> 45 | B47: JAI-317 | C47: 44426 | E47: Anchor | F47: 50100452147956 | G47: HDFC0003916 | H47: 101721436177 | I47: GVMPM6619A | J47: 5217668476 | K47: 37507 | L47: Female | M47: Semi-skilled | N47: No | O47: =VLOOKUP(B47,'Anchor-Attendance'!$B$4:$BB$84,53,0) -> 28 | P47: 12360 | Q47: =P47/$O$1*O47 -> 12360 | R47: =Q47*100% -> 12360 | S47: 0 | T47: 0 | U47: 0 | V47: =ROUND(SUM(R47:U47),0) -> 12360 | W47: 0 | X47: 0 | Y47: =SUM(V47:X47) -> 12360 | Z47: =ROUND(SUM(R47:U47)-S47,0) -> 12360 | AA47: =ROUND(IF(Z47>15000,15000,Z47),0) -> 12360 | AB47: =ROUND(IF(Z47>15000,1800,Z47*12%),0) -> 1483 | AC47: 0 | AD47: =ROUNDUP(IF(P47>21000,0,(Y47-X47)*0.75%),0) -> 93 | AE47: =ROUND(AB47/12%*8.33%,0) -> 1029 | AF47: =+AB47-AE47 -> 454 | AG47: =IF(P47>21000,0,(Y47-X47)*3.25%) -> 401.7 | AH47: 0 | AI47: 0 | AJ47: 0 | AK47: =IF((Y47-X47)>=20001,200,IF((Y47-X47)>=15001,150,0)) -> 0 | AL47: 0 | AM47: =AB47+AD47+AL47 -> 1576 | AN47: =SUM(ROUND((Y47)-(AH47+AI47+AJ47+AK47+AM47),0),0) -> 10784
A48: =A47+1 -> 46 | B48: JAI-374 | C48: 44522 | E48: Anchor | F48: 50100453958603 | G48: HDFC0001635 | H48: 101757902501 | I48: COSPN0843N | J48: 5217962015 | K48: 37122 | L48: Female | M48: Semi-skilled | N48: No | O48: =VLOOKUP(B48,'Anchor-Attendance'!$B$4:$BB$84,53,0) -> 28 | P48: 12360 | Q48: =P48/$O$1*O48 -> 12360 | R48: =Q48*100% -> 12360 | S48: 0 | T48: 0 | U48: 0 | V48: =ROUND(SUM(R48:U48),0) -> 12360 | W48: 0 | X48: 0 | Y48: =SUM(V48:X48) -> 12360 | Z48: =ROUND(SUM(R48:U48)-S48,0) -> 12360 | AA48: =ROUND(IF(Z48>15000,15000,Z48),0) -> 12360 | AB48: =ROUND(IF(Z48>15000,1800,Z48*12%),0) -> 1483 | AC48: 0 | AD48: =ROUNDUP(IF(P48>21000,0,(Y48-X48)*0.75%),0) -> 93 | AE48: =ROUND(AB48/12%*8.33%,0) -> 1029 | AF48: =+AB48-AE48 -> 454 | AG48: =IF(P48>21000,0,(Y48-X48)*3.25%) -> 401.7 | AH48: 0 | AI48: 0 | AJ48: 0 | AK48: =IF((Y48-X48)>=20001,200,IF((Y48-X48)>=15001,150,0)) -> 0 | AL48: 0 | AM48: =AB48+AD48+AL48 -> 1576 | AN48: =SUM(ROUND((Y48)-(AH48+AI48+AJ48+AK48+AM48),0),0) -> 10784
A49: =A48+1 -> 47 | B49: JAI-464 | C49: 44845 | E49: Anchor | F49: 50100527663841 | G49: HDFC0009087 | H49: 101877719356 | I49: EQAPA2205R | J49: 5218489712 | K49: 36365 | L49: Female | M49: Semi-skilled | N49: No | O49: =VLOOKUP(B49,'Anchor-Attendance'!$B$4:$BB$84,53,0) -> 25.5 | P49: 12360 | Q49: =P49/$O$1*O49 -> 11256.429 | R49: =Q49*100% -> 11256.429 | S49: 0 | T49: 0 | U49: 0 | V49: =ROUND(SUM(R49:U49),0) -> 11256 | W49: 0 | X49: 0 | Y49: =SUM(V49:X49) -> 11256 | Z49: =ROUND(SUM(R49:U49)-S49,0) -> 11256 | AA49: =ROUND(IF(Z49>15000,15000,Z49),0) -> 11256 | AB49: =ROUND(IF(Z49>15000,1800,Z49*12%),0) -> 1351 | AC49: 0 | AD49: =ROUNDUP(IF(P49>21000,0,(Y49-X49)*0.75%),0) -> 85 | AE49: =ROUND(AB49/12%*8.33%,0) -> 938 | AF49: =+AB49-AE49 -> 413 | AG49: =IF(P49>21000,0,(Y49-X49)*3.25%) -> 365.82 | AH49: 0 | AI49: 0 | AJ49: 0 | AK49: =IF((Y49-X49)>=20001,200,IF((Y49-X49)>=15001,150,0)) -> 0 | AL49: 0 | AM49: =AB49+AD49+AL49 -> 1436 | AN49: =SUM(ROUND((Y49)-(AH49+AI49+AJ49+AK49+AM49),0),0) -> 9820
A50: =A49+1 -> 48 | B50: JAI-468 | C50: 44845 | E50: Anchor | F50: 50100515745033 | G50: HDFC0009087 | H50: 101877719095 | I50: GIEPB3849E | J50: 5218490241 | K50: 36920 | L50: Female | M50: Semi-skilled | N50: No | O50: =VLOOKUP(B50,'Anchor-Attendance'!$B$4:$BB$84,53,0) -> 28 | P50: 12360 | Q50: =P50/$O$1*O50 -> 12360 | R50: =Q50*100% -> 12360 | S50: 0 | T50: 0 | U50: 0 | V50: =ROUND(SUM(R50:U50),0) -> 12360 | W50: 0 | X50: 0 | Y50: =SUM(V50:X50) -> 12360 | Z50: =ROUND(SUM(R50:U50)-S50,0) -> 12360 | AA50: =ROUND(IF(Z50>15000,15000,Z50),0) -> 12360 | AB50: =ROUND(IF(Z50>15000,1800,Z50*12%),0) -> 1483 | AC50: 0 | AD50: =ROUNDUP(IF(P50>21000,0,(Y50-X50)*0.75%),0) -> 93 | AE50: =ROUND(AB50/12%*8.33%,0) -> 1029 | AF50: =+AB50-AE50 -> 454 | AG50: =IF(P50>21000,0,(Y50-X50)*3.25%) -> 401.7 | AH50: 0 | AI50: 0 | AJ50: 0 | AK50: =IF((Y50-X50)>=20001,200,IF((Y50-X50)>=15001,150,0)) -> 0 | AL50: 0 | AM50: =AB50+AD50+AL50 -> 1576 | AN50: =SUM(ROUND((Y50)-(AH50+AI50+AJ50+AK50+AM50),0),0) -> 10784
A51: =A50+1 -> 49 | B51: JAI-469 | C51: 44845 | E51: Anchor | F51: 50100488397690 | G51: HDFC0003665 | H51: 101777906628 | I51: HKNPD7903K | J51: 5218492747 | K51: 36680 | L51: Female | M51: Semi-skilled | N51: No | O51: =VLOOKUP(B51,'Anchor-Attendance'!$B$4:$BB$84,53,0) -> 28 | P51: 12360 | Q51: =P51/$O$1*O51 -> 12360 | R51: =Q51*100% -> 12360 | S51: 0 | T51: 0 | U51: 0 | V51: =ROUND(SUM(R51:U51),0) -> 12360 | W51: 0 | X51: 0 | Y51: =SUM(V51:X51) -> 12360 | Z51: =ROUND(SUM(R51:U51)-S51,0) -> 12360 | AA51: =ROUND(IF(Z51>15000,15000,Z51),0) -> 12360 | AB51: =ROUND(IF(Z51>15000,1800,Z51*12%),0) -> 1483 | AC51: 0 | AD51: =ROUNDUP(IF(P51>21000,0,(Y51-X51)*0.75%),0) -> 93 | AE51: =ROUND(AB51/12%*8.33%,0) -> 1029 | AF51: =+AB51-AE51 -> 454 | AG51: =IF(P51>21000,0,(Y51-X51)*3.25%) -> 401.7 | AH51: 0 | AI51: 0 | AJ51: 0 | AK51: =IF((Y51-X51)>=20001,200,IF((Y51-X51)>=15001,150,0)) -> 0 | AL51: 0 | AM51: =AB51+AD51+AL51 -> 1576 | AN51: =SUM(ROUND((Y51)-(AH51+AI51+AJ51+AK51+AM51),0),0) -> 10784
A52: =A51+1 -> 50 | B52: JAI-471 | C52: 44845 | E52: Anchor | F52: 50100515745240 | G52: HDFC0009087 | H52: 101877719302 | I52: BNBPH4995J | J52: 5218493696 | K52: 36748 | L52: Female | M52: Semi-skilled | N52: No | O52: =VLOOKUP(B52,'Anchor-Attendance'!$B$4:$BB$84,53,0) -> 28 | P52: 12360 | Q52: =P52/$O$1*O52 -> 12360 | R52: =Q52*100% -> 12360 | S52: 0 | T52: 0 | U52: 0 | V52: =ROUND(SUM(R52:U52),0) -> 12360 | W52: 0 | X52: 0 | Y52: =SUM(V52:X52) -> 12360 | Z52: =ROUND(SUM(R52:U52)-S52,0) -> 12360 | AA52: =ROUND(IF(Z52>15000,15000,Z52),0) -> 12360 | AB52: =ROUND(IF(Z52>15000,1800,Z52*12%),0) -> 1483 | AC52: 0 | AD52: =ROUNDUP(IF(P52>21000,0,(Y52-X52)*0.75%),0) -> 93 | AE52: =ROUND(AB52/12%*8.33%,0) -> 1029 | AF52: =+AB52-AE52 -> 454 | AG52: =IF(P52>21000,0,(Y52-X52)*3.25%) -> 401.7 | AH52: 0 | AI52: 0 | AJ52: 0 | AK52: =IF((Y52-X52)>=20001,200,IF((Y52-X52)>=15001,150,0)) -> 0 | AL52: 0 | AM52: =AB52+AD52+AL52 -> 1576 | AN52: =SUM(ROUND((Y52)-(AH52+AI52+AJ52+AK52+AM52),0),0) -> 10784
A53: =A52+1 -> 51 | B53: JAI-486 | C53: 44845 | E53: Anchor | F53: 50100515745148 | G53: HDFC0009087 | H53: 101852889878 | I53: LPXPK6079J | J53: 5218504642 | K53: 36696 | L53: Female | M53: Semi-skilled | N53: No | O53: =VLOOKUP(B53,'Anchor-Attendance'!$B$4:$BB$84,53,0) -> 28 | P53: 12360 | Q53: =P53/$O$1*O53 -> 12360 | R53: =Q53*100% -> 12360 | S53: 0 | T53: 0 | U53: 0 | V53: =ROUND(SUM(R53:U53),0) -> 12360 | W53: 0 | X53: 0 | Y53: =SUM(V53:X53) -> 12360 | Z53: =ROUND(SUM(R53:U53)-S53,0) -> 12360 | AA53: =ROUND(IF(Z53>15000,15000,Z53),0) -> 12360 | AB53: =ROUND(IF(Z53>15000,1800,Z53*12%),0) -> 1483 | AC53: 0 | AD53: =ROUNDUP(IF(P53>21000,0,(Y53-X53)*0.75%),0) -> 93 | AE53: =ROUND(AB53/12%*8.33%,0) -> 1029 | AF53: =+AB53-AE53 -> 454 | AG53: =IF(P53>21000,0,(Y53-X53)*3.25%) -> 401.7 | AH53: 0 | AI53: 0 | AJ53: 0 | AK53: =IF((Y53-X53)>=20001,200,IF((Y53-X53)>=15001,150,0)) -> 0 | AL53: 0 | AM53: =AB53+AD53+AL53 -> 1576 | AN53: =SUM(ROUND((Y53)-(AH53+AI53+AJ53+AK53+AM53),0),0) -> 10784
A54: =A53+1 -> 52 | B54: JAI-487 | C54: 44845 | E54: Anchor | F54: 50100515744603 | G54: HDFC0009087 | H54: 101852889884 | I54: LXOPK1703Q | J54: 5218504699 | K54: 36361 | L54: Female | M54: Semi-skilled | N54: No | O54: =VLOOKUP(B54,'Anchor-Attendance'!$B$4:$BB$84,53,0) -> 28 | P54: 12360 | Q54: =P54/$O$1*O54 -> 12360 | R54: =Q54*100% -> 12360 | S54: =Q54*0% -> 0 | T54: 0 | U54: 0 | V54: =ROUND(SUM(R54:U54),0) -> 12360 | W54: 0 | X54: 0 | Y54: =SUM(V54:X54) -> 12360 | Z54: =ROUND(SUM(R54:U54)-S54,0) -> 12360 | AA54: =ROUND(IF(Z54>15000,15000,Z54),0) -> 12360 | AB54: =ROUND(IF(Z54>15000,1800,Z54*12%),0) -> 1483 | AC54: 0 | AD54: =ROUNDUP(IF(P54>21000,0,(Y54-X54)*0.75%),0) -> 93 | AE54: =ROUND(AB54/12%*8.33%,0) -> 1029 | AF54: =+AB54-AE54 -> 454 | AG54: =IF(P54>21000,0,(Y54-X54)*3.25%) -> 401.7 | AH54: 0 | AI54: 0 | AJ54: 0 | AK54: =IF((Y54-X54)>=20001,200,IF((Y54-X54)>=15001,150,0)) -> 0 | AL54: 0 | AM54: =AB54+AD54+AL54 -> 1576 | AN54: =SUM(ROUND((Y54)-(AH54+AI54+AJ54+AK54+AM54),0),0) -> 10784
A55: =A54+1 -> 53 | B55: JAI-517 | C55: 44845 | E55: Anchor | F55: 50100515745062 | G55: HDFC0009087 | H55: 101877719024 | I55: GNHPM0054E | J55: 5218505497 | K55: 35569 | L55: Female | M55: Semi-skilled | N55: =VLOOKUP(B55,'Anchor-Attendance'!$B$4:$K$84,10,0) -> 46072 | O55: =VLOOKUP(B55,'Anchor-Attendance'!$B$4:$BB$84,53,0) -> 19 | P55: 12360 | Q55: =P55/$O$1*O55 -> 8387.1429 | R55: =Q55*100% -> 8387.1429 | S55: 0 | T55: 0 | U55: 0 | V55: =ROUND(SUM(R55:U55),0) -> 8387 | W55: =12360-V55 -> 3973 | X55: =AR55 -> 0 | Y55: =SUM(V55:X55) -> 12360 | Z55: =ROUND(SUM(R55:U55)-S55,0) -> 8387 | AA55: =ROUND(IF(Z55>15000,15000,Z55),0) -> 8387 | AB55: =ROUND(IF(Z55>15000,1800,Z55*12%),0) -> 1006 | AC55: 0 | AD55: =ROUNDUP(IF(P55>21000,0,(Y55-X55)*0.75%),0) -> 93 | AE55: =ROUND(AB55/12%*8.33%,0) -> 698 | AF55: =+AB55-AE55 -> 308 | AG55: =IF(P55>21000,0,(Y55-X55)*3.25%) -> 401.7 | AH55: 0 | AI55: 0 | AJ55: 0 | AK55: =IF((Y55-X55)>=20001,200,IF((Y55-X55)>=15001,150,0)) -> 0 | AL55: 0 | AM55: =AB55+AD55+AL55 -> 1099 | AN55: =SUM(ROUND((Y55)-(AH55+AI55+AJ55+AK55+AM55),0),0) -> 11261 | AO55: Full month salary to be paid | AP55: =ROUND((N55-C55)/365,0) -> 3
A56: =A55+1 -> 54 | B56: JAI-542 | C56: 44845 | E56: Anchor | F56: 50100519894360 | G56: HDFC0009087 | H56: 101877719285 | I56: GSQPP1392Q | J56: 5218514630 | K56: 35596 | L56: Female | M56: Semi-skilled | N56: No | O56: =VLOOKUP(B56,'Anchor-Attendance'!$B$4:$BB$84,53,0) -> 28 | P56: 12360 | Q56: =P56/$O$1*O56 -> 12360 | R56: =Q56*100% -> 12360 | S56: 0 | T56: 0 | U56: 0 | V56: =ROUND(SUM(R56:U56),0) -> 12360 | W56: 0 | X56: 0 | Y56: =SUM(V56:X56) -> 12360 | Z56: =ROUND(SUM(R56:U56)-S56,0) -> 12360 | AA56: =ROUND(IF(Z56>15000,15000,Z56),0) -> 12360 | AB56: =ROUND(IF(Z56>15000,1800,Z56*12%),0) -> 1483 | AC56: 0 | AD56: =ROUNDUP(IF(P56>21000,0,(Y56-X56)*0.75%),0) -> 93 | AE56: =ROUND(AB56/12%*8.33%,0) -> 1029 | AF56: =+AB56-AE56 -> 454 | AG56: =IF(P56>21000,0,(Y56-X56)*3.25%) -> 401.7 | AH56: 0 | AI56: 0 | AJ56: 0 | AK56: =IF((Y56-X56)>=20001,200,IF((Y56-X56)>=15001,150,0)) -> 0 | AL56: 0 | AM56: =AB56+AD56+AL56 -> 1576 | AN56: =SUM(ROUND((Y56)-(AH56+AI56+AJ56+AK56+AM56),0),0) -> 10784
A57: =A56+1 -> 55 | B57: JAI-564 | C57: 44845 | E57: Anchor | F57: 50100515743474 | G57: HDFC0009087 | H57: 101877719198 | I57: HLZPM6514A | J57: 5218528649 | K57: 36229 | L57: Female | M57: Semi-skilled | N57: No | O57: =VLOOKUP(B57,'Anchor-Attendance'!$B$4:$BB$84,53,0) -> 28 | P57: 12360 | Q57: =P57/$O$1*O57 -> 12360 | R57: =Q57*100% -> 12360 | S57: 0 | T57: 0 | U57: 0 | V57: =ROUND(SUM(R57:U57),0) -> 12360 | W57: 0 | X57: 0 | Y57: =SUM(V57:X57) -> 12360 | Z57: =ROUND(SUM(R57:U57)-S57,0) -> 12360 | AA57: =ROUND(IF(Z57>15000,15000,Z57),0) -> 12360 | AB57: =ROUND(IF(Z57>15000,1800,Z57*12%),0) -> 1483 | AC57: 0 | AD57: =ROUNDUP(IF(P57>21000,0,(Y57-X57)*0.75%),0) -> 93 | AE57: =ROUND(AB57/12%*8.33%,0) -> 1029 | AF57: =+AB57-AE57 -> 454 | AG57: =IF(P57>21000,0,(Y57-X57)*3.25%) -> 401.7 | AH57: 0 | AI57: 0 | AJ57: 0 | AK57: =IF((Y57-X57)>=20001,200,IF((Y57-X57)>=15001,150,0)) -> 0 | AL57: 0 | AM57: =AB57+AD57+AL57 -> 1576 | AN57: =SUM(ROUND((Y57)-(AH57+AI57+AJ57+AK57+AM57),0),0) -> 10784
A58: =A57+1 -> 56 | B58: JAI-583 | C58: 44845 | E58: Anchor | F58: 50100527663788 | G58: HDFC0009087 | H58: 101852892332 | I58: FBCPR4633G | J58: 5218515903 | K58: 36222 | L58: Female | M58: Semi-skilled | N58: No | O58: =VLOOKUP(B58,'Anchor-Attendance'!$B$4:$BB$84,53,0) -> 25 | P58: 12360 | Q58: =P58/$O$1*O58 -> 11035.714 | R58: =Q58*100% -> 11035.714 | S58: 0 | T58: 0 | U58: 0 | V58: =ROUND(SUM(R58:U58),0) -> 11036 | W58: 0 | X58: 0 | Y58: =SUM(V58:X58) -> 11036 | Z58: =ROUND(SUM(R58:U58)-S58,0) -> 11036 | AA58: =ROUND(IF(Z58>15000,15000,Z58),0) -> 11036 | AB58: =ROUND(IF(Z58>15000,1800,Z58*12%),0) -> 1324 | AC58: 0 | AD58: =ROUNDUP(IF(P58>21000,0,(Y58-X58)*0.75%),0) -> 83 | AE58: =ROUND(AB58/12%*8.33%,0) -> 919 | AF58: =+AB58-AE58 -> 405 | AG58: =IF(P58>21000,0,(Y58-X58)*3.25%) -> 358.67 | AH58: 0 | AI58: 0 | AJ58: 0 | AK58: =IF((Y58-X58)>=20001,200,IF((Y58-X58)>=15001,150,0)) -> 0 | AL58: 0 | AM58: =AB58+AD58+AL58 -> 1407 | AN58: =SUM(ROUND((Y58)-(AH58+AI58+AJ58+AK58+AM58),0),0) -> 9629
A59: =A58+1 -> 57 | B59: JAI-732 | C59: 44909 | E59: Anchor | F59: 50100594522253 | G59: HDFC0009087 | H59: 101785031099 | I59: AHMPF8116H | J59: 5219226426 | K59: 36485 | L59: Female | M59: Semi-skilled | N59: No | O59: =VLOOKUP(B59,'Anchor-Attendance'!$B$4:$BB$84,53,0) -> 28 | P59: 12360 | Q59: =P59/$O$1*O59 -> 12360 | R59: =Q59*100% -> 12360 | S59: 0 | T59: 0 | U59: 0 | V59: =ROUND(SUM(R59:U59),0) -> 12360 | W59: 0 | X59: 0 | Y59: =SUM(V59:X59) -> 12360 | Z59: =ROUND(SUM(R59:U59)-S59,0) -> 12360 | AA59: =ROUND(IF(Z59>15000,15000,Z59),0) -> 12360 | AB59: =ROUND(IF(Z59>15000,1800,Z59*12%),0) -> 1483 | AC59: 0 | AD59: =ROUNDUP(IF(P59>21000,0,(Y59-X59)*0.75%),0) -> 93 | AE59: =ROUND(AB59/12%*8.33%,0) -> 1029 | AF59: =+AB59-AE59 -> 454 | AG59: =IF(P59>21000,0,(Y59-X59)*3.25%) -> 401.7 | AH59: 0 | AI59: 0 | AJ59: 0 | AK59: =IF((Y59-X59)>=20001,200,IF((Y59-X59)>=15001,150,0)) -> 0 | AL59: 0 | AM59: =AB59+AD59+AL59 -> 1576 | AN59: =SUM(ROUND((Y59)-(AH59+AI59+AJ59+AK59+AM59),0),0) -> 10784
A60: =A59+1 -> 58 | B60: JAI-796 | C60: 45033 | E60: Asset | F60: 50100583384310 | G60: HDFC0009087 | H60: 101907089402 | I60: IGCPD6253C | J60: 5219251156 | K60: 36392 | L60: Female | M60: Semi-skilled | N60: No | O60: =VLOOKUP(B60,'Anchor-Attendance'!$B$4:$BB$84,53,0) -> 28 | P60: 17000 | Q60: =P60/$O$1*O60 -> 17000 | R60: =Q60*90% -> 15300 | S60: =Q60*10% -> 1700 | T60: 0 | U60: 0 | V60: =ROUND(SUM(R60:U60),0) -> 17000 | W60: 0 | X60: 0 | Y60: =SUM(V60:X60) -> 17000 | Z60: =ROUND(SUM(R60:U60)-S60,0) -> 15300 | AA60: =ROUND(IF(Z60>15000,15000,Z60),0) -> 15000 | AB60: =ROUND(IF(Z60>15000,1800,Z60*12%),0) -> 1800 | AC60: 0 | AD60: =ROUNDUP(IF(P60>21000,0,(Y60-X60)*0.75%),0) -> 128 | AE60: =ROUND(AB60/12%*8.33%,0) -> 1250 | AF60: =+AB60-AE60 -> 550 | AG60: =IF(P60>21000,0,(Y60-X60)*3.25%) -> 552.5 | AH60: 0 | AI60: 0 | AJ60: 0 | AK60: =IF((Y60-X60)>=20001,200,IF((Y60-X60)>=15001,150,0)) -> 150 | AL60: 0 | AM60: =AB60+AD60+AL60 -> 1928 | AN60: =SUM(ROUND((Y60)-(AH60+AI60+AJ60+AK60+AM60),0),0) -> 14922
A61: =A60+1 -> 59 | B61: JAI-805 | C61: 45033 | E61: Anchor | F61: 50100588150309 | G61: HDFC0001635 | H61: 101907089441 | I61: ANYPI3225L | J61: 5219258989 | K61: 37365 | L61: Female | M61: Semi-skilled | N61: No | O61: =VLOOKUP(B61,'Anchor-Attendance'!$B$4:$BB$84,53,0) -> 28 | P61: 12360 | Q61: =P61/$O$1*O61 -> 12360 | R61: =Q61*100% -> 12360 | S61: 0 | T61: 0 | U61: 0 | V61: =ROUND(SUM(R61:U61),0) -> 12360 | W61: 0 | X61: 0 | Y61: =SUM(V61:X61) -> 12360 | Z61: =ROUND(SUM(R61:U61)-S61,0) -> 12360 | AA61: =ROUND(IF(Z61>15000,15000,Z61),0) -> 12360 | AB61: =ROUND(IF(Z61>15000,1800,Z61*12%),0) -> 1483 | AC61: 0 | AD61: =ROUNDUP(IF(P61>21000,0,(Y61-X61)*0.75%),0) -> 93 | AE61: =ROUND(AB61/12%*8.33%,0) -> 1029 | AF61: =+AB61-AE61 -> 454 | AG61: =IF(P61>21000,0,(Y61-X61)*3.25%) -> 401.7 | AH61: 0 | AI61: 0 | AJ61: 5763 | AK61: =IF((Y61-X61)>=20001,200,IF((Y61-X61)>=15001,150,0)) -> 0 | AL61: 0 | AM61: =AB61+AD61+AL61 -> 1576 | AN61: =SUM(ROUND((Y61)-(AH61+AI61+AJ61+AK61+AM61),0),0) -> 5021
A62: =A61+1 -> 60 | B62: JAI-833 | C62: 45033 | E62: Anchor | F62: 50100491125841 | G62: HDFC0000512 | H62: 101916714963 | I62: CMCPN1171M | J62: 5219252907 | K62: 36289 | L62: Female | M62: Semi-skilled | N62: =VLOOKUP(B62,'Anchor-Attendance'!$B$4:$K$84,10,0) -> 46072 | O62: =VLOOKUP(B62,'Anchor-Attendance'!$B$4:$BB$84,53,0) -> 19 | P62: 12360 | Q62: =P62/$O$1*O62 -> 8387.1429 | R62: =Q62*100% -> 8387.1429 | S62: 0 | T62: 0 | U62: 0 | V62: =ROUND(SUM(R62:U62),0) -> 8387 | W62: =12360-V62 -> 3973 | X62: =AR62 -> 0 | Y62: =SUM(V62:X62) -> 12360 | Z62: =ROUND(SUM(R62:U62)-S62,0) -> 8387 | AA62: =ROUND(IF(Z62>15000,15000,Z62),0) -> 8387 | AB62: =ROUND(IF(Z62>15000,1800,Z62*12%),0) -> 1006 | AC62: 0 | AD62: =ROUNDUP(IF(P62>21000,0,(Y62-X62)*0.75%),0) -> 93 | AE62: =ROUND(AB62/12%*8.33%,0) -> 698 | AF62: =+AB62-AE62 -> 308 | AG62: =IF(P62>21000,0,(Y62-X62)*3.25%) -> 401.7 | AH62: 0 | AI62: 0 | AJ62: 0 | AK62: =IF((Y62-X62)>=20001,200,IF((Y62-X62)>=15001,150,0)) -> 0 | AL62: 0 | AM62: =AB62+AD62+AL62 -> 1099 | AN62: =SUM(ROUND((Y62)-(AH62+AI62+AJ62+AK62+AM62),0),0) -> 11261 | AO62: Full month salary to be paid | AP62: =ROUND((N62-C62)/365,0) -> 3
A63: =A62+1 -> 61 | B63: JAI-880 | C63: 45033 | E63: Anchor | F63: 50100593127547 | G63: HDFC0001635 | H63: 101920510077 | I63: QHSPS3258B | J63: 5219251524 | K63: 36652 | L63: Female | M63: Semi-skilled | N63: No | O63: =VLOOKUP(B63,'Anchor-Attendance'!$B$4:$BB$84,53,0) -> 28 | P63: 12360 | Q63: =P63/$O$1*O63 -> 12360 | R63: =Q63*100% -> 12360 | S63: 0 | T63: 0 | U63: 0 | V63: =ROUND(SUM(R63:U63),0) -> 12360 | W63: 0 | X63: 0 | Y63: =SUM(V63:X63) -> 12360 | Z63: =ROUND(SUM(R63:U63)-S63,0) -> 12360 | AA63: =ROUND(IF(Z63>15000,15000,Z63),0) -> 12360 | AB63: =ROUND(IF(Z63>15000,1800,Z63*12%),0) -> 1483 | AC63: 0 | AD63: =ROUNDUP(IF(P63>21000,0,(Y63-X63)*0.75%),0) -> 93 | AE63: =ROUND(AB63/12%*8.33%,0) -> 1029 | AF63: =+AB63-AE63 -> 454 | AG63: =IF(P63>21000,0,(Y63-X63)*3.25%) -> 401.7 | AH63: 0 | AI63: 0 | AJ63: 0 | AK63: =IF((Y63-X63)>=20001,200,IF((Y63-X63)>=15001,150,0)) -> 0 | AL63: 0 | AM63: =AB63+AD63+AL63 -> 1576 | AN63: =SUM(ROUND((Y63)-(AH63+AI63+AJ63+AK63+AM63),0),0) -> 10784
A64: =A63+1 -> 62 | B64: JAI-891 | C64: 45033 | E64: Anchor | F64: 50100590041922 | G64: HDFC0009087 | H64: 101916715274 | I64: OWQPS3200E | J64: 5219246416 | K64: 38181 | L64: Female | M64: Semi-skilled | N64: No | O64: =VLOOKUP(B64,'Anchor-Attendance'!$B$4:$BB$84,53,0) -> 28 | P64: 12360 | Q64: =P64/$O$1*O64 -> 12360 | R64: =Q64*100% -> 12360 | S64: 0 | T64: 0 | U64: 0 | V64: =ROUND(SUM(R64:U64),0) -> 12360 | W64: 0 | X64: 0 | Y64: =SUM(V64:X64) -> 12360 | Z64: =ROUND(SUM(R64:U64)-S64,0) -> 12360 | AA64: =ROUND(IF(Z64>15000,15000,Z64),0) -> 12360 | AB64: =ROUND(IF(Z64>15000,1800,Z64*12%),0) -> 1483 | AC64: 0 | AD64: =ROUNDUP(IF(P64>21000,0,(Y64-X64)*0.75%),0) -> 93 | AE64: =ROUND(AB64/12%*8.33%,0) -> 1029 | AF64: =+AB64-AE64 -> 454 | AG64: =IF(P64>21000,0,(Y64-X64)*3.25%) -> 401.7 | AH64: 0 | AI64: 0 | AJ64: 0 | AK64: =IF((Y64-X64)>=20001,200,IF((Y64-X64)>=15001,150,0)) -> 0 | AL64: 0 | AM64: =AB64+AD64+AL64 -> 1576 | AN64: =SUM(ROUND((Y64)-(AH64+AI64+AJ64+AK64+AM64),0),0) -> 10784
A65: =A64+1 -> 63 | B65: JAI-906 | C65: 45033 | E65: Anchor | F65: 50100594521750 | G65: HDFC0009087 | H65: 101916215742 | I65: DRWPA0526F | J65: 5219306223 | K65: 37297 | L65: Female | M65: Semi-skilled | N65: No | O65: =VLOOKUP(B65,'Anchor-Attendance'!$B$4:$BB$84,53,0) -> 28 | P65: 12360 | Q65: =P65/$O$1*O65 -> 12360 | R65: =Q65*100% -> 12360 | S65: 0 | T65: 0 | U65: 0 | V65: =ROUND(SUM(R65:U65),0) -> 12360 | W65: 0 | X65: 0 | Y65: =SUM(V65:X65) -> 12360 | Z65: =ROUND(SUM(R65:U65)-S65,0) -> 12360 | AA65: =ROUND(IF(Z65>15000,15000,Z65),0) -> 12360 | AB65: =ROUND(IF(Z65>15000,1800,Z65*12%),0) -> 1483 | AC65: 0 | AD65: =ROUNDUP(IF(P65>21000,0,(Y65-X65)*0.75%),0) -> 93 | AE65: =ROUND(AB65/12%*8.33%,0) -> 1029 | AF65: =+AB65-AE65 -> 454 | AG65: =IF(P65>21000,0,(Y65-X65)*3.25%) -> 401.7 | AH65: 0 | AI65: 0 | AJ65: 0 | AK65: =IF((Y65-X65)>=20001,200,IF((Y65-X65)>=15001,150,0)) -> 0 | AL65: 0 | AM65: =AB65+AD65+AL65 -> 1576 | AN65: =SUM(ROUND((Y65)-(AH65+AI65+AJ65+AK65+AM65),0),0) -> 10784
A66: =A65+1 -> 64 | B66: JAI-926 | C66: 45033 | E66: Anchor | F66: 50100590014820 | G66: HDFC0009087 | H66: 101916217003 | I66: GUNPB2687F | J66: 5219296272 | K66: 37275 | L66: Female | M66: Semi-skilled | N66: No | O66: =VLOOKUP(B66,'Anchor-Attendance'!$B$4:$BB$84,53,0) -> 28 | P66: 12360 | Q66: =P66/$O$1*O66 -> 12360 | R66: =Q66*100% -> 12360 | S66: 0 | T66: 0 | U66: 0 | V66: =ROUND(SUM(R66:U66),0) -> 12360 | W66: 0 | X66: 0 | Y66: =SUM(V66:X66) -> 12360 | Z66: =ROUND(SUM(R66:U66)-S66,0) -> 12360 | AA66: =ROUND(IF(Z66>15000,15000,Z66),0) -> 12360 | AB66: =ROUND(IF(Z66>15000,1800,Z66*12%),0) -> 1483 | AC66: 0 | AD66: =ROUNDUP(IF(P66>21000,0,(Y66-X66)*0.75%),0) -> 93 | AE66: =ROUND(AB66/12%*8.33%,0) -> 1029 | AF66: =+AB66-AE66 -> 454 | AG66: =IF(P66>21000,0,(Y66-X66)*3.25%) -> 401.7 | AH66: 0 | AI66: 0 | AJ66: 0 | AK66: =IF((Y66-X66)>=20001,200,IF((Y66-X66)>=15001,150,0)) -> 0 | AL66: 0 | AM66: =AB66+AD66+AL66 -> 1576 | AN66: =SUM(ROUND((Y66)-(AH66+AI66+AJ66+AK66+AM66),0),0) -> 10784
A67: =A66+1 -> 65 | B67: JAI-1015 | C67: 45033 | E67: Anchor | F67: 50100590014833 | G67: HDFC0009087 | H67: 101916216961 | I67: QLCPS4334A | J67: 5219306282 | K67: 37054 | L67: Female | M67: Semi-skilled | N67: No | O67: =VLOOKUP(B67,'Anchor-Attendance'!$B$4:$BB$84,53,0) -> 28 | P67: 12360 | Q67: =P67/$O$1*O67 -> 12360 | R67: =Q67*100% -> 12360 | S67: 0 | T67: 0 | U67: 0 | V67: =ROUND(SUM(R67:U67),0) -> 12360 | W67: 0 | X67: 0 | Y67: =SUM(V67:X67) -> 12360 | Z67: =ROUND(SUM(R67:U67)-S67,0) -> 12360 | AA67: =ROUND(IF(Z67>15000,15000,Z67),0) -> 12360 | AB67: =ROUND(IF(Z67>15000,1800,Z67*12%),0) -> 1483 | AC67: 0 | AD67: =ROUNDUP(IF(P67>21000,0,(Y67-X67)*0.75%),0) -> 93 | AE67: =ROUND(AB67/12%*8.33%,0) -> 1029 | AF67: =+AB67-AE67 -> 454 | AG67: =IF(P67>21000,0,(Y67-X67)*3.25%) -> 401.7 | AH67: 0 | AI67: 0 | AJ67: 0 | AK67: =IF((Y67-X67)>=20001,200,IF((Y67-X67)>=15001,150,0)) -> 0 | AL67: 0 | AM67: =AB67+AD67+AL67 -> 1576 | AN67: =SUM(ROUND((Y67)-(AH67+AI67+AJ67+AK67+AM67),0),0) -> 10784
A68: =A67+1 -> 66 | B68: JAI-1029 | C68: 45033 | E68: Anchor | F68: 50100594521938 | G68: HDFC0009401 | H68: 101916715482 | I68: MPFPS4677M | J68: 5219305106 | K68: 35587 | L68: Female | M68: Semi-skilled | N68: =VLOOKUP(B68,'Anchor-Attendance'!$B$4:$K$84,10,0) -> 46060 | O68: =VLOOKUP(B68,'Anchor-Attendance'!$B$4:$BB$84,53,0) -> 2 | P68: 12360 | Q68: =P68/$O$1*O68 -> 882.85714 | R68: =Q68*100% -> 882.85714 | S68: 0 | T68: 0 | U68: 0 | V68: =ROUND(SUM(R68:U68),0) -> 883 | W68: 0 | X68: =AR68 -> 0 | Y68: =SUM(V68:X68) -> 883 | Z68: =ROUND(SUM(R68:U68)-S68,0) -> 883 | AA68: =ROUND(IF(Z68>15000,15000,Z68),0) -> 883 | AB68: =ROUND(IF(Z68>15000,1800,Z68*12%),0) -> 106 | AC68: 0 | AD68: =ROUNDUP(IF(P68>21000,0,(Y68-X68)*0.75%),0) -> 7 | AE68: =ROUND(AB68/12%*8.33%,0) -> 74 | AF68: =+AB68-AE68 -> 32 | AG68: =IF(P68>21000,0,(Y68-X68)*3.25%) -> 28.6975 | AH68: 0 | AI68: 0 | AJ68: 0 | AK68: =IF((Y68-X68)>=20001,200,IF((Y68-X68)>=15001,150,0)) -> 0 | AL68: 0 | AM68: =AB68+AD68+AL68 -> 113 | AN68: =SUM(ROUND((Y68)-(AH68+AI68+AJ68+AK68+AM68),0),0) -> 770 | AP68: =ROUND((N68-C68)/365,0) -> 3
A69: =A68+1 -> 67 | B69: JAI-1094 | C69: 45047 | E69: Anchor | F69: 50100620735829 | G69: HDFC0003059 | H69: 101935600601 | I69: FBJPB2320F | J69: 5219560268 | K69: 37205 | L69: Female | M69: Semi-skilled | N69: No | O69: =VLOOKUP(B69,'Anchor-Attendance'!$B$4:$BB$84,53,0) -> 28 | P69: 12360 | Q69: =P69/$O$1*O69 -> 12360 | R69: =Q69*100% -> 12360 | S69: 0 | T69: 0 | U69: 0 | V69: =ROUND(SUM(R69:U69),0) -> 12360 | W69: 0 | X69: 0 | Y69: =SUM(V69:X69) -> 12360 | Z69: =ROUND(SUM(R69:U69)-S69,0) -> 12360 | AA69: =ROUND(IF(Z69>15000,15000,Z69),0) -> 12360 | AB69: =ROUND(IF(Z69>15000,1800,Z69*12%),0) -> 1483 | AC69: 0 | AD69: =ROUNDUP(IF(P69>21000,0,(Y69-X69)*0.75%),0) -> 93 | AE69: =ROUND(AB69/12%*8.33%,0) -> 1029 | AF69: =+AB69-AE69 -> 454 | AG69: =IF(P69>21000,0,(Y69-X69)*3.25%) -> 401.7 | AH69: 0 | AI69: 0 | AJ69: 0 | AK69: =IF((Y69-X69)>=20001,200,IF((Y69-X69)>=15001,150,0)) -> 0 | AL69: 0 | AM69: =AB69+AD69+AL69 -> 1576 | AN69: =SUM(ROUND((Y69)-(AH69+AI69+AJ69+AK69+AM69),0),0) -> 10784
A70: =A69+1 -> 68 | B70: JAI-1095 | C70: 45047 | E70: Anchor | F70: 50100614278619 | G70: HDFC0003059 | H70: 101935600557 | I70: PXYPS1182R | J70: 5219560367 | K70: 37330 | L70: Female | M70: Semi-skilled | N70: No | O70: =VLOOKUP(B70,'Anchor-Attendance'!$B$4:$BB$84,53,0) -> 28 | P70: 12360 | Q70: =P70/$O$1*O70 -> 12360 | R70: =Q70*100% -> 12360 | S70: 0 | T70: 0 | U70: 0 | V70: =ROUND(SUM(R70:U70),0) -> 12360 | W70: 0 | X70: 0 | Y70: =SUM(V70:X70) -> 12360 | Z70: =ROUND(SUM(R70:U70)-S70,0) -> 12360 | AA70: =ROUND(IF(Z70>15000,15000,Z70),0) -> 12360 | AB70: =ROUND(IF(Z70>15000,1800,Z70*12%),0) -> 1483 | AC70: 0 | AD70: =ROUNDUP(IF(P70>21000,0,(Y70-X70)*0.75%),0) -> 93 | AE70: =ROUND(AB70/12%*8.33%,0) -> 1029 | AF70: =+AB70-AE70 -> 454 | AG70: =IF(P70>21000,0,(Y70-X70)*3.25%) -> 401.7 | AH70: 0 | AI70: 0 | AJ70: 0 | AK70: =IF((Y70-X70)>=20001,200,IF((Y70-X70)>=15001,150,0)) -> 0 | AL70: 0 | AM70: =AB70+AD70+AL70 -> 1576 | AN70: =SUM(ROUND((Y70)-(AH70+AI70+AJ70+AK70+AM70),0),0) -> 10784
A71: =A70+1 -> 69 | B71: JAI-1226 | C71: 45139 | E71: Anchor | F71: 50100643349448 | G71: HDFC0004250 | H71: 101977542162 | I71: BLYPH8180E | J71: 5219933484 | K71: 37046 | L71: Female | M71: Semi-skilled | N71: No | O71: =VLOOKUP(B71,'Anchor-Attendance'!$B$4:$BB$84,53,0) -> 28 | P71: 12360 | Q71: =P71/$O$1*O71 -> 12360 | R71: =Q71*100% -> 12360 | S71: 0 | T71: 0 | U71: 0 | V71: =ROUND(SUM(R71:U71),0) -> 12360 | W71: 0 | X71: 0 | Y71: =SUM(V71:X71) -> 12360 | Z71: =ROUND(SUM(R71:U71)-S71,0) -> 12360 | AA71: =ROUND(IF(Z71>15000,15000,Z71),0) -> 12360 | AB71: =ROUND(IF(Z71>15000,1800,Z71*12%),0) -> 1483 | AC71: 0 | AD71: =ROUNDUP(IF(P71>21000,0,(Y71-X71)*0.75%),0) -> 93 | AE71: =ROUND(AB71/12%*8.33%,0) -> 1029 | AF71: =+AB71-AE71 -> 454 | AG71: =IF(P71>21000,0,(Y71-X71)*3.25%) -> 401.7 | AH71: 0 | AI71: 0 | AJ71: 0 | AK71: =IF((Y71-X71)>=20001,200,IF((Y71-X71)>=15001,150,0)) -> 0 | AL71: 0 | AM71: =AB71+AD71+AL71 -> 1576 | AN71: =SUM(ROUND((Y71)-(AH71+AI71+AJ71+AK71+AM71),0),0) -> 10784
A72: =A71+1 -> 70 | B72: JAI-1259 | C72: 45159 | E72: Anchor | F72: 50100646519941 | G72: HDFC0003059 | H72: 101988385028 | I72: MGXPK9263J | J72: 5219994222 | K72: 35867 | L72: Female | M72: Semi-skilled | N72: No | O72: =VLOOKUP(B72,'Anchor-Attendance'!$B$4:$BB$84,53,0) -> 28 | P72: 12360 | Q72: =P72/$O$1*O72 -> 12360 | R72: =Q72*100% -> 12360 | S72: 0 | T72: 0 | U72: 0 | V72: =ROUND(SUM(R72:U72),0) -> 12360 | W72: 0 | X72: 0 | Y72: =SUM(V72:X72) -> 12360 | Z72: =ROUND(SUM(R72:U72)-S72,0) -> 12360 | AA72: =ROUND(IF(Z72>15000,15000,Z72),0) -> 12360 | AB72: =ROUND(IF(Z72>15000,1800,Z72*12%),0) -> 1483 | AC72: 0 | AD72: =ROUNDUP(IF(P72>21000,0,(Y72-X72)*0.75%),0) -> 93 | AE72: =ROUND(AB72/12%*8.33%,0) -> 1029 | AF72: =+AB72-AE72 -> 454 | AG72: =IF(P72>21000,0,(Y72-X72)*3.25%) -> 401.7 | AH72: 0 | AI72: 0 | AJ72: 0 | AK72: =IF((Y72-X72)>=20001,200,IF((Y72-X72)>=15001,150,0)) -> 0 | AL72: 0 | AM72: =AB72+AD72+AL72 -> 1576 | AN72: =SUM(ROUND((Y72)-(AH72+AI72+AJ72+AK72+AM72),0),0) -> 10784
A73: =A72+1 -> 71 | B73: JAI-1246 | C73: 45159 | E73: Anchor | F73: 50100660357253 | G73: HDFC0000642 | H73: 101992458369 | I73: KSTPK0296K | J73: 5220002041 | K73: 37594 | L73: Female | M73: Semi-skilled | N73: No | O73: =VLOOKUP(B73,'Anchor-Attendance'!$B$4:$BB$84,53,0) -> 26 | P73: 12360 | Q73: =P73/$O$1*O73 -> 11477.143 | R73: =Q73*100% -> 11477.143 | S73: 0 | T73: 0 | U73: 0 | V73: =ROUND(SUM(R73:U73),0) -> 11477 | W73: 0 | X73: 0 | Y73: =SUM(V73:X73) -> 11477 | Z73: =ROUND(SUM(R73:U73)-S73,0) -> 11477 | AA73: =ROUND(IF(Z73>15000,15000,Z73),0) -> 11477 | AB73: =ROUND(IF(Z73>15000,1800,Z73*12%),0) -> 1377 | AC73: 0 | AD73: =ROUNDUP(IF(P73>21000,0,(Y73-X73)*0.75%),0) -> 87 | AE73: =ROUND(AB73/12%*8.33%,0) -> 956 | AF73: =+AB73-AE73 -> 421 | AG73: =IF(P73>21000,0,(Y73-X73)*3.25%) -> 373.0025 | AH73: 0 | AI73: 0 | AJ73: 0 | AK73: =IF((Y73-X73)>=20001,200,IF((Y73-X73)>=15001,150,0)) -> 0 | AL73: 0 | AM73: =AB73+AD73+AL73 -> 1464 | AN73: =SUM(ROUND((Y73)-(AH73+AI73+AJ73+AK73+AM73),0),0) -> 10013
A74: =A73+1 -> 72 | B74: JAI-1251 | C74: 45159 | E74: Anchor | F74: 50100651126190 | G74: HDFC0009087 | H74: 101988384848 | I74: NYFPK7090N | J74: 5220003707 | K74: 37057 | L74: Female | M74: Semi-skilled | N74: No | O74: =VLOOKUP(B74,'Anchor-Attendance'!$B$4:$BB$84,53,0) -> 28 | P74: 12360 | Q74: =P74/$O$1*O74 -> 12360 | R74: =Q74*100% -> 12360 | S74: 0 | T74: 0 | U74: 0 | V74: =ROUND(SUM(R74:U74),0) -> 12360 | W74: 0 | X74: 0 | Y74: =SUM(V74:X74) -> 12360 | Z74: =ROUND(SUM(R74:U74)-S74,0) -> 12360 | AA74: =ROUND(IF(Z74>15000,15000,Z74),0) -> 12360 | AB74: =ROUND(IF(Z74>15000,1800,Z74*12%),0) -> 1483 | AC74: 0 | AD74: =ROUNDUP(IF(P74>21000,0,(Y74-X74)*0.75%),0) -> 93 | AE74: =ROUND(AB74/12%*8.33%,0) -> 1029 | AF74: =+AB74-AE74 -> 454 | AG74: =IF(P74>21000,0,(Y74-X74)*3.25%) -> 401.7 | AH74: 0 | AI74: 0 | AJ74: 0 | AK74: =IF((Y74-X74)>=20001,200,IF((Y74-X74)>=15001,150,0)) -> 0 | AL74: 0 | AM74: =AB74+AD74+AL74 -> 1576 | AN74: =SUM(ROUND((Y74)-(AH74+AI74+AJ74+AK74+AM74),0),0) -> 10784
A75: =A74+1 -> 73 | B75: JAI-1264 | C75: 45159 | E75: Anchor | F75: 50100646504312 | G75: HDFC0000512 | H75: 101988385092 | I75: DCKPN1130H | J75: 5220004441 | K75: 36849 | L75: Female | M75: Semi-skilled | N75: No | O75: =VLOOKUP(B75,'Anchor-Attendance'!$B$4:$BB$84,53,0) -> 28 | P75: 12360 | Q75: =P75/$O$1*O75 -> 12360 | R75: =Q75*100% -> 12360 | S75: 0 | T75: 0 | U75: 0 | V75: =ROUND(SUM(R75:U75),0) -> 12360 | W75: 0 | X75: 0 | Y75: =SUM(V75:X75) -> 12360 | Z75: =ROUND(SUM(R75:U75)-S75,0) -> 12360 | AA75: =ROUND(IF(Z75>15000,15000,Z75),0) -> 12360 | AB75: =ROUND(IF(Z75>15000,1800,Z75*12%),0) -> 1483 | AC75: 0 | AD75: =ROUNDUP(IF(P75>21000,0,(Y75-X75)*0.75%),0) -> 93 | AE75: =ROUND(AB75/12%*8.33%,0) -> 1029 | AF75: =+AB75-AE75 -> 454 | AG75: =IF(P75>21000,0,(Y75-X75)*3.25%) -> 401.7 | AH75: 0 | AI75: 0 | AJ75: 0 | AK75: =IF((Y75-X75)>=20001,200,IF((Y75-X75)>=15001,150,0)) -> 0 | AL75: 0 | AM75: =AB75+AD75+AL75 -> 1576 | AN75: =SUM(ROUND((Y75)-(AH75+AI75+AJ75+AK75+AM75),0),0) -> 10784
A76: =A75+1 -> 74 | B76: JAI-1280 | C76: 45159 | E76: Anchor | F76: 50100646504029 | G76: HDFC0000512 | H76: 101988385156 | I76: GPBPR1524A | J76: 5219999187 | K76: 36661 | L76: Female | M76: Semi-skilled | N76: No | O76: =VLOOKUP(B76,'Anchor-Attendance'!$B$4:$BB$84,53,0) -> 28 | P76: 12360 | Q76: =P76/$O$1*O76 -> 12360 | R76: =Q76*100% -> 12360 | S76: 0 | T76: 0 | U76: 0 | V76: =ROUND(SUM(R76:U76),0) -> 12360 | W76: 0 | X76: 0 | Y76: =SUM(V76:X76) -> 12360 | Z76: =ROUND(SUM(R76:U76)-S76,0) -> 12360 | AA76: =ROUND(IF(Z76>15000,15000,Z76),0) -> 12360 | AB76: =ROUND(IF(Z76>15000,1800,Z76*12%),0) -> 1483 | AC76: 0 | AD76: =ROUNDUP(IF(P76>21000,0,(Y76-X76)*0.75%),0) -> 93 | AE76: =ROUND(AB76/12%*8.33%,0) -> 1029 | AF76: =+AB76-AE76 -> 454 | AG76: =IF(P76>21000,0,(Y76-X76)*3.25%) -> 401.7 | AH76: 0 | AI76: 0 | AJ76: 0 | AK76: =IF((Y76-X76)>=20001,200,IF((Y76-X76)>=15001,150,0)) -> 0 | AL76: 0 | AM76: =AB76+AD76+AL76 -> 1576 | AN76: =SUM(ROUND((Y76)-(AH76+AI76+AJ76+AK76+AM76),0),0) -> 10784
A77: =A76+1 -> 75 | B77: JAI-1284 | C77: 45159 | E77: Anchor | F77: 50100524321492 | G77: HDFC0005831 | H77: 101838768093 | I77: POVPS2348B | J77: 5220010002 | K77: 37427 | L77: Female | M77: Semi-skilled | N77: =VLOOKUP(B77,'Anchor-Attendance'!$B$4:$K$84,10,0) -> 46072 | O77: =VLOOKUP(B77,'Anchor-Attendance'!$B$4:$BB$84,53,0) -> 19 | P77: 12360 | Q77: =P77/$O$1*O77 -> 8387.1429 | R77: =Q77*100% -> 8387.1429 | S77: 0 | T77: 0 | U77: 0 | V77: =ROUND(SUM(R77:U77),0) -> 8387 | W77: =12360-V77 -> 3973 | X77: =AR77 -> 0 | Y77: =SUM(V77:X77) -> 12360 | Z77: =ROUND(SUM(R77:U77)-S77,0) -> 8387 | AA77: =ROUND(IF(Z77>15000,15000,Z77),0) -> 8387 | AB77: =ROUND(IF(Z77>15000,1800,Z77*12%),0) -> 1006 | AC77: 0 | AD77: =ROUNDUP(IF(P77>21000,0,(Y77-X77)*0.75%),0) -> 93 | AE77: =ROUND(AB77/12%*8.33%,0) -> 698 | AF77: =+AB77-AE77 -> 308 | AG77: =IF(P77>21000,0,(Y77-X77)*3.25%) -> 401.7 | AH77: 0 | AI77: 0 | AJ77: 0 | AK77: =IF((Y77-X77)>=20001,200,IF((Y77-X77)>=15001,150,0)) -> 0 | AL77: 0 | AM77: =AB77+AD77+AL77 -> 1099 | AN77: =SUM(ROUND((Y77)-(AH77+AI77+AJ77+AK77+AM77),0),0) -> 11261 | AO77: Full month salary to be paid | AP77: =ROUND((N77-C77)/365,0) -> 3
A78: =A77+1 -> 76 | B78: JAI-1287 | C78: 45159 | E78: Anchor | F78: 50100660357214 | G78: HDFC0000642 | H78: 101988384998 | I78: OGDPS1081L | J78: 5219999566 | K78: 37070 | L78: Female | M78: Semi-skilled | N78: No | O78: =VLOOKUP(B78,'Anchor-Attendance'!$B$4:$BB$84,53,0) -> 28 | P78: 12360 | Q78: =P78/$O$1*O78 -> 12360 | R78: =Q78*100% -> 12360 | S78: 0 | T78: 0 | U78: 0 | V78: =ROUND(SUM(R78:U78),0) -> 12360 | W78: 0 | X78: 0 | Y78: =SUM(V78:X78) -> 12360 | Z78: =ROUND(SUM(R78:U78)-S78,0) -> 12360 | AA78: =ROUND(IF(Z78>15000,15000,Z78),0) -> 12360 | AB78: =ROUND(IF(Z78>15000,1800,Z78*12%),0) -> 1483 | AC78: 0 | AD78: =ROUNDUP(IF(P78>21000,0,(Y78-X78)*0.75%),0) -> 93 | AE78: =ROUND(AB78/12%*8.33%,0) -> 1029 | AF78: =+AB78-AE78 -> 454 | AG78: =IF(P78>21000,0,(Y78-X78)*3.25%) -> 401.7 | AH78: 0 | AI78: 0 | AJ78: 0 | AK78: =IF((Y78-X78)>=20001,200,IF((Y78-X78)>=15001,150,0)) -> 0 | AL78: 0 | AM78: =AB78+AD78+AL78 -> 1576 | AN78: =SUM(ROUND((Y78)-(AH78+AI78+AJ78+AK78+AM78),0),0) -> 10784
A79: =A78+1 -> 77 | B79: JAI-1314 | C79: 45217 | E79: Anchor | F79: 50100678876851 | G79: HDFC0009087 | H79: 102012168883 | I79: FIUPA1549F | J79: 5220197385 | K79: 37368 | L79: Female | M79: Semi-skilled | N79: =VLOOKUP(B79,'Anchor-Attendance'!$B$4:$K$84,10,0) -> 46062 | O79: =VLOOKUP(B79,'Anchor-Attendance'!$B$4:$BB$84,53,0) -> 9 | P79: 12360 | Q79: =P79/$O$1*O79 -> 3972.8571 | R79: =Q79*100% -> 3972.8571 | S79: 0 | T79: 0 | U79: 0 | V79: =ROUND(SUM(R79:U79),0) -> 3973 | W79: 0 | X79: =AR79 -> 0 | Y79: =SUM(V79:X79) -> 3973 | Z79: =ROUND(SUM(R79:U79)-S79,0) -> 3973 | AA79: =ROUND(IF(Z79>15000,15000,Z79),0) -> 3973 | AB79: =ROUND(IF(Z79>15000,1800,Z79*12%),0) -> 477 | AC79: 0 | AD79: =ROUNDUP(IF(P79>21000,0,(Y79-X79)*0.75%),0) -> 30 | AE79: =ROUND(AB79/12%*8.33%,0) -> 331 | AF79: =+AB79-AE79 -> 146 | AG79: =IF(P79>21000,0,(Y79-X79)*3.25%) -> 129.1225 | AH79: 0 | AI79: 0 | AJ79: 0 | AK79: =IF((Y79-X79)>=20001,200,IF((Y79-X79)>=15001,150,0)) -> 0 | AL79: 0 | AM79: =AB79+AD79+AL79 -> 507 | AN79: =SUM(ROUND((Y79)-(AH79+AI79+AJ79+AK79+AM79),0),0) -> 3466 | AP79: =ROUND((N79-C79)/365,0) -> 2
A80: =A79+1 -> 78 | B80: JAI-1316 | C80: 45217 | E80: Anchor | F80: 50100678876887 | G80: HDFC0009087 | H80: 101737403301 | I80: BQCPL8157Q | J80: 5220197291 | K80: 36337 | L80: Female | M80: Semi-skilled | N80: No | O80: =VLOOKUP(B80,'Anchor-Attendance'!$B$4:$BB$84,53,0) -> 28 | P80: 12360 | Q80: =P80/$O$1*O80 -> 12360 | R80: =Q80*100% -> 12360 | S80: 0 | T80: 0 | U80: 0 | V80: =ROUND(SUM(R80:U80),0) -> 12360 | W80: 0 | X80: 0 | Y80: =SUM(V80:X80) -> 12360 | Z80: =ROUND(SUM(R80:U80)-S80,0) -> 12360 | AA80: =ROUND(IF(Z80>15000,15000,Z80),0) -> 12360 | AB80: =ROUND(IF(Z80>15000,1800,Z80*12%),0) -> 1483 | AC80: 0 | AD80: =ROUNDUP(IF(P80>21000,0,(Y80-X80)*0.75%),0) -> 93 | AE80: =ROUND(AB80/12%*8.33%,0) -> 1029 | AF80: =+AB80-AE80 -> 454 | AG80: =IF(P80>21000,0,(Y80-X80)*3.25%) -> 401.7 | AH80: 0 | AI80: 0 | AJ80: 0 | AK80: =IF((Y80-X80)>=20001,200,IF((Y80-X80)>=15001,150,0)) -> 0 | AL80: 0 | AM80: =AB80+AD80+AL80 -> 1576 | AN80: =SUM(ROUND((Y80)-(AH80+AI80+AJ80+AK80+AM80),0),0) -> 10784
A81: =A80+1 -> 79 | B81: JAI-1325 | C81: 45292 | E81: Anchor | F81: 50100373849430 | G81: HDFC0001635 | H81: 101636967755 | I81: CAGPV5847L | J81: 5216750890 | K81: 36378 | L81: Female | M81: Semi-skilled | N81: =VLOOKUP(B81,'Anchor-Attendance'!$B$4:$K$84,10,0) -> 46058 | O81: =VLOOKUP(B81,'Anchor-Attendance'!$B$4:$BB$84,53,0) -> 2 | P81: 12360 | Q81: =P81/$O$1*O81 -> 882.85714 | R81: =Q81*100% -> 882.85714 | S81: 0 | T81: 0 | U81: 0 | V81: =ROUND(SUM(R81:U81),0) -> 883 | W81: 0 | X81: =AR81 -> 0 | Y81: =SUM(V81:X81) -> 883 | Z81: =ROUND(SUM(R81:U81)-S81,0) -> 883 | AA81: =ROUND(IF(Z81>15000,15000,Z81),0) -> 883 | AB81: =ROUND(IF(Z81>15000,1800,Z81*12%),0) -> 106 | AC81: 0 | AD81: =ROUNDUP(IF(P81>21000,0,(Y81-X81)*0.75%),0) -> 7 | AE81: =ROUND(AB81/12%*8.33%,0) -> 74 | AF81: =+AB81-AE81 -> 32 | AG81: =IF(P81>21000,0,(Y81-X81)*3.25%) -> 28.6975 | AH81: 0 | AI81: 0 | AJ81: 0 | AK81: =IF((Y81-X81)>=20001,200,IF((Y81-X81)>=15001,150,0)) -> 0 | AL81: 0 | AM81: =AB81+AD81+AL81 -> 113 | AN81: =SUM(ROUND((Y81)-(AH81+AI81+AJ81+AK81+AM81),0),0) -> 770 | AP81: =ROUND((N81-C81)/365,0) -> 2
A82: =A81+1 -> 80 | B82: JAI-1381 | C82: 45748 | E82: Anchor | F82: 50100453957422 | G82: HDFC0001635 | H82: 101758025867 | I82: GMZPP9889M | J82: 5217966593 | K82: 36778 | L82: Female | M82: Semi-skilled | N82: No | O82: =VLOOKUP(B82,'Anchor-Attendance'!$B$4:$BB$84,53,0) -> 28 | P82: 12360 | Q82: =P82/$O$1*O82 -> 12360 | R82: =Q82*100% -> 12360 | S82: 0 | T82: 0 | U82: 0 | V82: =ROUND(SUM(R82:U82),0) -> 12360 | W82: 0 | X82: 0 | Y82: =SUM(V82:X82) -> 12360 | Z82: =ROUND(SUM(R82:U82)-S82,0) -> 12360 | AA82: =ROUND(IF(Z82>15000,15000,Z82),0) -> 12360 | AB82: =ROUND(IF(Z82>15000,1800,Z82*12%),0) -> 1483 | AC82: 0 | AD82: =ROUNDUP(IF(P82>21000,0,(Y82-X82)*0.75%),0) -> 93 | AE82: =ROUND(AB82/12%*8.33%,0) -> 1029 | AF82: =+AB82-AE82 -> 454 | AG82: =IF(P82>21000,0,(Y82-X82)*3.25%) -> 401.7 | AH82: 0 | AI82: 0 | AJ82: 0 | AK82: =IF((Y82-X82)>=20001,200,IF((Y82-X82)>=15001,150,0)) -> 0 | AL82: 0 | AM82: =AB82+AD82+AL82 -> 1576 | AN82: =SUM(ROUND((Y82)-(AH82+AI82+AJ82+AK82+AM82),0),0) -> 10784
AP83: =ROUND((N83-C83)/365,0) -> 0 | AQ83: =P83 -> 0 | AR83: =ROUND(AQ83*15/26*AP83,0) -> 0
R84: =SUM(R3:R83) -> 884172.86 | S84: =SUM(S3:S83) -> 5100 | T84: =SUM(T3:T83) -> 0 | U84: =SUM(U3:U83) -> 0 | V84: =SUM(V3:V83) -> 889272 | W84: =SUM(W3:W83) -> 37743 | X84: =SUM(X3:X83) -> 156878 | Y84: =SUM(Y3:Y83) -> 1083893 | ... AN84: =SUM(AN3:AN83) -> 964722

Sheet Anchor-Attendance
D1: Customer | E1: Project | F1: Sub Project | G1: Work Location | H1: Mobile Numbers | I1: Mail Id's | J1: Jukshio DOJ | K1: DOE | L1: Sun | M1: Mon | N1: Tue | O1: Wed | P1: Thu | Q1: Fri | R1: Sat | S1: Sun | T1: Mon | U1: Tue | V1: Wed | W1: Thu | X1: Fri | Y1: Sat | Z1: Sun | AA1: Mon | AB1: Tue | AC1: Wed | AD1: Thu | AE1: Fri | AF1: Sat | AG1: Sun | AH1: Mon | AI1: Tue | AJ1: Wed | AK1: Thu | AL1: Fri | AM1: Sat | AN1: TD | AO1: W/O | AP1: L | AQ1: HFL | AR1: H | AS1: MG | AT1: ML | AU1: UL | AV1: MC | AW1: BL | AX1: MDL | AY1: LOP | AZ1: TD | BD1: November Opening leaves | BJ1: Present month leave utilization | BP1: Closing Leaves
A2: S.NO | B2: EMP ID | C2: Names | L2: 1 | M2: 2 | N2: 3 | O2: 4 | P2: 5 | Q2: 6 | R2: 7 | S2: 8 | T2: 9 | U2: 10 | V2: 11 | W2: 12 | X2: 13 | Y2: 14 | Z2: 15 | AA2: 16 | AB2: 17 | AC2: 18 | AD2: 19 | AE2: 20 | AF2: 21 | AG2: 22 | AH2: 23 | AI2: 24 | AJ2: 25 | AK2: 26 | AL2: 27 | AM2: 28 | AN2: Total Present | AO2: Total Week Offs | AP2: Total Leaves | AQ2: Total Half Day Leaves | AR2: Holiday | AS2: Marriage | AT2: Maternity Leave | AU2: UnPaid Leave | AV2: Misscarriage | AW2: Bereavement Leaves | AX2: Medical Leave | AY2: Loss of Pay | AZ2: Total Days | BA2: Total Actual Days | BB2: Total Payable Days | BC2: Total % | BD2: Last Year Carry Forward Leave's | BE2: CL | BF2: SL | BG2: EL | BH2: MG | BI2: Extra EL Balance | BJ2: Last Year Carry Forward Leave's | BK2: CL | BL2: SL | BM2: EL | BN2: MG | BO2: Lop | BP2: Last Year Carry Forward Leave's | BQ2: CL | BR2: SL | BS2: EL | BT2: MG | BU2: Extra EL Balance | BV2: Feb'26 Attendance Comments | BW2: Jan'26 Attendance Comments
BE3: 0.5 | BF3: 0.5 | BG3: 1 | BI3: 0.25
A4: 1 | B4: JAI-148 | D4: Manappuram/Muthoot/Bajaj | E4: KYC | F4: Birdman | G4: Suvali | H4: 8688615667 | I4: poojitha.gundlapalli@jukshio.com | J4: 44075 | L4: W/O | M4: P | N4: P | O4: P | P4: P | Q4: P | R4: P | S4: W/O | T4: P | U4: P | V4: P | W4: P | X4: P | Y4: W/O | Z4: P | AA4: P | AB4: P | AC4: P | AD4: P | AE4: P | AF4: P | AG4: W/O | AH4: P | AI4: P | AJ4: W/O | AK4: P | AL4: P | AM4: P | AN4: =COUNTIF(L4:AM4,"P")+COUNTIF(L4:AM4,"HFL")/2 -> 23 | AO4: =COUNTIF(L4:AM4,"W/O") -> 5 | AP4: =COUNTIF(L4:AM4,"L") -> 0 | AQ4: =COUNTIF(L4:AM4,"HFL")/2 -> 0 | AR4: =COUNTIF(L4:AM4,"H") -> 0 | AS4: =COUNTIF(L4:AM4,"MG") -> 0 | AT4: =COUNTIF(L4:AM4,"ML") -> 0 | AU4: =COUNTIF(L4:AM4,"UL") -> 0 | AV4: =COUNTIF(L4:AM4,"MC") -> 0 | AW4: =COUNTIF(L4:AM4,"BL") -> 0 | AX4: =COUNTIF(L4:AM4,"MDL") -> 0 | AY4: =COUNTIF(L4:AM4,"LOP") -> 0 | AZ4: =SUM(AN4:AY4) -> 28 | BA4: =SUM(AP4:AQ4,AS4:AY4,AN4) -> 23 | BB4: =AZ4-(AU4+BO4) -> 28 | BC4: =AN4/BA4 -> 1 | BD4: =VLOOKUP(B4,'Jan''26- Leave Bal'!$B$3:$D$83,3,0) -> 0 | BE4: =VLOOKUP(B4,'Jan''26- Leave Bal'!$B$3:$E$83,4,0)+$BE$3 -> 1 | BF4: =VLOOKUP(B4,'Jan''26- Leave Bal'!$B$3:$F$83,5,0)+$BF$3 -> 2.5 | BG4: =VLOOKUP(B4,'Jan''26- Leave Bal'!$B$3:$G$83,6,0)+$BG$3 -> 13 | BH4: =VLOOKUP(B4,'Jan''26- Leave Bal'!$B$3:$H$83,7,0) -> 15 | BI4: =VLOOKUP(B4,'Jan''26- Leave Bal'!$B$3:$I$83,8,0)+$BI$3 -> 0.75 | BJ4: =IF((AP4+AQ4)<=BD4, (AP4+AQ4),BD4) -> 0 | BK4: =IF(((AP4+AQ4)-BJ4)>BE4,BE4,(AP4+AQ4)-BJ4) -> 0 | BL4: =IF((AP4+AQ4-BJ4-BK4)>=BF4,BF4,(AP4+AQ4-BJ4-BK4)) -> 0 | BM4: =IF((AP4+AQ4-BJ4-BK4-BL4)>=BG4,BG4,(AP4+AQ4-BJ4-BK4-BL4)) -> 0 | BN4: =AS4 -> 0 | BO4: =AP4+AQ4-BJ4-BK4-BL4-BM4 -> 0 | BP4: =BD4-BJ4 -> 0 | BQ4: =BE4-BK4 -> 1 | BR4: =BF4-BL4 -> 2.5 | BS4: =BG4-BM4 -> 13 | BT4: =BH4-BN4 -> 15 | BU4: =BI4 -> 0.75 | BV4: 01st Mar weekoff taken in Feb Last week itself | BW4: 0
A5: 2 | B5: JAI-394 | D5: Manappuram/Muthoot/Bajaj | E5: KYC | F5: Birdman | G5: Suvali | H5: 7995932074 | I5: swathi.baddam@jukshio.com | J5: 44522 | L5: W/O | M5: P | N5: P | O5: P | P5: P | Q5: P | R5: W/O | S5: P | T5: P | U5: P | V5: P | W5: P | X5: P | Y5: P | Z5: W/O | AA5: P | AB5: P | AC5: P | AD5: P | AE5: P | AF5: W/O | AG5: P | AH5: P | AI5: P | AJ5: P | AK5: P | AL5: P | AM5: P | AN5: =COUNTIF(L5:AM5,"P")+COUNTIF(L5:AM5,"HFL")/2 -> 24 | AO5: =COUNTIF(L5:AM5,"W/O") -> 4 | AP5: =COUNTIF(L5:AM5,"L") -> 0 | AQ5: =COUNTIF(L5:AM5,"HFL")/2 -> 0 | AR5: =COUNTIF(L5:AM5,"H") -> 0 | AS5: =COUNTIF(L5:AM5,"MG") -> 0 | AT5: =COUNTIF(L5:AM5,"ML") -> 0 | AU5: =COUNTIF(L5:AM5,"UL") -> 0 | AV5: =COUNTIF(L5:AM5,"MC") -> 0 | AW5: =COUNTIF(L5:AM5,"BL") -> 0 | AX5: =COUNTIF(L5:AM5,"MDL") -> 0 | AY5: =COUNTIF(L5:AM5,"LOP") -> 0 | AZ5: =SUM(AN5:AY5) -> 28 | BA5: =SUM(AP5:AQ5,AS5:AY5,AN5) -> 24 | BB5: =AZ5-(AU5+BO5) -> 28 | BC5: =AN5/BA5 -> 1 | BD5: =VLOOKUP(B5,'Jan''26- Leave Bal'!$B$3:$D$83,3,0) -> 0 | BE5: =VLOOKUP(B5,'Jan''26- Leave Bal'!$B$3:$E$83,4,0)+$BE$3 -> 0.5 | BF5: =VLOOKUP(B5,'Jan''26- Leave Bal'!$B$3:$F$83,5,0)+$BF$3 -> 0.5 | BG5: =VLOOKUP(B5,'Jan''26- Leave Bal'!$B$3:$G$83,6,0)+$BG$3 -> 6.5 | BH5: =VLOOKUP(B5,'Jan''26- Leave Bal'!$B$3:$H$83,7,0) -> 15 | BI5: =VLOOKUP(B5,'Jan''26- Leave Bal'!$B$3:$I$83,8,0)+$BI$3 -> 0.75 | BJ5: =IF((AP5+AQ5)<=BD5, (AP5+AQ5),BD5) -> 0 | BK5: =IF(((AP5+AQ5)-BJ5)>BE5,BE5,(AP5+AQ5)-BJ5) -> 0 | BL5: =IF((AP5+AQ5-BJ5-BK5)>=BF5,BF5,(AP5+AQ5-BJ5-BK5)) -> 0 | BM5: =IF((AP5+AQ5-BJ5-BK5-BL5)>=BG5,BG5,(AP5+AQ5-BJ5-BK5-BL5)) -> 0 | BN5: =AS5 -> 0 | BO5: =AP5+AQ5-BJ5-BK5-BL5-BM5 -> 0 | BP5: =BD5-BJ5 -> 0 | BQ5: =BE5-BK5 -> 0.5 | BR5: =BF5-BL5 -> 0.5 | BS5: =BG5-BM5 -> 6.5 | BT5: =BH5-BN5 -> 15 | BU5: =BI5 -> 0.75 | BW5: 0
A6: 3 | B6: JAI-502 | D6: Manappuram/Muthoot/Bajaj | E6: KYC | F6: Birdman | G6: Suvali | H6: 9052853216 | I6: balajyothi.somana@jukshio.com | J6: 44845 | L6: P | M6: P | N6: P | O6: HFL | P6: L | Q6: P | R6: P | S6: W/O | T6: P | U6: P | V6: P | W6: P | X6: P | Y6: W/O | Z6: P | AA6: P | AB6: P | AC6: P | AD6: P | AE6: P | AF6: P | AG6: W/O | AH6: P | AI6: P | AJ6: W/O | AK6: P | AL6: P | AM6: P | AN6: =COUNTIF(L6:AM6,"P")+COUNTIF(L6:AM6,"HFL")/2 -> 22.5 | AO6: =COUNTIF(L6:AM6,"W/O") -> 4 | AP6: =COUNTIF(L6:AM6,"L") -> 1 | AQ6: =COUNTIF(L6:AM6,"HFL")/2 -> 0.5 | AR6: =COUNTIF(L6:AM6,"H") -> 0 | AS6: =COUNTIF(L6:AM6,"MG") -> 0 | AT6: =COUNTIF(L6:AM6,"ML") -> 0 | AU6: =COUNTIF(L6:AM6,"UL") -> 0 | AV6: =COUNTIF(L6:AM6,"MC") -> 0 | AW6: =COUNTIF(L6:AM6,"BL") -> 0 | AX6: =COUNTIF(L6:AM6,"MDL") -> 0 | AY6: =COUNTIF(L6:AM6,"LOP") -> 0 | AZ6: =SUM(AN6:AY6) -> 28 | BA6: =SUM(AP6:AQ6,AS6:AY6,AN6) -> 24 | BB6: =AZ6-(AU6+BO6) -> 28 | BC6: =AN6/BA6 -> 0.9375 | BD6: =VLOOKUP(B6,'Jan''26- Leave Bal'!$B$3:$D$83,3,0) -> 0 | BE6: =VLOOKUP(B6,'Jan''26- Leave Bal'!$B$3:$E$83,4,0)+$BE$3 -> 0.5 | BF6: =VLOOKUP(B6,'Jan''26- Leave Bal'!$B$3:$F$83,5,0)+$BF$3 -> 0.5 | BG6: =VLOOKUP(B6,'Jan''26- Leave Bal'!$B$3:$G$83,6,0)+$BG$3 -> 6.5 | BH6: =VLOOKUP(B6,'Jan''26- Leave Bal'!$B$3:$H$83,7,0) -> 15 | BI6: =VLOOKUP(B6,'Jan''26- Leave Bal'!$B$3:$I$83,8,0)+$BI$3 -> 0.75 | BJ6: =IF((AP6+AQ6)<=BD6, (AP6+AQ6),BD6) -> 0 | BK6: =IF(((AP6+AQ6)-BJ6)>BE6,BE6,(AP6+AQ6)-BJ6) -> 0.5 | BL6: =IF((AP6+AQ6-BJ6-BK6)>=BF6,BF6,(AP6+AQ6-BJ6-BK6)) -> 0.5 | BM6: =IF((AP6+AQ6-BJ6-BK6-BL6)>=BG6,BG6,(AP6+AQ6-BJ6-BK6-BL6)) -> 0.5 | BN6: =AS6 -> 0 | BO6: =AP6+AQ6-BJ6-BK6-BL6-BM6 -> 0 | BP6: =BD6-BJ6 -> 0 | BQ6: =BE6-BK6 -> 0 | BR6: =BF6-BL6 -> 0 | BS6: =BG6-BM6 -> 6 | BT6: =BH6-BN6 -> 15 | BU6: =BI6 -> 0.75 | BV6: 01st Mar weekoff taken in Feb Last week itself | BW6: 01st feb Weekoff taken early in Jan'26
A7: 4 | B7: JAI-098 | D7: Manappuram/Muthoot/Bajaj | E7: KYC | F7: Birdman | G7: Suvali | H7: 9381993843 | I7: parijatha.paka@jukshio.com | J7: 43983 | L7: P | M7: P | N7: W/O | O7: L | P7: P | Q7: P | R7: P | S7: P | T7: P | U7: P | V7: P | W7: P | X7: W/O | Y7: P | Z7: P | AA7: P | AB7: P | AC7: W/O | AD7: P | AE7: P | AF7: L | AG7: P | AH7: P | AI7: P | AJ7: P | AK7: P | AL7: P | AM7: P | AN7: =COUNTIF(L7:AM7,"P")+COUNTIF(L7:AM7,"HFL")/2 -> 23 | AO7: =COUNTIF(L7:AM7,"W/O") -> 3 | AP7: =COUNTIF(L7:AM7,"L") -> 2 | AQ7: =COUNTIF(L7:AM7,"HFL")/2 -> 0 | AR7: =COUNTIF(L7:AM7,"H") -> 0 | AS7: =COUNTIF(L7:AM7,"MG") -> 0 | AT7: =COUNTIF(L7:AM7,"ML") -> 0 | AU7: =COUNTIF(L7:AM7,"UL") -> 0 | AV7: =COUNTIF(L7:AM7,"MC") -> 0 | AW7: =COUNTIF(L7:AM7,"BL") -> 0 | AX7: =COUNTIF(L7:AM7,"MDL") -> 0 | AY7: =COUNTIF(L7:AM7,"LOP") -> 0 | AZ7: =SUM(AN7:AY7) -> 28 | BA7: =SUM(AP7:AQ7,AS7:AY7,AN7) -> 25 | BB7: =AZ7-(AU7+BO7) -> 28 | BC7: =AN7/BA7 -> 0.92 | BD7: =VLOOKUP(B7,'Jan''26- Leave Bal'!$B$3:$D$83,3,0) -> 0 | BE7: =VLOOKUP(B7,'Jan''26- Leave Bal'!$B$3:$E$83,4,0)+$BE$3 -> 0.5 | BF7: =VLOOKUP(B7,'Jan''26- Leave Bal'!$B$3:$F$83,5,0)+$BF$3 -> 0.5 | BG7: =VLOOKUP(B7,'Jan''26- Leave Bal'!$B$3:$G$83,6,0)+$BG$3 -> 1 | BH7: =VLOOKUP(B7,'Jan''26- Leave Bal'!$B$3:$H$83,7,0) -> 15 | BI7: =VLOOKUP(B7,'Jan''26- Leave Bal'!$B$3:$I$83,8,0)+$BI$3 -> 0.75 | BJ7: =IF((AP7+AQ7)<=BD7, (AP7+AQ7),BD7) -> 0 | BK7: =IF(((AP7+AQ7)-BJ7)>BE7,BE7,(AP7+AQ7)-BJ7) -> 0.5 | BL7: =IF((AP7+AQ7-BJ7-BK7)>=BF7,BF7,(AP7+AQ7-BJ7-BK7)) -> 0.5 | BM7: =IF((AP7+AQ7-BJ7-BK7-BL7)>=BG7,BG7,(AP7+AQ7-BJ7-BK7-BL7)) -> 1 | BN7: =AS7 -> 0 | BO7: =AP7+AQ7-BJ7-BK7-BL7-BM7 -> 0 | BP7: =BD7-BJ7 -> 0 | BQ7: =BE7-BK7 -> 0 | BR7: =BF7-BL7 -> 0 | BS7: =BG7-BM7 -> 0 | BT7: =BH7-BN7 -> 15 | BU7: =BI7 -> 0.75 | BW7: 01st feb Weekoff taken early in Jan'26
A8: 5 | B8: JAI-265 | D8: Manappuram/Muthoot/Bajaj | E8: KYC | F8: Birdman | G8: Suvali | H8: 9381626507 | I8: shravya.busha@jukshio.com | J8: 44326 | L8: HFL | M8: W/O | N8: P | O8: P | P8: P | Q8: P | R8: P | S8: P | T8: P | U8: P | V8: P | W8: P | X8: P | Y8: P | Z8: W/O | AA8: P | AB8: P | AC8: P | AD8: P | AE8: W/O | AF8: L | AG8: L | AH8: P | AI8: P | AJ8: P | AK8: P | AL8: P | AM8: P | AN8: =COUNTIF(L8:AM8,"P")+COUNTIF(L8:AM8,"HFL")/2 -> 22.5 | AO8: =COUNTIF(L8:AM8,"W/O") -> 3 | AP8: =COUNTIF(L8:AM8,"L") -> 2 | AQ8: =COUNTIF(L8:AM8,"HFL")/2 -> 0.5 | AR8: =COUNTIF(L8:AM8,"H") -> 0 | AS8: =COUNTIF(L8:AM8,"MG") -> 0 | AT8: =COUNTIF(L8:AM8,"ML") -> 0 | AU8: =COUNTIF(L8:AM8,"UL") -> 0 | AV8: =COUNTIF(L8:AM8,"MC") -> 0 | AW8: =COUNTIF(L8:AM8,"BL") -> 0 | AX8: =COUNTIF(L8:AM8,"MDL") -> 0 | AY8: =COUNTIF(L8:AM8,"LOP") -> 0 | AZ8: =SUM(AN8:AY8) -> 28 | BA8: =SUM(AP8:AQ8,AS8:AY8,AN8) -> 25 | BB8: =AZ8-(AU8+BO8) -> 28 | BC8: =AN8/BA8 -> 0.9 | BD8: =VLOOKUP(B8,'Jan''26- Leave Bal'!$B$3:$D$83,3,0) -> 0 | BE8: =VLOOKUP(B8,'Jan''26- Leave Bal'!$B$3:$E$83,4,0)+$BE$3 -> 0.5 | BF8: =VLOOKUP(B8,'Jan''26- Leave Bal'!$B$3:$F$83,5,0)+$BF$3 -> 2.5 | BG8: =VLOOKUP(B8,'Jan''26- Leave Bal'!$B$3:$G$83,6,0)+$BG$3 -> 11 | BH8: =VLOOKUP(B8,'Jan''26- Leave Bal'!$B$3:$H$83,7,0) -> 0 | BI8: =VLOOKUP(B8,'Jan''26- Leave Bal'!$B$3:$I$83,8,0)+$BI$3 -> 0.75 | BJ8: =IF((AP8+AQ8)<=BD8, (AP8+AQ8),BD8) -> 0 | BK8: =IF(((AP8+AQ8)-BJ8)>BE8,BE8,(AP8+AQ8)-BJ8) -> 0.5 | BL8: =IF((AP8+AQ8-BJ8-BK8)>=BF8,BF8,(AP8+AQ8-BJ8-BK8)) -> 2 | BM8: =IF((AP8+AQ8-BJ8-BK8-BL8)>=BG8,BG8,(AP8+AQ8-BJ8-BK8-BL8)) -> 0 | BN8: =AS8 -> 0 | BO8: =AP8+AQ8-BJ8-BK8-BL8-BM8 -> 0 | BP8: =BD8-BJ8 -> 0 | BQ8: =BE8-BK8 -> 0 | BR8: =BF8-BL8 -> 0.5 | BS8: =BG8-BM8 -> 11 | BT8: =BH8-BN8 -> 0 | BU8: =BI8 -> 0.75 | BW8: 01st feb Weekoff taken early in Jan'26
A9: 6 | B9: JAI-382 | D9: Manappuram/Muthoot/Bajaj | E9: KYC | F9: Birdman | G9: Suvali | H9: 90522 62927 | I9: rekha.bommaraju@jukshio.com | J9: 44522 | L9: W/O | M9: P | N9: P | O9: P | P9: W/O | Q9: P | R9: P | S9: P | T9: P | U9: P | V9: P | W9: P | X9: P | Y9: P | Z9: W/O | AA9: P | AB9: P | AC9: L | AD9: P | AE9: W/O | AF9: P | AG9: P | AH9: P | AI9: P | AJ9: W/O | AK9: P | AL9: P | AM9: P | AN9: =COUNTIF(L9:AM9,"P")+COUNTIF(L9:AM9,"HFL")/2 -> 22 | AO9: =COUNTIF(L9:AM9,"W/O") -> 5 | AP9: =COUNTIF(L9:AM9,"L") -> 1 | AQ9: =COUNTIF(L9:AM9,"HFL")/2 -> 0 | AR9: =COUNTIF(L9:AM9,"H") -> 0 | AS9: =COUNTIF(L9:AM9,"MG") -> 0 | AT9: =COUNTIF(L9:AM9,"ML") -> 0 | AU9: =COUNTIF(L9:AM9,"UL") -> 0 | AV9: =COUNTIF(L9:AM9,"MC") -> 0 | AW9: =COUNTIF(L9:AM9,"BL") -> 0 | AX9: =COUNTIF(L9:AM9,"MDL") -> 0 | AY9: =COUNTIF(L9:AM9,"LOP") -> 0 | AZ9: =SUM(AN9:AY9) -> 28 | BA9: =SUM(AP9:AQ9,AS9:AY9,AN9) -> 23 | BB9: =AZ9-(AU9+BO9) -> 28 | BC9: =AN9/BA9 -> 0.95652174 | BD9: =VLOOKUP(B9,'Jan''26- Leave Bal'!$B$3:$D$83,3,0) -> 0 | BE9: =VLOOKUP(B9,'Jan''26- Leave Bal'!$B$3:$E$83,4,0)+$BE$3 -> 0.5 | BF9: =VLOOKUP(B9,'Jan''26- Leave Bal'!$B$3:$F$83,5,0)+$BF$3 -> 0.5 | BG9: =VLOOKUP(B9,'Jan''26- Leave Bal'!$B$3:$G$83,6,0)+$BG$3 -> 5.5 | BH9: =VLOOKUP(B9,'Jan''26- Leave Bal'!$B$3:$H$83,7,0) -> 15 | BI9: =VLOOKUP(B9,'Jan''26- Leave Bal'!$B$3:$I$83,8,0)+$BI$3 -> 0.75 | BJ9: =IF((AP9+AQ9)<=BD9, (AP9+AQ9),BD9) -> 0 | BK9: =IF(((AP9+AQ9)-BJ9)>BE9,BE9,(AP9+AQ9)-BJ9) -> 0.5 | BL9: =IF((AP9+AQ9-BJ9-BK9)>=BF9,BF9,(AP9+AQ9-BJ9-BK9)) -> 0.5 | BM9: =IF((AP9+AQ9-BJ9-BK9-BL9)>=BG9,BG9,(AP9+AQ9-BJ9-BK9-BL9)) -> 0 | BN9: =AS9 -> 0 | BO9: =AP9+AQ9-BJ9-BK9-BL9-BM9 -> 0 | BP9: =BD9-BJ9 -> 0 | BQ9: =BE9-BK9 -> 0 | BR9: =BF9-BL9 -> 0 | BS9: =BG9-BM9 -> 5.5 | BT9: =BH9-BN9 -> 15 | BU9: =BI9 -> 0.75 | BV9: 01st Mar weekoff taken in Feb Last week itself | BW9: 0
A10: 7 | B10: JAI-248 | D10: Manappuram/Muthoot/Bajaj | E10: KYC | F10: Birdman | G10: Suvali | H10: 9014106905 | I10: balamani.dommata@jukshio.com | J10: 44326 | L10: P | M10: P | N10: P | O10: P | P10: P | Q10: P | R10: P | S10: W/O | T10: P | U10: L | V10: W/O | W10: L | X10: P | Y10: P | Z10: P | AA10: P | AB10: P | AC10: P | AD10: P | AE10: P | AF10: P | AG10: W/O | AH10: P | AI10: P | AJ10: P | AK10: P | AL10: P | AM10: P | AN10: =COUNTIF(L10:AM10,"P")+COUNTIF(L10:AM10,"HFL")/2 -> 23 | AO10: =COUNTIF(L10:AM10,"W/O") -> 3 | AP10: =COUNTIF(L10:AM10,"L") -> 2 | AQ10: =COUNTIF(L10:AM10,"HFL")/2 -> 0 | AR10: =COUNTIF(L10:AM10,"H") -> 0 | AS10: =COUNTIF(L10:AM10,"MG") -> 0 | AT10: =COUNTIF(L10:AM10,"ML") -> 0 | AU10: =COUNTIF(L10:AM10,"UL") -> 0 | AV10: =COUNTIF(L10:AM10,"MC") -> 0 | AW10: =COUNTIF(L10:AM10,"BL") -> 0 | AX10: =COUNTIF(L10:AM10,"MDL") -> 0 | AY10: =COUNTIF(L10:AM10,"LOP") -> 0 | AZ10: =SUM(AN10:AY10) -> 28 | BA10: =SUM(AP10:AQ10,AS10:AY10,AN10) -> 25 | BB10: =AZ10-(AU10+BO10) -> 28 | BC10: =AN10/BA10 -> 0.92 | BD10: =VLOOKUP(B10,'Jan''26- Leave Bal'!$B$3:$D$83,3,0) -> 0 | BE10: =VLOOKUP(B10,'Jan''26- Leave Bal'!$B$3:$E$83,4,0)+$BE$3 -> 0.5 | BF10: =VLOOKUP(B10,'Jan''26- Leave Bal'!$B$3:$F$83,5,0)+$BF$3 -> 2 | BG10: =VLOOKUP(B10,'Jan''26- Leave Bal'!$B$3:$G$83,6,0)+$BG$3 -> 13 | BH10: =VLOOKUP(B10,'Jan''26- Leave Bal'!$B$3:$H$83,7,0) -> 15 | BI10: =VLOOKUP(B10,'Jan''26- Leave Bal'!$B$3:$I$83,8,0)+$BI$3 -> 0.75 | BJ10: =IF((AP10+AQ10)<=BD10, (AP10+AQ10),BD10) -> 0 | BK10: =IF(((AP10+AQ10)-BJ10)>BE10,BE10,(AP10+AQ10)-BJ10) -> 0.5 | BL10: =IF((AP10+AQ10-BJ10-BK10)>=BF10,BF10,(AP10+AQ10-BJ10-BK10)) -> 1.5 | BM10: =IF((AP10+AQ10-BJ10-BK10-BL10)>=BG10,BG10,(AP10+AQ10-BJ10-BK10-BL10)) -> 0 | BN10: =AS10 -> 0 | BO10: =AP10+AQ10-BJ10-BK10-BL10-BM10 -> 0 | BP10: =BD10-BJ10 -> 0 | BQ10: =BE10-BK10 -> 0 | BR10: =BF10-BL10 -> 0.5 | BS10: =BG10-BM10 -> 13 | BT10: =BH10-BN10 -> 15 | BU10: =BI10 -> 0.75 | BW10: 01st feb Weekoff taken early in Jan'26
A11: 8 | B11: JAI-494 | D11: Manappuram/Muthoot/Bajaj | E11: KYC | F11: Birdman | G11: Uppal | H11: 9032615583 | I11: srilekha.dodla@jukshio.com | J11: 44845 | L11: W/O | M11: P | N11: P | O11: P | P11: P | Q11: P | R11: P | S11: W/O | T11: W/O | U11: P | V11: P | W11: P | X11: P | Y11: P | Z11: P | AA11: P | AB11: P | AC11: P | AD11: P | AE11: P | AF11: P | AG11: W/O | AH11: P | AI11: P | AJ11: P | AK11: P | AL11: P | AM11: P | AN11: =COUNTIF(L11:AM11,"P")+COUNTIF(L11:AM11,"HFL")/2 -> 24 | AO11: =COUNTIF(L11:AM11,"W/O") -> 4 | AP11: =COUNTIF(L11:AM11,"L") -> 0 | AQ11: =COUNTIF(L11:AM11,"HFL")/2 -> 0 | AR11: =COUNTIF(L11:AM11,"H") -> 0 | AS11: =COUNTIF(L11:AM11,"MG") -> 0 | AT11: =COUNTIF(L11:AM11,"ML") -> 0 | AU11: =COUNTIF(L11:AM11,"UL") -> 0 | AV11: =COUNTIF(L11:AM11,"MC") -> 0 | AW11: =COUNTIF(L11:AM11,"BL") -> 0 | AX11: =COUNTIF(L11:AM11,"MDL") -> 0 | AY11: =COUNTIF(L11:AM11,"LOP") -> 0 | AZ11: =SUM(AN11:AY11) -> 28 | BA11: =SUM(AP11:AQ11,AS11:AY11,AN11) -> 24 | BB11: =AZ11-(AU11+BO11) -> 28 | BC11: =AN11/BA11 -> 1 | BD11: =VLOOKUP(B11,'Jan''26- Leave Bal'!$B$3:$D$83,3,0) -> 0 | BE11: =VLOOKUP(B11,'Jan''26- Leave Bal'!$B$3:$E$83,4,0)+$BE$3 -> 1 | BF11: =VLOOKUP(B11,'Jan''26- Leave Bal'!$B$3:$F$83,5,0)+$BF$3 -> 1.5 | BG11: =VLOOKUP(B11,'Jan''26- Leave Bal'!$B$3:$G$83,6,0)+$BG$3 -> 9.3 | BH11: =VLOOKUP(B11,'Jan''26- Leave Bal'!$B$3:$H$83,7,0) -> 15 | BI11: =VLOOKUP(B11,'Jan''26- Leave Bal'!$B$3:$I$83,8,0)+$BI$3 -> 0.75 | BJ11: =IF((AP11+AQ11)<=BD11, (AP11+AQ11),BD11) -> 0 | BK11: =IF(((AP11+AQ11)-BJ11)>BE11,BE11,(AP11+AQ11)-BJ11) -> 0 | BL11: =IF((AP11+AQ11-BJ11-BK11)>=BF11,BF11,(AP11+AQ11-BJ11-BK11)) -> 0 | BM11: =IF((AP11+AQ11-BJ11-BK11-BL11)>=BG11,BG11,(AP11+AQ11-BJ11-BK11-BL11)) -> 0 | BN11: =AS11 -> 0 | BO11: =AP11+AQ11-BJ11-BK11-BL11-BM11 -> 0 | BP11: =BD11-BJ11 -> 0 | BQ11: =BE11-BK11 -> 1 | BR11: =BF11-BL11 -> 1.5 | BS11: =BG11-BM11 -> 9.3 | BT11: =BH11-BN11 -> 15 | BU11: =BI11 -> 0.75 | BW11: 0
A12: 9 | B12: JAI-1153 | D12: Manappuram/Muthoot/Bajaj | E12: KYC | F12: Birdman | G12: Uppal | H12: 9573067930 | I12: vaishnavi.madoori@jukshio.com | J12: 45086 | L12: W/O | M12: P | N12: P | O12: L | P12: P | Q12: L | R12: W/O | S12: P | T12: L | U12: L | V12: P | W12: P | X12: L | Y12: P | Z12: W/O | AA12: L | AB12: L | AC12: P | AD12: P | AE12: P | AF12: L | AG12: W/O | AH12: P | AI12: P | AJ12: P | AK12: P | AL12: P | AM12: W/O | AN12: =COUNTIF(L12:AM12,"P")+COUNTIF(L12:AM12,"HFL")/2 -> 15 | AO12: =COUNTIF(L12:AM12,"W/O") -> 5 | AP12: =COUNTIF(L12:AM12,"L") -> 8 | AQ12: =COUNTIF(L12:AM12,"HFL")/2 -> 0 | AR12: =COUNTIF(L12:AM12,"H") -> 0 | AS12: =COUNTIF(L12:AM12,"MG") -> 0 | AT12: =COUNTIF(L12:AM12,"ML") -> 0 | AU12: =COUNTIF(L12:AM12,"UL") -> 0 | AV12: =COUNTIF(L12:AM12,"MC") -> 0 | AW12: =COUNTIF(L12:AM12,"BL") -> 0 | AX12: =COUNTIF(L12:AM12,"MDL") -> 0 | AY12: =COUNTIF(L12:AM12,"LOP") -> 0 | AZ12: =SUM(AN12:AY12) -> 28 | BA12: =SUM(AP12:AQ12,AS12:AY12,AN12) -> 23 | BB12: =AZ12-(AU12+BO12) -> 26.5 | BC12: =AN12/BA12 -> 0.65217391 | BD12: =VLOOKUP(B12,'Jan''26- Leave Bal'!$B$3:$D$83,3,0) -> 0 | BE12: =VLOOKUP(B12,'Jan''26- Leave Bal'!$B$3:$E$83,4,0)+$BE$3 -> 0.5 | BF12: =VLOOKUP(B12,'Jan''26- Leave Bal'!$B$3:$F$83,5,0)+$BF$3 -> 0.5 | BG12: =VLOOKUP(B12,'Jan''26- Leave Bal'!$B$3:$G$83,6,0)+$BG$3 -> 5.5 | BH12: =VLOOKUP(B12,'Jan''26- Leave Bal'!$B$3:$H$83,7,0) -> 15 | BI12: =VLOOKUP(B12,'Jan''26- Leave Bal'!$B$3:$I$83,8,0)+$BI$3 -> 0.75 | BJ12: =IF((AP12+AQ12)<=BD12, (AP12+AQ12),BD12) -> 0 | BK12: =IF(((AP12+AQ12)-BJ12)>BE12,BE12,(AP12+AQ12)-BJ12) -> 0.5 | BL12: =IF((AP12+AQ12-BJ12-BK12)>=BF12,BF12,(AP12+AQ12-BJ12-BK12)) -> 0.5 | BM12: =IF((AP12+AQ12-BJ12-BK12-BL12)>=BG12,BG12,(AP12+AQ12-BJ12-BK12-BL12)) -> 5.5 | BN12: =AS12 -> 0 | BO12: =AP12+AQ12-BJ12-BK12-BL12-BM12 -> 1.5 | BP12: =BD12-BJ12 -> 0 | BQ12: =BE12-BK12 -> 0 | BR12: =BF12-BL12 -> 0 | BS12: =BG12-BM12 -> 0 | BT12: =BH12-BN12 -> 15 | BU12: =BI12 -> 0.75 | BV12: 01st Mar weekoff taken in Feb Last week itself | BW12: 0
A13: 10 | B13: JAI-333 | D13: Manappuram/Muthoot/Bajaj | E13: KYC | F13: Birdman | G13: Suvali | H13: 7893739623 | I13: sushmitha.padmasri@jukshio.com | J13: 44426 | L13: W/O | M13: P | N13: P | O13: P | P13: P | Q13: P | R13: P | S13: W/O | T13: P | U13: P | V13: P | W13: P | X13: P | Y13: P | Z13: W/O | AA13: P | AB13: L | AC13: P | AD13: L | AE13: P | AF13: L | AG13: P | AH13: L | AI13: P | AJ13: L | AK13: P | AL13: L | AM13: P | AN13: =COUNTIF(L13:AM13,"P")+COUNTIF(L13:AM13,"HFL")/2 -> 19 | AO13: =COUNTIF(L13:AM13,"W/O") -> 3 | AP13: =COUNTIF(L13:AM13,"L") -> 6 | AQ13: =COUNTIF(L13:AM13,"HFL")/2 -> 0 | AR13: =COUNTIF(L13:AM13,"H") -> 0 | AS13: =COUNTIF(L13:AM13,"MG") -> 0 | AT13: =COUNTIF(L13:AM13,"ML") -> 0 | AU13: =COUNTIF(L13:AM13,"UL") -> 0 | AV13: =COUNTIF(L13:AM13,"MC") -> 0 | AW13: =COUNTIF(L13:AM13,"BL") -> 0 | AX13: =COUNTIF(L13:AM13,"MDL") -> 0 | AY13: =COUNTIF(L13:AM13,"LOP") -> 0 | AZ13: =SUM(AN13:AY13) -> 28 | BA13: =SUM(AP13:AQ13,AS13:AY13,AN13) -> 25 | BB13: =AZ13-(AU13+BO13) -> 28 | BC13: =AN13/BA13 -> 0.76 | BD13: =VLOOKUP(B13,'Jan''26- Leave Bal'!$B$3:$D$83,3,0) -> 0 | BE13: =VLOOKUP(B13,'Jan''26- Leave Bal'!$B$3:$E$83,4,0)+$BE$3 -> 0.5 | BF13: =VLOOKUP(B13,'Jan''26- Leave Bal'!$B$3:$F$83,5,0)+$BF$3 -> 0.5 | BG13: =VLOOKUP(B13,'Jan''26- Leave Bal'!$B$3:$G$83,6,0)+$BG$3 -> 7.5 | BH13: =VLOOKUP(B13,'Jan''26- Leave Bal'!$B$3:$H$83,7,0) -> 15 | BI13: =VLOOKUP(B13,'Jan''26- Leave Bal'!$B$3:$I$83,8,0)+$BI$3 -> 0.75 | BJ13: =IF((AP13+AQ13)<=BD13, (AP13+AQ13),BD13) -> 0 | BK13: =IF(((AP13+AQ13)-BJ13)>BE13,BE13,(AP13+AQ13)-BJ13) -> 0.5 | BL13: =IF((AP13+AQ13-BJ13-BK13)>=BF13,BF13,(AP13+AQ13-BJ13-BK13)) -> 0.5 | BM13: =IF((AP13+AQ13-BJ13-BK13-BL13)>=BG13,BG13,(AP13+AQ13-BJ13-BK13-BL13)) -> 5 | BN13: =AS13 -> 0 | BO13: =AP13+AQ13-BJ13-BK13-BL13-BM13 -> 0 | BP13: =BD13-BJ13 -> 0 | BQ13: =BE13-BK13 -> 0 | BR13: =BF13-BL13 -> 0 | BS13: =BG13-BM13 -> 2.5 | BT13: =BH13-BN13 -> 15 | BU13: =BI13 -> 0.75 | BW13: 01st feb Weekoff taken early in Jan'26
A14: 11 | B14: JAI-260 | D14: Manappuram/Muthoot/Bajaj | E14: KYC | F14: Birdman | G14: Suvali | H14: 9550982385 | I14: ramya.shanagala@jukshio.com | J14: 44326 | L14: ML | M14: ML | N14: ML | O14: ML | P14: ML | Q14: UL | R14: UL | S14: UL | T14: UL | U14: UL | V14: UL | W14: UL | X14: UL | Y14: UL | Z14: UL | AA14: UL | AB14: UL | AC14: L | AD14: L | AE14: L | AF14: L | AG14: UL | AH14: P | AI14: P | AJ14: L | AK14: P | AL14: W/O | AM14: P | AN14: =COUNTIF(L14:AM14,"P")+COUNTIF(L14:AM14,"HFL")/2 -> 4 | AO14: =COUNTIF(L14:AM14,"W/O") -> 1 | AP14: =COUNTIF(L14:AM14,"L") -> 5 | AQ14: =COUNTIF(L14:AM14,"HFL")/2 -> 0 | AR14: =COUNTIF(L14:AM14,"H") -> 0 | AS14: =COUNTIF(L14:AM14,"MG") -> 0 | AT14: =COUNTIF(L14:AM14,"ML") -> 5 | AU14: =COUNTIF(L14:AM14,"UL") -> 13 | AV14: =COUNTIF(L14:AM14,"MC") -> 0 | AW14: =COUNTIF(L14:AM14,"BL") -> 0 | AX14: =COUNTIF(L14:AM14,"MDL") -> 0 | AY14: =COUNTIF(L14:AM14,"LOP") -> 0 | AZ14: =SUM(AN14:AY14) -> 28 | BA14: =SUM(AP14:AQ14,AS14:AY14,AN14) -> 27 | BB14: =AZ14-(AU14+BO14) -> 12 | BC14: =AN14/BA14 -> 0.14814815 | BD14: =VLOOKUP(B14,'Jan''26- Leave Bal'!$B$3:$D$83,3,0) -> 0 | BE14: =VLOOKUP(B14,'Jan''26- Leave Bal'!$B$3:$E$83,4,0)+$BE$3 -> 0.5 | BF14: =VLOOKUP(B14,'Jan''26- Leave Bal'!$B$3:$F$83,5,0)+$BF$3 -> 0.5 | BG14: =VLOOKUP(B14,'Jan''26- Leave Bal'!$B$3:$G$83,6,0)+$BG$3 -> 1 | BH14: =VLOOKUP(B14,'Jan''26- Leave Bal'!$B$3:$H$83,7,0) -> 0 | BI14: =VLOOKUP(B14,'Jan''26- Leave Bal'!$B$3:$I$83,8,0)+$BI$3 -> 0.25 | BJ14: =IF((AP14+AQ14)<=BD14, (AP14+AQ14),BD14) -> 0 | BK14: =IF(((AP14+AQ14)-BJ14)>BE14,BE14,(AP14+AQ14)-BJ14) -> 0.5 | BL14: =IF((AP14+AQ14-BJ14-BK14)>=BF14,BF14,(AP14+AQ14-BJ14-BK14)) -> 0.5 | BM14: =IF((AP14+AQ14-BJ14-BK14-BL14)>=BG14,BG14,(AP14+AQ14-BJ14-BK14-BL14)) -> 1 | BN14: =AS14 -> 0 | BO14: =AP14+AQ14-BJ14-BK14-BL14-BM14 -> 3 | BP14: =BD14-BJ14 -> 0 | BQ14: =BE14-BK14 -> 0 | BR14: =BF14-BL14 -> 0 | BS14: =BG14-BM14 -> 0 | BT14: =BH14-BN14 -> 0 | BU14: =BI14 -> 0.25 | BW14: 0
A15: 12 | B15: JAI-725 | D15: Manappuram/Muthoot/Bajaj | E15: KYC | F15: Birdman | G15: Suvali | H15: 9848887958 | I15: rajitha.peraboina@jukshio.com | J15: 44909 | L15: W/O | M15: P | N15: P | O15: P | P15: P | Q15: P | R15: P | S15: W/O | T15: L | U15: P | V15: P | W15: P | X15: P | Y15: P | Z15: W/O | AA15: P | AB15: L | AC15: L | AD15: P | AE15: P | AF15: P | AG15: W/O | AH15: P | AI15: P | AJ15: P | AK15: P | AL15: P | AM15: P | AN15: =COUNTIF(L15:AM15,"P")+COUNTIF(L15:AM15,"HFL")/2 -> 21 | AO15: =COUNTIF(L15:AM15,"W/O") -> 4 | AP15: =COUNTIF(L15:AM15,"L") -> 3 | AQ15: =COUNTIF(L15:AM15,"HFL")/2 -> 0 | AR15: =COUNTIF(L15:AM15,"H") -> 0 | AS15: =COUNTIF(L15:AM15,"MG") -> 0 | AT15: =COUNTIF(L15:AM15,"ML") -> 0 | AU15: =COUNTIF(L15:AM15,"UL") -> 0 | AV15: =COUNTIF(L15:AM15,"MC") -> 0 | AW15: =COUNTIF(L15:AM15,"BL") -> 0 | AX15: =COUNTIF(L15:AM15,"MDL") -> 0 | AY15: =COUNTIF(L15:AM15,"LOP") -> 0 | AZ15: =SUM(AN15:AY15) -> 28 | BA15: =SUM(AP15:AQ15,AS15:AY15,AN15) -> 24 | BB15: =AZ15-(AU15+BO15) -> 28 | BC15: =AN15/BA15 -> 0.875 | BD15: =VLOOKUP(B15,'Jan''26- Leave Bal'!$B$3:$D$83,3,0) -> 0 | BE15: =VLOOKUP(B15,'Jan''26- Leave Bal'!$B$3:$E$83,4,0)+$BE$3 -> 0.5 | BF15: =VLOOKUP(B15,'Jan''26- Leave Bal'!$B$3:$F$83,5,0)+$BF$3 -> 0.5 | BG15: =VLOOKUP(B15,'Jan''26- Leave Bal'!$B$3:$G$83,6,0)+$BG$3 -> 11 | BH15: =VLOOKUP(B15,'Jan''26- Leave Bal'!$B$3:$H$83,7,0) -> 15 | BI15: =VLOOKUP(B15,'Jan''26- Leave Bal'!$B$3:$I$83,8,0)+$BI$3 -> 0.75 | BJ15: =IF((AP15+AQ15)<=BD15, (AP15+AQ15),BD15) -> 0 | BK15: =IF(((AP15+AQ15)-BJ15)>BE15,BE15,(AP15+AQ15)-BJ15) -> 0.5 | BL15: =IF((AP15+AQ15-BJ15-BK15)>=BF15,BF15,(AP15+AQ15-BJ15-BK15)) -> 0.5 | BM15: =IF((AP15+AQ15-BJ15-BK15-BL15)>=BG15,BG15,(AP15+AQ15-BJ15-BK15-BL15)) -> 2 | BN15: =AS15 -> 0 | BO15: =AP15+AQ15-BJ15-BK15-BL15-BM15 -> 0 | BP15: =BD15-BJ15 -> 0 | BQ15: =BE15-BK15 -> 0 | BR15: =BF15-BL15 -> 0 | BS15: =BG15-BM15 -> 9 | BT15: =BH15-BN15 -> 15 | BU15: =BI15 -> 0.75 | BW15: 0
A16: 13 | B16: JAI-805 | D16: Manappuram/Muthoot/Bajaj | E16: KYC | F16: Birdman | G16: Suvali | H16: 8374073673 | I16: indumathi.regonda@jukshio.com | J16: 45033 | L16: W/O | M16: P | N16: P | O16: P | P16: P | Q16: P | R16: P | S16: W/O | T16: P | U16: L | V16: P | W16: P | X16: P | Y16: P | Z16: W/O | AA16: P | AB16: P | AC16: P | AD16: P | AE16: P | AF16: P | AG16: W/O | AH16: P | AI16: P | AJ16: P | AK16: P | AL16: W/O | AM16: P | AN16: =COUNTIF(L16:AM16,"P")+COUNTIF(L16:AM16,"HFL")/2 -> 22 | AO16: =COUNTIF(L16:AM16,"W/O") -> 5 | AP16: =COUNTIF(L16:AM16,"L") -> 1 | AQ16: =COUNTIF(L16:AM16,"HFL")/2 -> 0 | AR16: =COUNTIF(L16:AM16,"H") -> 0 | AS16: =COUNTIF(L16:AM16,"MG") -> 0 | AT16: =COUNTIF(L16:AM16,"ML") -> 0 | AU16: =COUNTIF(L16:AM16,"UL") -> 0 | AV16: =COUNTIF(L16:AM16,"MC") -> 0 | AW16: =COUNTIF(L16:AM16,"BL") -> 0 | AX16: =COUNTIF(L16:AM16,"MDL") -> 0 | AY16: =COUNTIF(L16:AM16,"LOP") -> 0 | AZ16: =SUM(AN16:AY16) -> 28 | BA16: =SUM(AP16:AQ16,AS16:AY16,AN16) -> 23 | BB16: =AZ16-(AU16+BO16) -> 28 | BC16: =AN16/BA16 -> 0.95652174 | BD16: =VLOOKUP(B16,'Jan''26- Leave Bal'!$B$3:$D$83,3,0) -> 0 | BE16: =VLOOKUP(B16,'Jan''26- Leave Bal'!$B$3:$E$83,4,0)+$BE$3 -> 0.5 | BF16: =VLOOKUP(B16,'Jan''26- Leave Bal'!$B$3:$F$83,5,0)+$BF$3 -> 0.5 | BG16: =VLOOKUP(B16,'Jan''26- Leave Bal'!$B$3:$G$83,6,0)+$BG$3 -> 1 | BH16: =VLOOKUP(B16,'Jan''26- Leave Bal'!$B$3:$H$83,7,0) -> 15 | BI16: =VLOOKUP(B16,'Jan''26- Leave Bal'!$B$3:$I$83,8,0)+$BI$3 -> 0.75 | BJ16: =IF((AP16+AQ16)<=BD16, (AP16+AQ16),BD16) -> 0 | BK16: =IF(((AP16+AQ16)-BJ16)>BE16,BE16,(AP16+AQ16)-BJ16) -> 0.5 | BL16: =IF((AP16+AQ16-BJ16-BK16)>=BF16,BF16,(AP16+AQ16-BJ16-BK16)) -> 0.5 | BM16: =IF((AP16+AQ16-BJ16-BK16-BL16)>=BG16,BG16,(AP16+AQ16-BJ16-BK16-BL16)) -> 0 | BN16: =AS16 -> 0 | BO16: =AP16+AQ16-BJ16-BK16-BL16-BM16 -> 0 | BP16: =BD16-BJ16 -> 0 | BQ16: =BE16-BK16 -> 0 | BR16: =BF16-BL16 -> 0 | BS16: =BG16-BM16 -> 1 | BT16: =BH16-BN16 -> 15 | BU16: =BI16 -> 0.75 | BV16: 01st Mar weekoff taken in Feb Last week itself | BW16: 0
A17: 14 | B17: JAI-1145 | D17: Manappuram/Muthoot/Bajaj | E17: KYC | F17: Birdman | G17: Uppal | H17: 7093331093 | I17: sindhu.kondra@jukshio.com | J17: 45086 | L17: W/O | M17: P | N17: P | O17: L | P17: W/O | Q17: P | R17: P | S17: P | T17: P | U17: P | V17: P | W17: P | X17: P | Y17: P | Z17: W/O | AA17: P | AB17: P | AC17: P | AD17: P | AE17: P | AF17: P | AG17: W/O | AH17: P | AI17: P | AJ17: P | AK17: P | AL17: L | AM17: P | AN17: =COUNTIF(L17:AM17,"P")+COUNTIF(L17:AM17,"HFL")/2 -> 22 | AO17: =COUNTIF(L17:AM17,"W/O") -> 4 | AP17: =COUNTIF(L17:AM17,"L") -> 2 | AQ17: =COUNTIF(L17:AM17,"HFL")/2 -> 0 | AR17: =COUNTIF(L17:AM17,"H") -> 0 | AS17: =COUNTIF(L17:AM17,"MG") -> 0 | AT17: =COUNTIF(L17:AM17,"ML") -> 0 | AU17: =COUNTIF(L17:AM17,"UL") -> 0 | AV17: =COUNTIF(L17:AM17,"MC") -> 0 | AW17: =COUNTIF(L17:AM17,"BL") -> 0 | AX17: =COUNTIF(L17:AM17,"MDL") -> 0 | AY17: =COUNTIF(L17:AM17,"LOP") -> 0 | AZ17: =SUM(AN17:AY17) -> 28 | BA17: =SUM(AP17:AQ17,AS17:AY17,AN17) -> 24 | BB17: =AZ17-(AU17+BO17) -> 28 | BC17: =AN17/BA17 -> 0.91666667 | BD17: =VLOOKUP(B17,'Jan''26- Leave Bal'!$B$3:$D$83,3,0) -> 0 | BE17: =VLOOKUP(B17,'Jan''26- Leave Bal'!$B$3:$E$83,4,0)+$BE$3 -> 0.5 | BF17: =VLOOKUP(B17,'Jan''26- Leave Bal'!$B$3:$F$83,5,0)+$BF$3 -> 0.5 | BG17: =VLOOKUP(B17,'Jan''26- Leave Bal'!$B$3:$G$83,6,0)+$BG$3 -> 6.8 | BH17: =VLOOKUP(B17,'Jan''26- Leave Bal'!$B$3:$H$83,7,0) -> 0 | BI17: =VLOOKUP(B17,'Jan''26- Leave Bal'!$B$3:$I$83,8,0)+$BI$3 -> 0.75 | BJ17: =IF((AP17+AQ17)<=BD17, (AP17+AQ17),BD17) -> 0 | BK17: =IF(((AP17+AQ17)-BJ17)>BE17,BE17,(AP17+AQ17)-BJ17) -> 0.5 | BL17: =IF((AP17+AQ17-BJ17-BK17)>=BF17,BF17,(AP17+AQ17-BJ17-BK17)) -> 0.5 | BM17: =IF((AP17+AQ17-BJ17-BK17-BL17)>=BG17,BG17,(AP17+AQ17-BJ17-BK17-BL17)) -> 1 | BN17: =AS17 -> 0 | BO17: =AP17+AQ17-BJ17-BK17-BL17-BM17 -> 0 | BP17: =BD17-BJ17 -> 0 | BQ17: =BE17-BK17 -> 0 | BR17: =BF17-BL17 -> 0 | BS17: =BG17-BM17 -> 5.8 | BT17: =BH17-BN17 -> 0 | BU17: =BI17 -> 0.75 | BW17: 0
A18: 15 | B18: JAI-301 | D18: Manappuram/Muthoot/Bajaj | E18: KYC | F18: Birdman | G18: Suvali | H18: 6302402308 | I18: athikha.md@jukshio.com | J18: 44426 | L18: L | M18: P | N18: P | O18: P | P18: P | Q18: W/O | R18: L | S18: L | T18: L | U18: P | V18: P | W18: P | X18: P | Y18: P | Z18: W/O | AA18: P | AB18: P | AC18: P | AD18: W/O | AE18: P | AF18: P | AG18: P | AH18: P | AI18: P | AJ18: P | AK18: P | AL18: W/O | AM18: P | AN18: =COUNTIF(L18:AM18,"P")+COUNTIF(L18:AM18,"HFL")/2 -> 20 | AO18: =COUNTIF(L18:AM18,"W/O") -> 4 | AP18: =COUNTIF(L18:AM18,"L") -> 4 | AQ18: =COUNTIF(L18:AM18,"HFL")/2 -> 0 | AR18: =COUNTIF(L18:AM18,"H") -> 0 | AS18: =COUNTIF(L18:AM18,"MG") -> 0 | AT18: =COUNTIF(L18:AM18,"ML") -> 0 | AU18: =COUNTIF(L18:AM18,"UL") -> 0 | AV18: =COUNTIF(L18:AM18,"MC") -> 0 | AW18: =COUNTIF(L18:AM18,"BL") -> 0 | AX18: =COUNTIF(L18:AM18,"MDL") -> 0 | AY18: =COUNTIF(L18:AM18,"LOP") -> 0 | AZ18: =SUM(AN18:AY18) -> 28 | BA18: =SUM(AP18:AQ18,AS18:AY18,AN18) -> 24 | BB18: =AZ18-(AU18+BO18) -> 26 | BC18: =AN18/BA18 -> 0.83333333 | BD18: =VLOOKUP(B18,'Jan''26- Leave Bal'!$B$3:$D$83,3,0) -> 0 | BE18: =VLOOKUP(B18,'Jan''26- Leave Bal'!$B$3:$E$83,4,0)+$BE$3 -> 0.5 | BF18: =VLOOKUP(B18,'Jan''26- Leave Bal'!$B$3:$F$83,5,0)+$BF$3 -> 0.5 | BG18: =VLOOKUP(B18,'Jan''26- Leave Bal'!$B$3:$G$83,6,0)+$BG$3 -> 1 | BH18: =VLOOKUP(B18,'Jan''26- Leave Bal'!$B$3:$H$83,7,0) -> 0 | BI18: =VLOOKUP(B18,'Jan''26- Leave Bal'!$B$3:$I$83,8,0)+$BI$3 -> 0.75 | BJ18: =IF((AP18+AQ18)<=BD18, (AP18+AQ18),BD18) -> 0 | BK18: =IF(((AP18+AQ18)-BJ18)>BE18,BE18,(AP18+AQ18)-BJ18) -> 0.5 | BL18: =IF((AP18+AQ18-BJ18-BK18)>=BF18,BF18,(AP18+AQ18-BJ18-BK18)) -> 0.5 | BM18: =IF((AP18+AQ18-BJ18-BK18-BL18)>=BG18,BG18,(AP18+AQ18-BJ18-BK18-BL18)) -> 1 | BN18: =AS18 -> 0 | BO18: =AP18+AQ18-BJ18-BK18-BL18-BM18 -> 2 | BP18: =BD18-BJ18 -> 0 | BQ18: =BE18-BK18 -> 0 | BR18: =BF18-BL18 -> 0 | BS18: =BG18-BM18 -> 0 | BT18: =BH18-BN18 -> 0 | BU18: =BI18 -> 0.75 | BW18: 0
A19: 16 | B19: JAI-374 | D19: Manappuram/Muthoot/Bajaj | E19: KYC | F19: Birdman | G19: Suvali | H19: 9392278721 | I19: md.nishath@jukshio.com | J19: 44522 | L19: W/O | M19: P | N19: P | O19: P | P19: P | Q19: P | R19: P | S19: W/O | T19: P | U19: P | V19: P | W19: P | X19: P | Y19: P | Z19: W/O | AA19: P | AB19: P | AC19: P | AD19: P | AE19: P | AF19: P | AG19: W/O | AH19: P | AI19: P | AJ19: P | AK19: P | AL19: P | AM19: P | AN19: =COUNTIF(L19:AM19,"P")+COUNTIF(L19:AM19,"HFL")/2 -> 24 | AO19: =COUNTIF(L19:AM19,"W/O") -> 4 | AP19: =COUNTIF(L19:AM19,"L") -> 0 | AQ19: =COUNTIF(L19:AM19,"HFL")/2 -> 0 | AR19: =COUNTIF(L19:AM19,"H") -> 0 | AS19: =COUNTIF(L19:AM19,"MG") -> 0 | AT19: =COUNTIF(L19:AM19,"ML") -> 0 | AU19: =COUNTIF(L19:AM19,"UL") -> 0 | AV19: =COUNTIF(L19:AM19,"MC") -> 0 | AW19: =COUNTIF(L19:AM19,"BL") -> 0 | AX19: =COUNTIF(L19:AM19,"MDL") -> 0 | AY19: =COUNTIF(L19:AM19,"LOP") -> 0 | AZ19: =SUM(AN19:AY19) -> 28 | BA19: =SUM(AP19:AQ19,AS19:AY19,AN19) -> 24 | BB19: =AZ19-(AU19+BO19) -> 28 | BC19: =AN19/BA19 -> 1 | BD19: =VLOOKUP(B19,'Jan''26- Leave Bal'!$B$3:$D$83,3,0) -> 0 | BE19: =VLOOKUP(B19,'Jan''26- Leave Bal'!$B$3:$E$83,4,0)+$BE$3 -> 1.5 | BF19: =VLOOKUP(B19,'Jan''26- Leave Bal'!$B$3:$F$83,5,0)+$BF$3 -> 5.5 | BG19: =VLOOKUP(B19,'Jan''26- Leave Bal'!$B$3:$G$83,6,0)+$BG$3 -> 13 | BH19: =VLOOKUP(B19,'Jan''26- Leave Bal'!$B$3:$H$83,7,0) -> 15 | BI19: =VLOOKUP(B19,'Jan''26- Leave Bal'!$B$3:$I$83,8,0)+$BI$3 -> 0.75 | BJ19: =IF((AP19+AQ19)<=BD19, (AP19+AQ19),BD19) -> 0 | BK19: =IF(((AP19+AQ19)-BJ19)>BE19,BE19,(AP19+AQ19)-BJ19) -> 0 | BL19: =IF((AP19+AQ19-BJ19-BK19)>=BF19,BF19,(AP19+AQ19-BJ19-BK19)) -> 0 | BM19: =IF((AP19+AQ19-BJ19-BK19-BL19)>=BG19,BG19,(AP19+AQ19-BJ19-BK19-BL19)) -> 0 | BN19: =AS19 -> 0 | BO19: =AP19+AQ19-BJ19-BK19-BL19-BM19 -> 0 | BP19: =BD19-BJ19 -> 0 | BQ19: =BE19-BK19 -> 1.5 | BR19: =BF19-BL19 -> 5.5 | BS19: =BG19-BM19 -> 13 | BT19: =BH19-BN19 -> 15 | BU19: =BI19 -> 0.75 | BW19: 0
A20: 17 | B20: JAI-732 | D20: Manappuram/Muthoot/Bajaj | E20: KYC | F20: Birdman | G20: Uppal | H20: 7670951643 | I20: sana.fathima@jukshio.com | J20: 44909 | L20: P | M20: P | N20: P | O20: P | P20: P | Q20: P | R20: W/O | S20: P | T20: L | U20: P | V20: P | W20: P | X20: P | Y20: P | Z20: W/O | AA20: P | AB20: P | AC20: P | AD20: L | AE20: P | AF20: P | AG20: W/O | AH20: P | AI20: HFL | AJ20: P | AK20: P | AL20: P | AM20: P | AN20: =COUNTIF(L20:AM20,"P")+COUNTIF(L20:AM20,"HFL")/2 -> 22.5 | AO20: =COUNTIF(L20:AM20,"W/O") -> 3 | AP20: =COUNTIF(L20:AM20,"L") -> 2 | AQ20: =COUNTIF(L20:AM20,"HFL")/2 -> 0.5 | AR20: =COUNTIF(L20:AM20,"H") -> 0 | AS20: =COUNTIF(L20:AM20,"MG") -> 0 | AT20: =COUNTIF(L20:AM20,"ML") -> 0 | AU20: =COUNTIF(L20:AM20,"UL") -> 0 | AV20: =COUNTIF(L20:AM20,"MC") -> 0 | AW20: =COUNTIF(L20:AM20,"BL") -> 0 | AX20: =COUNTIF(L20:AM20,"MDL") -> 0 | AY20: =COUNTIF(L20:AM20,"LOP") -> 0 | AZ20: =SUM(AN20:AY20) -> 28 | BA20: =SUM(AP20:AQ20,AS20:AY20,AN20) -> 25 | BB20: =AZ20-(AU20+BO20) -> 28 | BC20: =AN20/BA20 -> 0.9 | BD20: =VLOOKUP(B20,'Jan''26- Leave Bal'!$B$3:$D$83,3,0) -> 0 | BE20: =VLOOKUP(B20,'Jan''26- Leave Bal'!$B$3:$E$83,4,0)+$BE$3 -> 0.5 | BF20: =VLOOKUP(B20,'Jan''26- Leave Bal'!$B$3:$F$83,5,0)+$BF$3 -> 0.5 | BG20: =VLOOKUP(B20,'Jan''26- Leave Bal'!$B$3:$G$83,6,0)+$BG$3 -> 11.5 | BH20: =VLOOKUP(B20,'Jan''26- Leave Bal'!$B$3:$H$83,7,0) -> 15 | BI20: =VLOOKUP(B20,'Jan''26- Leave Bal'!$B$3:$I$83,8,0)+$BI$3 -> 0.75 | BJ20: =IF((AP20+AQ20)<=BD20, (AP20+AQ20),BD20) -> 0 | BK20: =IF(((AP20+AQ20)-BJ20)>BE20,BE20,(AP20+AQ20)-BJ20) -> 0.5 | BL20: =IF((AP20+AQ20-BJ20-BK20)>=BF20,BF20,(AP20+AQ20-BJ20-BK20)) -> 0.5 | BM20: =IF((AP20+AQ20-BJ20-BK20-BL20)>=BG20,BG20,(AP20+AQ20-BJ20-BK20-BL20)) -> 1.5 | BN20: =AS20 -> 0 | BO20: =AP20+AQ20-BJ20-BK20-BL20-BM20 -> 0 | BP20: =BD20-BJ20 -> 0 | BQ20: =BE20-BK20 -> 0 | BR20: =BF20-BL20 -> 0 | BS20: =BG20-BM20 -> 10 | BT20: =BH20-BN20 -> 15 | BU20: =BI20 -> 0.75 | BW20: 01st feb Weekoff taken early in Jan'26
A21: 18 | B21: JAI-1095 | D21: Manappuram/Muthoot/Bajaj | E21: KYC | F21: Birdman | G21: Uppal | H21: 9381253076 | I21: srivani.maddikunta@jukshio.com | J21: 45047 | L21: W/O | M21: P | N21: W/O | O21: L | P21: L | Q21: P | R21: P | S21: P | T21: P | U21: P | V21: P | W21: P | X21: P | Y21: P | Z21: W/O | AA21: P | AB21: P | AC21: P | AD21: P | AE21: W/O | AF21: P | AG21: P | AH21: P | AI21: P | AJ21: P | AK21: P | AL21: P | AM21: P | AN21: =COUNTIF(L21:AM21,"P")+COUNTIF(L21:AM21,"HFL")/2 -> 22 | AO21: =COUNTIF(L21:AM21,"W/O") -> 4 | AP21: =COUNTIF(L21:AM21,"L") -> 2 | AQ21: =COUNTIF(N21:AM21,"HFL")/2 -> 0 | AR21: =COUNTIF(L21:AM21,"H") -> 0 | AS21: =COUNTIF(N21:AM21,"MG") -> 0 | AT21: =COUNTIF(N21:AM21,"ML") -> 0 | AU21: =COUNTIF(L21:AM21,"UL") -> 0 | AV21: =COUNTIF(N21:AM21,"MC") -> 0 | AW21: =COUNTIF(N21:AM21,"BL") -> 0 | AX21: =COUNTIF(N21:AM21,"MDL") -> 0 | AY21: =COUNTIF(N21:AM21,"LOP") -> 0 | AZ21: =SUM(AN21:AY21) -> 28 | BA21: =SUM(AP21:AQ21,AS21:AY21,AN21) -> 24 | BB21: =AZ21-(AU21+BO21) -> 28 | BC21: =AN21/BA21 -> 0.91666667 | BD21: =VLOOKUP(B21,'Jan''26- Leave Bal'!$B$3:$D$83,3,0) -> 0 | BE21: =VLOOKUP(B21,'Jan''26- Leave Bal'!$B$3:$E$83,4,0)+$BE$3 -> 1 | BF21: =VLOOKUP(B21,'Jan''26- Leave Bal'!$B$3:$F$83,5,0)+$BF$3 -> 1 | BG21: =VLOOKUP(B21,'Jan''26- Leave Bal'!$B$3:$G$83,6,0)+$BG$3 -> 2 | BH21: =VLOOKUP(B21,'Jan''26- Leave Bal'!$B$3:$H$83,7,0) -> 15 | BI21: =VLOOKUP(B21,'Jan''26- Leave Bal'!$B$3:$I$83,8,0)+$BI$3 -> 0.75 | BJ21: =IF((AP21+AQ21)<=BD21, (AP21+AQ21),BD21) -> 0 | BK21: =IF(((AP21+AQ21)-BJ21)>BE21,BE21,(AP21+AQ21)-BJ21) -> 1 | BL21: =IF((AP21+AQ21-BJ21-BK21)>=BF21,BF21,(AP21+AQ21-BJ21-BK21)) -> 1 | BM21: =IF((AP21+AQ21-BJ21-BK21-BL21)>=BG21,BG21,(AP21+AQ21-BJ21-BK21-BL21)) -> 0 | BN21: =AS21 -> 0 | BO21: =AP21+AQ21-BJ21-BK21-BL21-BM21 -> 0 | BP21: =BD21-BJ21 -> 0 | BQ21: =BE21-BK21 -> 0 | BR21: =BF21-BL21 -> 0 | BS21: =BG21-BM21 -> 2 | BT21: =BH21-BN21 -> 15 | BU21: =BI21 -> 0.75 | BW21: 0
A22: 19 | B22: JAI-1280 | D22: Manappuram/Muthoot/Bajaj | E22: KYC | F22: Birdman | G22: Uppal | H22: 8374033884 | I22: revathi.bhushetti@jukshio.com | J22: 45159 | L22: P | M22: P | N22: P | O22: P | P22: P | Q22: P | R22: W/O | S22: P | T22: P | U22: P | V22: P | W22: P | X22: L | Y22: W/O | Z22: L | AA22: P | AB22: P | AC22: P | AD22: P | AE22: P | AF22: P | AG22: W/O | AH22: P | AI22: P | AJ22: P | AK22: P | AL22: P | AM22: P | AN22: =COUNTIF(L22:AM22,"P")+COUNTIF(L22:AM22,"HFL")/2 -> 23 | AO22: =COUNTIF(L22:AM22,"W/O") -> 3 | AP22: =COUNTIF(L22:AM22,"L") -> 2 | AQ22: =COUNTIF(L22:AM22,"HFL")/2 -> 0 | AR22: =COUNTIF(L22:AM22,"H") -> 0 | AS22: =COUNTIF(L22:AM22,"MG") -> 0 | AT22: =COUNTIF(L22:AM22,"ML") -> 0 | AU22: =COUNTIF(L22:AM22,"UL") -> 0 | AV22: =COUNTIF(L22:AM22,"MC") -> 0 | AW22: =COUNTIF(L22:AM22,"BL") -> 0 | AX22: =COUNTIF(L22:AM22,"MDL") -> 0 | AY22: =COUNTIF(L22:AM22,"LOP") -> 0 | AZ22: =SUM(AN22:AY22) -> 28 | BA22: =SUM(AP22:AQ22,AS22:AY22,AN22) -> 25 | BB22: =AZ22-(AU22+BO22) -> 28 | BC22: =AN22/BA22 -> 0.92 | BD22: =VLOOKUP(B22,'Jan''26- Leave Bal'!$B$3:$D$83,3,0) -> 0 | BE22: =VLOOKUP(B22,'Jan''26- Leave Bal'!$B$3:$E$83,4,0)+$BE$3 -> 0.5 | BF22: =VLOOKUP(B22,'Jan''26- Leave Bal'!$B$3:$F$83,5,0)+$BF$3 -> 0.5 | BG22: =VLOOKUP(B22,'Jan''26- Leave Bal'!$B$3:$G$83,6,0)+$BG$3 -> 3.5 | BH22: =VLOOKUP(B22,'Jan''26- Leave Bal'!$B$3:$H$83,7,0) -> 15 | BI22: =VLOOKUP(B22,'Jan''26- Leave Bal'!$B$3:$I$83,8,0)+$BI$3 -> 0.75 | BJ22: =IF((AP22+AQ22)<=BD22, (AP22+AQ22),BD22) -> 0 | BK22: =IF(((AP22+AQ22)-BJ22)>BE22,BE22,(AP22+AQ22)-BJ22) -> 0.5 | BL22: =IF((AP22+AQ22-BJ22-BK22)>=BF22,BF22,(AP22+AQ22-BJ22-BK22)) -> 0.5 | BM22: =IF((AP22+AQ22-BJ22-BK22-BL22)>=BG22,BG22,(AP22+AQ22-BJ22-BK22-BL22)) -> 1 | BN22: =AS22 -> 0 | BO22: =AP22+AQ22-BJ22-BK22-BL22-BM22 -> 0 | BP22: =BD22-BJ22 -> 0 | BQ22: =BE22-BK22 -> 0 | BR22: =BF22-BL22 -> 0 | BS22: =BG22-BM22 -> 2.5 | BT22: =BH22-BN22 -> 15 | BU22: =BI22 -> 0.75 | BW22: 01st feb Weekoff taken early in Jan'26
A23: 20 | B23: JAI-468 | D23: KYC | F23: Birdman | G23: Uppal | H23: 9542904926 | I23: bhargavi.rampally@jukshio.com | J23: 44845 | L23: P | M23: P | N23: P | O23: P | P23: P | Q23: P | R23: P | S23: W/O | T23: P | U23: P | V23: P | W23: P | X23: P | Y23: P | Z23: W/O | AA23: P | AB23: P | AC23: P | AD23: P | AE23: P | AF23: P | AG23: W/O | AH23: P | AI23: P | AJ23: P | AK23: P | AL23: P | AM23: P | AN23: =COUNTIF(L23:AM23,"P")+COUNTIF(L23:AM23,"HFL")/2 -> 25 | AO23: =COUNTIF(L23:AM23,"W/O") -> 3 | AP23: =COUNTIF(L23:AM23,"L") -> 0 | AQ23: =COUNTIF(L23:AM23,"HFL")/2 -> 0 | AR23: =COUNTIF(L23:AM23,"H") -> 0 | AS23: =COUNTIF(L23:AM23,"MG") -> 0 | AT23: =COUNTIF(L23:AM23,"ML") -> 0 | AU23: =COUNTIF(L23:AM23,"UL") -> 0 | AV23: =COUNTIF(L23:AM23,"MC") -> 0 | AW23: =COUNTIF(L23:AM23,"BL") -> 0 | AX23: =COUNTIF(L23:AM23,"MDL") -> 0 | AY23: =COUNTIF(L23:AM23,"LOP") -> 0 | AZ23: =SUM(AN23:AY23) -> 28 | BA23: =SUM(AP23:AQ23,AS23:AY23,AN23) -> 25 | BB23: =AZ23-(AU23+BO23) -> 28 | BC23: =AN23/BA23 -> 1 | BD23: =VLOOKUP(B23,'Jan''26- Leave Bal'!$B$3:$D$83,3,0) -> 0 | BE23: =VLOOKUP(B23,'Jan''26- Leave Bal'!$B$3:$E$83,4,0)+$BE$3 -> 0.5 | BF23: =VLOOKUP(B23,'Jan''26- Leave Bal'!$B$3:$F$83,5,0)+$BF$3 -> 0.5 | BG23: =VLOOKUP(B23,'Jan''26- Leave Bal'!$B$3:$G$83,6,0)+$BG$3 -> 1 | BH23: =VLOOKUP(B23,'Jan''26- Leave Bal'!$B$3:$H$83,7,0) -> 15 | BI23: =VLOOKUP(B23,'Jan''26- Leave Bal'!$B$3:$I$83,8,0)+$BI$3 -> 0.75 | BJ23: =IF((AP23+AQ23)<=BD23, (AP23+AQ23),BD23) -> 0 | BK23: =IF(((AP23+AQ23)-BJ23)>BE23,BE23,(AP23+AQ23)-BJ23) -> 0 | BL23: =IF((AP23+AQ23-BJ23-BK23)>=BF23,BF23,(AP23+AQ23-BJ23-BK23)) -> 0 | BM23: =IF((AP23+AQ23-BJ23-BK23-BL23)>=BG23,BG23,(AP23+AQ23-BJ23-BK23-BL23)) -> 0 | BN23: =AS23 -> 0 | BO23: =AP23+AQ23-BJ23-BK23-BL23-BM23 -> 0 | BP23: =BD23-BJ23 -> 0 | BQ23: =BE23-BK23 -> 0.5 | BR23: =BF23-BL23 -> 0.5 | BS23: =BG23-BM23 -> 1 | BT23: =BH23-BN23 -> 15 | BU23: =BI23 -> 0.75 | BW23: 01st feb Weekoff taken early in Jan'26
A24: 21 | B24: JAI-487 | D24: Manappuram/Muthoot/Bajaj | E24: KYC | F24: Labelling | G24: Suvali | H24: 7731030574 | I24: sangeetha.kuchula@jukshio.com | J24: 44845 | L24: P | M24: P | N24: L | O24: W/O | P24: P | Q24: P | R24: P | S24: L | T24: P | U24: P | V24: P | W24: P | X24: P | Y24: P | Z24: W/O | AA24: P | AB24: P | AC24: P | AD24: P | AE24: P | AF24: P | AG24: W/O | AH24: P | AI24: P | AJ24: W/O | AK24: HFL | AL24: P | AM24: P | AN24: =COUNTIF(L24:AM24,"P")+COUNTIF(L24:AM24,"HFL")/2 -> 21.5 | AO24: =COUNTIF(L24:AM24,"W/O") -> 4 | AP24: =COUNTIF(L24:AM24,"L") -> 2 | AQ24: =COUNTIF(L24:AM24,"HFL")/2 -> 0.5 | AR24: =COUNTIF(L24:AM24,"H") -> 0 | AS24: =COUNTIF(L24:AM24,"MG") -> 0 | AT24: =COUNTIF(L24:AM24,"ML") -> 0 | AU24: =COUNTIF(L24:AM24,"UL") -> 0 | AV24: =COUNTIF(L24:AM24,"MC") -> 0 | AW24: =COUNTIF(L24:AM24,"BL") -> 0 | AX24: =COUNTIF(L24:AM24,"MDL") -> 0 | AY24: =COUNTIF(L24:AM24,"LOP") -> 0 | AZ24: =SUM(AN24:AY24) -> 28 | BA24: =SUM(AP24:AQ24,AS24:AY24,AN24) -> 24 | BB24: =AZ24-(AU24+BO24) -> 28 | BC24: =AN24/BA24 -> 0.89583333 | BD24: =VLOOKUP(B24,'Jan''26- Leave Bal'!$B$3:$D$83,3,0) -> 0 | BE24: =VLOOKUP(B24,'Jan''26- Leave Bal'!$B$3:$E$83,4,0)+$BE$3 -> 0.5 | BF24: =VLOOKUP(B24,'Jan''26- Leave Bal'!$B$3:$F$83,5,0)+$BF$3 -> 0.5 | BG24: =VLOOKUP(B24,'Jan''26- Leave Bal'!$B$3:$G$83,6,0)+$BG$3 -> 3.3 | BH24: =VLOOKUP(B24,'Jan''26- Leave Bal'!$B$3:$H$83,7,0) -> 15 | BI24: =VLOOKUP(B24,'Jan''26- Leave Bal'!$B$3:$I$83,8,0)+$BI$3 -> 0.75 | BJ24: =IF((AP24+AQ24)<=BD24, (AP24+AQ24),BD24) -> 0 | BK24: =IF(((AP24+AQ24)-BJ24)>BE24,BE24,(AP24+AQ24)-BJ24) -> 0.5 | BL24: =IF((AP24+AQ24-BJ24-BK24)>=BF24,BF24,(AP24+AQ24-BJ24-BK24)) -> 0.5 | BM24: =IF((AP24+AQ24-BJ24-BK24-BL24)>=BG24,BG24,(AP24+AQ24-BJ24-BK24-BL24)) -> 1.5 | BN24: =AS24 -> 0 | BO24: =AP24+AQ24-BJ24-BK24-BL24-BM24 -> 0 | BP24: =BD24-BJ24 -> 0 | BQ24: =BE24-BK24 -> 0 | BR24: =BF24-BL24 -> 0 | BS24: =BG24-BM24 -> 1.8 | BT24: =BH24-BN24 -> 15 | BU24: =BI24 -> 0.75 | BW24: 01st feb Weekoff taken early in Jan'26
A25: 22 | B25: JAI-342 | D25: Manappuram/Muthoot/Bajaj | E25: KYC | F25: Labelling | G25: Suvali | H25: 7893787813 | I25: preethi.kairamkonda@jukshio.com | J25: 44431 | L25: P | M25: P | N25: P | O25: P | P25: P | Q25: P | R25: P | S25: W/O | T25: P | U25: P | V25: P | W25: P | X25: P | Y25: P | Z25: W/O | AA25: L | AB25: P | AC25: P | AD25: P | AE25: P | AF25: W/O | AG25: P | AH25: P | AI25: P | AJ25: P | AK25: P | AL25: P | AM25: P | AN25: =COUNTIF(L25:AM25,"P")+COUNTIF(L25:AM25,"HFL")/2 -> 24 | AO25: =COUNTIF(L25:AM25,"W/O") -> 3 | AP25: =COUNTIF(L25:AM25,"L") -> 1 | AQ25: =COUNTIF(L25:AM25,"HFL")/2 -> 0 | AR25: =COUNTIF(L25:AM25,"H") -> 0 | AS25: =COUNTIF(L25:AM25,"MG") -> 0 | AT25: =COUNTIF(L25:AM25,"ML") -> 0 | AU25: =COUNTIF(L25:AM25,"UL") -> 0 | AV25: =COUNTIF(L25:AM25,"MC") -> 0 | AW25: =COUNTIF(L25:AM25,"BL") -> 0 | AX25: =COUNTIF(L25:AM25,"MDL") -> 0 | AY25: =COUNTIF(L25:AM25,"LOP") -> 0 | AZ25: =SUM(AN25:AY25) -> 28 | BA25: =SUM(AP25:AQ25,AS25:AY25,AN25) -> 25 | BB25: =AZ25-(AU25+BO25) -> 28 | BC25: =AN25/BA25 -> 0.96 | BD25: =VLOOKUP(B25,'Jan''26- Leave Bal'!$B$3:$D$83,3,0) -> 0 | BE25: =VLOOKUP(B25,'Jan''26- Leave Bal'!$B$3:$E$83,4,0)+$BE$3 -> 0.5 | BF25: =VLOOKUP(B25,'Jan''26- Leave Bal'!$B$3:$F$83,5,0)+$BF$3 -> 0.5 | BG25: =VLOOKUP(B25,'Jan''26- Leave Bal'!$B$3:$G$83,6,0)+$BG$3 -> 3 | BH25: =VLOOKUP(B25,'Jan''26- Leave Bal'!$B$3:$H$83,7,0) -> 15 | BI25: =VLOOKUP(B25,'Jan''26- Leave Bal'!$B$3:$I$83,8,0)+$BI$3 -> 0.75 | BJ25: =IF((AP25+AQ25)<=BD25, (AP25+AQ25),BD25) -> 0 | BK25: =IF(((AP25+AQ25)-BJ25)>BE25,BE25,(AP25+AQ25)-BJ25) -> 0.5 | BL25: =IF((AP25+AQ25-BJ25-BK25)>=BF25,BF25,(AP25+AQ25-BJ25-BK25)) -> 0.5 | BM25: =IF((AP25+AQ25-BJ25-BK25-BL25)>=BG25,BG25,(AP25+AQ25-BJ25-BK25-BL25)) -> 0 | BN25: =AS25 -> 0 | BO25: =AP25+AQ25-BJ25-BK25-BL25-BM25 -> 0 | BP25: =BD25-BJ25 -> 0 | BQ25: =BE25-BK25 -> 0 | BR25: =BF25-BL25 -> 0 | BS25: =BG25-BM25 -> 3 | BT25: =BH25-BN25 -> 15 | BU25: =BI25 -> 0.75 | BW25: 01st feb Weekoff taken early in Jan'26
A26: 23 | B26: JAI-880 | D26: Manappuram/Muthoot/Bajaj | E26: KYC | F26: Labelling | G26: Suvali | H26: 6300868596 | I26: sowjanya.palugula@jukshio.com | J26: 45033 | L26: W/O | M26: P | N26: P | O26: P | P26: P | Q26: P | R26: P | S26: W/O | T26: P | U26: P | V26: P | W26: P | X26: L | Y26: P | Z26: W/O | AA26: P | AB26: P | AC26: P | AD26: P | AE26: P | AF26: P | AG26: W/O | AH26: P | AI26: P | AJ26: P | AK26: P | AL26: W/O | AM26: P | AN26: =COUNTIF(L26:AM26,"P")+COUNTIF(L26:AM26,"HFL")/2 -> 22 | AO26: =COUNTIF(L26:AL26,"W/O") -> 5 | AP26: =COUNTIF(L26:AL26,"L") -> 1 | AQ26: =COUNTIF(L26:AL26,"HFL")/2 -> 0 | AR26: =COUNTIF(L26:AL26,"H") -> 0 | AS26: =COUNTIF(L26:AL26,"MG") -> 0 | AT26: =COUNTIF(L26:AL26,"ML") -> 0 | AU26: =COUNTIF(L26:AL26,"UL") -> 0 | AV26: =COUNTIF(L26:AL26,"MC") -> 0 | AW26: =COUNTIF(L26:AL26,"BL") -> 0 | AX26: =COUNTIF(L26:AL26,"MDL") -> 0 | AY26: =COUNTIF(L26:AL26,"LOP") -> 0 | AZ26: =SUM(AN26:AY26) -> 28 | BA26: =SUM(AP26:AQ26,AS26:AY26,AN26) -> 23 | BB26: =AZ26-(AU26+BO26) -> 28 | BC26: =AN26/BA26 -> 0.95652174 | BD26: =VLOOKUP(B26,'Jan''26- Leave Bal'!$B$3:$D$83,3,0) -> 0 | BE26: =VLOOKUP(B26,'Jan''26- Leave Bal'!$B$3:$E$83,4,0)+$BE$3 -> 0.5 | BF26: =VLOOKUP(B26,'Jan''26- Leave Bal'!$B$3:$F$83,5,0)+$BF$3 -> 0.5 | BG26: =VLOOKUP(B26,'Jan''26- Leave Bal'!$B$3:$G$83,6,0)+$BG$3 -> 3 | BH26: =VLOOKUP(B26,'Jan''26- Leave Bal'!$B$3:$H$83,7,0) -> 0 | BI26: =VLOOKUP(B26,'Jan''26- Leave Bal'!$B$3:$I$83,8,0)+$BI$3 -> 0.75 | BJ26: =IF((AP26+AQ26)<=BD26, (AP26+AQ26),BD26) -> 0 | BK26: =IF(((AP26+AQ26)-BJ26)>BE26,BE26,(AP26+AQ26)-BJ26) -> 0.5 | BL26: =IF((AP26+AQ26-BJ26-BK26)>=BF26,BF26,(AP26+AQ26-BJ26-BK26)) -> 0.5 | BM26: =IF((AP26+AQ26-BJ26-BK26-BL26)>=BG26,BG26,(AP26+AQ26-BJ26-BK26-BL26)) -> 0 | BN26: =AS26 -> 0 | BO26: =AP26+AQ26-BJ26-BK26-BL26-BM26 -> 0 | BP26: =BD26-BJ26 -> 0 | BQ26: =BE26-BK26 -> 0 | BR26: =BF26-BL26 -> 0 | BS26: =BG26-BM26 -> 3 | BT26: =BH26-BN26 -> 0 | BU26: =BI26 -> 0.75 | BV26: 01st Mar weekoff taken in Feb Last week itself | BW26: 0
A27: 24 | B27: JAI-757 | D27: Manappuram/Muthoot/Bajaj | E27: KYC | F27: Labelling | G27: Suvali | H27: 6302885706 | I27: vasavi.gundla@jukshio.com | J27: 44909 | L27: P | M27: P | N27: P | O27: W/O | P27: P | Q27: P | R27: P | S27: P | T27: P | U27: P | V27: P | W27: P | X27: P | Y27: P | Z27: W/O | AA27: P | AB27: P | AC27: P | AD27: P | AE27: W/O | AF27: P | AG27: P | AH27: L | AI27: L | AJ27: P | AK27: P | AL27: P | AM27: P | AN27: =COUNTIF(L27:AM27,"P")+COUNTIF(L27:AM27,"HFL")/2 -> 23 | AO27: =COUNTIF(L27:AM27,"W/O") -> 3 | AP27: =COUNTIF(L27:AM27,"L") -> 2 | AQ27: =COUNTIF(L27:AM27,"HFL")/2 -> 0 | AR27: =COUNTIF(L27:AM27,"H") -> 0 | AS27: =COUNTIF(L27:AM27,"MG") -> 0 | AT27: =COUNTIF(L27:AM27,"ML") -> 0 | AU27: =COUNTIF(L27:AM27,"UL") -> 0 | AV27: =COUNTIF(L27:AM27,"MC") -> 0 | AW27: =COUNTIF(L27:AM27,"BL") -> 0 | AX27: =COUNTIF(L27:AM27,"MDL") -> 0 | AY27: =COUNTIF(L27:AM27,"LOP") -> 0 | AZ27: =SUM(AN27:AY27) -> 28 | BA27: =SUM(AP27:AQ27,AS27:AY27,AN27) -> 25 | BB27: =AZ27-(AU27+BO27) -> 28 | BC27: =AN27/BA27 -> 0.92 | BD27: =VLOOKUP(B27,'Jan''26- Leave Bal'!$B$3:$D$83,3,0) -> 0 | BE27: =VLOOKUP(B27,'Jan''26- Leave Bal'!$B$3:$E$83,4,0)+$BE$3 -> 0.5 | BF27: =VLOOKUP(B27,'Jan''26- Leave Bal'!$B$3:$F$83,5,0)+$BF$3 -> 0.5 | BG27: =VLOOKUP(B27,'Jan''26- Leave Bal'!$B$3:$G$83,6,0)+$BG$3 -> 1 | BH27: =VLOOKUP(B27,'Jan''26- Leave Bal'!$B$3:$H$83,7,0) -> 15 | BI27: =VLOOKUP(B27,'Jan''26- Leave Bal'!$B$3:$I$83,8,0)+$BI$3 -> 0.75 | BJ27: =IF((AP27+AQ27)<=BD27, (AP27+AQ27),BD27) -> 0 | BK27: =IF(((AP27+AQ27)-BJ27)>BE27,BE27,(AP27+AQ27)-BJ27) -> 0.5 | BL27: =IF((AP27+AQ27-BJ27-BK27)>=BF27,BF27,(AP27+AQ27-BJ27-BK27)) -> 0.5 | BM27: =IF((AP27+AQ27-BJ27-BK27-BL27)>=BG27,BG27,(AP27+AQ27-BJ27-BK27-BL27)) -> 1 | BN27: =AS27 -> 0 | BO27: =AP27+AQ27-BJ27-BK27-BL27-BM27 -> 0 | BP27: =BD27-BJ27 -> 0 | BQ27: =BE27-BK27 -> 0 | BR27: =BF27-BL27 -> 0 | BS27: =BG27-BM27 -> 0 | BT27: =BH27-BN27 -> 15 | BU27: =BI27 -> 0.75 | BW27: 01st feb Weekoff taken early in Jan'26
A28: 25 | B28: JAI-270 | D28: Manappuram/Muthoot/Bajaj | E28: KYC | F28: Curation | G28: Suvali | H28: 6304843335 | I28: Swathi.majjiga@jukshio.com | J28: 44326 | L28: W/O | M28: P | N28: P | O28: P | P28: P | Q28: P | R28: P | S28: W/O | T28: P | U28: P | V28: P | W28: P | X28: P | Y28: P | Z28: W/O | AA28: P | AB28: P | AC28: P | AD28: P | AE28: P | AF28: P | AG28: W/O | AH28: P | AI28: P | AJ28: P | AK28: P | AL28: P | AM28: W/O | AN28: =COUNTIF(L28:AM28,"P")+COUNTIF(L28:AM28,"HFL")/2 -> 23 | AO28: =COUNTIF(L28:AM28,"W/O") -> 5 | AP28: =COUNTIF(L28:AM28,"L") -> 0 | AQ28: =COUNTIF(L28:AM28,"HFL")/2 -> 0 | AR28: =COUNTIF(L28:AM28,"H") -> 0 | AS28: =COUNTIF(L28:AM28,"MG") -> 0 | AT28: =COUNTIF(L28:AM28,"ML") -> 0 | AU28: =COUNTIF(L28:AM28,"UL") -> 0 | AV28: =COUNTIF(L28:AM28,"MC") -> 0 | AW28: =COUNTIF(L28:AM28,"BL") -> 0 | AX28: =COUNTIF(L28:AM28,"MDL") -> 0 | AY28: =COUNTIF(L28:AM28,"LOP") -> 0 | AZ28: =SUM(AN28:AY28) -> 28 | BA28: =SUM(AP28:AQ28,AS28:AY28,AN28) -> 23 | BB28: =AZ28-(AU28+BO28) -> 28 | BC28: =AN28/BA28 -> 1 | BD28: =VLOOKUP(B28,'Jan''26- Leave Bal'!$B$3:$D$83,3,0) -> 4 | BE28: =VLOOKUP(B28,'Jan''26- Leave Bal'!$B$3:$E$83,4,0)+$BE$3 -> 5.5 | BF28: =VLOOKUP(B28,'Jan''26- Leave Bal'!$B$3:$F$83,5,0)+$BF$3 -> 5.5 | BG28: =VLOOKUP(B28,'Jan''26- Leave Bal'!$B$3:$G$83,6,0)+$BG$3 -> 13 | BH28: =VLOOKUP(B28,'Jan''26- Leave Bal'!$B$3:$H$83,7,0) -> 15 | BI28: =VLOOKUP(B28,'Jan''26- Leave Bal'!$B$3:$I$83,8,0)+$BI$3 -> 0.75 | BJ28: =IF((AP28+AQ28)<=BD28, (AP28+AQ28),BD28) -> 0 | BK28: =IF(((AP28+AQ28)-BJ28)>BE28,BE28,(AP28+AQ28)-BJ28) -> 0 | BL28: =IF((AP28+AQ28-BJ28-BK28)>=BF28,BF28,(AP28+AQ28-BJ28-BK28)) -> 0 | BM28: =IF((AP28+AQ28-BJ28-BK28-BL28)>=BG28,BG28,(AP28+AQ28-BJ28-BK28-BL28)) -> 0 | BN28: =AS28 -> 0 | BO28: =AP28+AQ28-BJ28-BK28-BL28-BM28 -> 0 | BP28: =BD28-BJ28 -> 4 | BQ28: =BE28-BK28 -> 5.5 | BR28: =BF28-BL28 -> 5.5 | BS28: =BG28-BM28 -> 13 | BT28: =BH28-BN28 -> 15 | BU28: =BI28 -> 0.75 | BV28: 01st Mar weekoff taken in Feb Last week itself | BW28: 0
A29: 26 | B29: JAI-383 | D29: Manappuram/Muthoot/Bajaj | E29: KYC | F29: Curation | G29: Suvali | H29: 91773 61601 | I29: rekha.thatikonda@jukshio.com | J29: 44522 | L29: W/O | M29: P | N29: P | O29: P | P29: P | Q29: P | R29: P | S29: W/O | T29: P | U29: P | V29: P | W29: W/O | X29: P | Y29: P | Z29: P | AA29: P | AB29: P | AC29: P | AD29: P | AE29: P | AF29: P | AG29: W/O | AH29: P | AI29: P | AJ29: P | AK29: P | AL29: P | AM29: L | AN29: =COUNTIF(L29:AM29,"P")+COUNTIF(L29:AM29,"HFL")/2 -> 23 | AO29: =COUNTIF(L29:AM29,"W/O") -> 4 | AP29: =COUNTIF(L29:AM29,"L") -> 1 | AQ29: =COUNTIF(L29:AM29,"HFL")/2 -> 0 | AR29: =COUNTIF(L29:AM29,"H") -> 0 | AS29: =COUNTIF(L29:AM29,"MG") -> 0 | AT29: =COUNTIF(L29:AM29,"ML") -> 0 | AU29: =COUNTIF(L29:AM29,"UL") -> 0 | AV29: =COUNTIF(L29:AM29,"MC") -> 0 | AW29: =COUNTIF(L29:AM29,"BL") -> 0 | AX29: =COUNTIF(L29:AM29,"MDL") -> 0 | AY29: =COUNTIF(L29:AM29,"LOP") -> 0 | AZ29: =SUM(AN29:AY29) -> 28 | BA29: =SUM(AP29:AQ29,AS29:AY29,AN29) -> 24 | BB29: =AZ29-(AU29+BO29) -> 28 | BC29: =AN29/BA29 -> 0.95833333 | BD29: =VLOOKUP(B29,'Jan''26- Leave Bal'!$B$3:$D$83,3,0) -> 0 | BE29: =VLOOKUP(B29,'Jan''26- Leave Bal'!$B$3:$E$83,4,0)+$BE$3 -> 0.5 | BF29: =VLOOKUP(B29,'Jan''26- Leave Bal'!$B$3:$F$83,5,0)+$BF$3 -> 0.5 | BG29: =VLOOKUP(B29,'Jan''26- Leave Bal'!$B$3:$G$83,6,0)+$BG$3 -> 4 | BH29: =VLOOKUP(B29,'Jan''26- Leave Bal'!$B$3:$H$83,7,0) -> 15 | BI29: =VLOOKUP(B29,'Jan''26- Leave Bal'!$B$3:$I$83,8,0)+$BI$3 -> 0.75 | BJ29: =IF((AP29+AQ29)<=BD29, (AP29+AQ29),BD29) -> 0 | BK29: =IF(((AP29+AQ29)-BJ29)>BE29,BE29,(AP29+AQ29)-BJ29) -> 0.5 | BL29: =IF((AP29+AQ29-BJ29-BK29)>=BF29,BF29,(AP29+AQ29-BJ29-BK29)) -> 0.5 | BM29: =IF((AP29+AQ29-BJ29-BK29-BL29)>=BG29,BG29,(AP29+AQ29-BJ29-BK29-BL29)) -> 0 | BN29: =AS29 -> 0 | BO29: =AP29+AQ29-BJ29-BK29-BL29-BM29 -> 0 | BP29: =BD29-BJ29 -> 0 | BQ29: =BE29-BK29 -> 0 | BR29: =BF29-BL29 -> 0 | BS29: =BG29-BM29 -> 4 | BT29: =BH29-BN29 -> 15 | BU29: =BI29 -> 0.75 | BW29: 0
A30: 27 | B30: JAI-583 | D30: Manappuram/Muthoot/Bajaj | E30: KYC | F30: Curation | G30: Suvali/Siddipet | H30: 7997575026 | I30: srinisha.racha@jukshio.com | J30: 44845 | L30: W/O | M30: P | N30: P | O30: L | P30: P | Q30: P | R30: P | S30: W/O | T30: P | U30: P | V30: P | W30: P | X30: P | Y30: P | Z30: W/O | AA30: P | AB30: P | AC30: P | AD30: P | AE30: P | AF30: P | AG30: W/O | AH30: P | AI30: L | AJ30: L | AK30: L | AL30: L | AM30: L | AN30: =COUNTIF(L30:AM30,"P")+COUNTIF(L30:AM30,"HFL")/2 -> 18 | AO30: =COUNTIF(L30:AM30,"W/O") -> 4 | AP30: =COUNTIF(L30:AM30,"L") -> 6 | AQ30: =COUNTIF(L30:AM30,"HFL")/2 -> 0 | AR30: =COUNTIF(L30:AM30,"H") -> 0 | AS30: =COUNTIF(L30:AM30,"MG") -> 0 | AT30: =COUNTIF(L30:AM30,"ML") -> 0 | AU30: =COUNTIF(L30:AM30,"UL") -> 0 | AV30: =COUNTIF(L30:AM30,"MC") -> 0 | AW30: =COUNTIF(L30:AM30,"BL") -> 0 | AX30: =COUNTIF(L30:AM30,"MDL") -> 0 | AY30: =COUNTIF(L30:AM30,"LOP") -> 0 | AZ30: =SUM(AN30:AY30) -> 28 | BA30: =SUM(AP30:AQ30,AS30:AY30,AN30) -> 24 | BB30: =AZ30-(AU30+BO30) -> 25 | BC30: =AN30/BA30 -> 0.75 | BD30: =VLOOKUP(B30,'Jan''26- Leave Bal'!$B$3:$D$83,3,0) -> 0 | BE30: =VLOOKUP(B30,'Jan''26- Leave Bal'!$B$3:$E$83,4,0)+$BE$3 -> 0.5 | BF30: =VLOOKUP(B30,'Jan''26- Leave Bal'!$B$3:$F$83,5,0)+$BF$3 -> 0.5 | BG30: =VLOOKUP(B30,'Jan''26- Leave Bal'!$B$3:$G$83,6,0)+$BG$3 -> 2 | BH30: =VLOOKUP(B30,'Jan''26- Leave Bal'!$B$3:$H$83,7,0) -> 0 | BI30: =VLOOKUP(B30,'Jan''26- Leave Bal'!$B$3:$I$83,8,0)+$BI$3 -> 0.75 | BJ30: =IF((AP30+AQ30)<=BD30, (AP30+AQ30),BD30) -> 0 | BK30: =IF(((AP30+AQ30)-BJ30)>BE30,BE30,(AP30+AQ30)-BJ30) -> 0.5 | BL30: =IF((AP30+AQ30-BJ30-BK30)>=BF30,BF30,(AP30+AQ30-BJ30-BK30)) -> 0.5 | BM30: =IF((AP30+AQ30-BJ30-BK30-BL30)>=BG30,BG30,(AP30+AQ30-BJ30-BK30-BL30)) -> 2 | BN30: =AS30 -> 0 | BO30: =AP30+AQ30-BJ30-BK30-BL30-BM30 -> 3 | BP30: =BD30-BJ30 -> 0 | BQ30: =BE30-BK30 -> 0 | BR30: =BF30-BL30 -> 0 | BS30: =BG30-BM30 -> 0 | BT30: =BH30-BN30 -> 0 | BU30: =BI30 -> 0.75 | BW30: 0
A31: 28 | B31: JAI-246 | D31: Manappuram/Muthoot/Bajaj | E31: KYC | F31: Curation | G31: Suvali | H31: 9014924293 | I31: akhila.gadhe@jukshio.com | J31: 44326 | L31: W/O | M31: P | N31: P | O31: W/O | P31: P | Q31: P | R31: P | S31: P | T31: P | U31: P | V31: P | W31: P | X31: P | Y31: P | Z31: W/O | AA31: P | AB31: P | AC31: P | AD31: P | AE31: P | AF31: P | AG31: W/O | AH31: P | AI31: P | AJ31: W/O | AK31: P | AL31: P | AM31: P | AN31: =COUNTIF(L31:AM31,"P")+COUNTIF(L31:AM31,"HFL")/2 -> 23 | AO31: =COUNTIF(L31:AM31,"W/O") -> 5 | AP31: =COUNTIF(L31:AM31,"L") -> 0 | AQ31: =COUNTIF(L31:AM31,"HFL")/2 -> 0 | AR31: =COUNTIF(L31:AM31,"H") -> 0 | AS31: =COUNTIF(L31:AM31,"MG") -> 0 | AT31: =COUNTIF(L31:AM31,"ML") -> 0 | AU31: =COUNTIF(L31:AM31,"UL") -> 0 | AV31: =COUNTIF(L31:AM31,"MC") -> 0 | AW31: =COUNTIF(L31:AM31,"BL") -> 0 | AX31: =COUNTIF(L31:AM31,"MDL") -> 0 | AY31: =COUNTIF(L31:AM31,"LOP") -> 0 | AZ31: =SUM(AN31:AY31) -> 28 | BA31: =SUM(AP31:AQ31,AS31:AY31,AN31) -> 23 | BB31: =AZ31-(AU31+BO31) -> 28 | BC31: =AN31/BA31 -> 1 | BD31: =VLOOKUP(B31,'Jan''26- Leave Bal'!$B$3:$D$83,3,0) -> 0 | BE31: =VLOOKUP(B31,'Jan''26- Leave Bal'!$B$3:$E$83,4,0)+$BE$3 -> 0.5 | BF31: =VLOOKUP(B31,'Jan''26- Leave Bal'!$B$3:$F$83,5,0)+$BF$3 -> 0.5 | BG31: =VLOOKUP(B31,'Jan''26- Leave Bal'!$B$3:$G$83,6,0)+$BG$3 -> 6.5 | BH31: =VLOOKUP(B31,'Jan''26- Leave Bal'!$B$3:$H$83,7,0) -> 15 | BI31: =VLOOKUP(B31,'Jan''26- Leave Bal'!$B$3:$I$83,8,0)+$BI$3 -> 0.75 | BJ31: =IF((AP31+AQ31)<=BD31, (AP31+AQ31),BD31) -> 0 | BK31: =IF(((AP31+AQ31)-BJ31)>BE31,BE31,(AP31+AQ31)-BJ31) -> 0 | BL31: =IF((AP31+AQ31-BJ31-BK31)>=BF31,BF31,(AP31+AQ31-BJ31-BK31)) -> 0 | BM31: =IF((AP31+AQ31-BJ31-BK31-BL31)>=BG31,BG31,(AP31+AQ31-BJ31-BK31-BL31)) -> 0 | BN31: =AS31 -> 0 | BO31: =AP31+AQ31-BJ31-BK31-BL31-BM31 -> 0 | BP31: =BD31-BJ31 -> 0 | BQ31: =BE31-BK31 -> 0.5 | BR31: =BF31-BL31 -> 0.5 | BS31: =BG31-BM31 -> 6.5 | BT31: =BH31-BN31 -> 15 | BU31: =BI31 -> 0.75 | BV31: 01st Mar weekoff taken in Feb Last week itself | BW31: 0
A32: 29 | B32: JAI-796 | D32: BHT | E32: BHT | F32: BHT | G32: Uppal | H32: 93906 40467 | I32: divya.baddam@jukshio.com | L32: W/O | M32: P | N32: P | O32: P | P32: P | Q32: P | R32: W/O | S32: W/O | T32: P | U32: P | V32: P | W32: P | X32: L | Y32: L | Z32: W/O | AA32: P | AB32: P | AC32: P | AD32: P | AE32: P | AF32: P | AG32: W/O | AH32: P | AI32: P | AJ32: P | AK32: P | AL32: L | AM32: P | AN32: =COUNTIF(L32:AM32,"P")+COUNTIF(L32:AM32,"HFL")/2 -> 20 | AO32: =COUNTIF(L32:AM32,"W/O") -> 5 | AP32: =COUNTIF(L32:AM32,"L") -> 3 | AQ32: =COUNTIF(L32:AM32,"HFL")/2 -> 0 | AR32: =COUNTIF(L32:AM32,"H") -> 0 | AS32: =COUNTIF(L32:AM32,"MG") -> 0 | AT32: =COUNTIF(L32:AM32,"ML") -> 0 | AU32: =COUNTIF(L32:AM32,"UL") -> 0 | AV32: =COUNTIF(L32:AM32,"MC") -> 0 | AW32: =COUNTIF(L32:AM32,"BL") -> 0 | AX32: =COUNTIF(L32:AM32,"MDL") -> 0 | AY32: =COUNTIF(L32:AM32,"LOP") -> 0 | AZ32: =SUM(AN32:AY32) -> 28 | BA32: =SUM(AP32:AQ32,AS32:AY32,AN32) -> 23 | BB32: =AZ32-(AU32+BO32) -> 28 | BC32: =AN32/BA32 -> 0.86956522 | BD32: =VLOOKUP(B32,'Jan''26- Leave Bal'!$B$3:$D$83,3,0) -> 0 | BE32: =VLOOKUP(B32,'Jan''26- Leave Bal'!$B$3:$E$83,4,0)+$BE$3 -> 0.5 | BF32: =VLOOKUP(B32,'Jan''26- Leave Bal'!$B$3:$F$83,5,0)+$BF$3 -> 3.5 | BG32: =VLOOKUP(B32,'Jan''26- Leave Bal'!$B$3:$G$83,6,0)+$BG$3 -> 11 | BH32: =VLOOKUP(B32,'Jan''26- Leave Bal'!$B$3:$H$83,7,0) -> 15 | BI32: =VLOOKUP(B32,'Jan''26- Leave Bal'!$B$3:$I$83,8,0)+$BI$3 -> 0.75 | BJ32: =IF((AP32+AQ32)<=BD32, (AP32+AQ32),BD32) -> 0 | BK32: =IF(((AP32+AQ32)-BJ32)>BE32,BE32,(AP32+AQ32)-BJ32) -> 0.5 | BL32: =IF((AP32+AQ32-BJ32-BK32)>=BF32,BF32,(AP32+AQ32-BJ32-BK32)) -> 2.5 | BM32: =IF((AP32+AQ32-BJ32-BK32-BL32)>=BG32,BG32,(AP32+AQ32-BJ32-BK32-BL32)) -> 0 | BN32: =AS32 -> 0 | BO32: =AP32+AQ32-BJ32-BK32-BL32-BM32 -> 0 | BP32: =BD32-BJ32 -> 0 | BQ32: =BE32-BK32 -> 0 | BR32: =BF32-BL32 -> 1 | BS32: =BG32-BM32 -> 11 | BT32: =BH32-BN32 -> 15 | BU32: =BI32 -> 0.75 | BW32: 0
A33: 30 | B33: JAI-268 | D33: Manappuram/Muthoot/Bajaj | E33: KYC | F33: OCR curation | G33: Uppal | H33: 7702552113 | I33: spandana.samudrala@jukshio.com | J33: 44326 | L33: W/O | M33: P | N33: P | O33: P | P33: P | Q33: P | R33: P | S33: W/O | T33: P | U33: P | V33: P | W33: P | X33: P | Y33: P | Z33: W/O | AA33: P | AB33: P | AC33: P | AD33: P | AE33: P | AF33: P | AG33: W/O | AH33: P | AI33: P | AJ33: P | AK33: L | AL33: P | AM33: P | AN33: =COUNTIF(L33:AM33,"P")+COUNTIF(L33:AM33,"HFL")/2 -> 23 | AO33: =COUNTIF(L33:AM33,"W/O") -> 4 | AP33: =COUNTIF(L33:AM33,"L") -> 1 | AQ33: =COUNTIF(L33:AM33,"HFL")/2 -> 0 | AR33: =COUNTIF(L33:AM33,"H") -> 0 | AS33: =COUNTIF(L33:AM33,"MG") -> 0 | AT33: =COUNTIF(L33:AM33,"ML") -> 0 | AU33: =COUNTIF(L33:AM33,"UL") -> 0 | AV33: =COUNTIF(L33:AM33,"MC") -> 0 | AW33: =COUNTIF(L33:AM33,"BL") -> 0 | AX33: =COUNTIF(L33:AM33,"MDL") -> 0 | AY33: =COUNTIF(L33:AM33,"LOP") -> 0 | AZ33: =SUM(AN33:AY33) -> 28 | BA33: =SUM(AP33:AQ33,AS33:AY33,AN33) -> 24 | BB33: =AZ33-(AU33+BO33) -> 28 | BC33: =AN33/BA33 -> 0.95833333 | BD33: =VLOOKUP(B33,'Jan''26- Leave Bal'!$B$3:$D$83,3,0) -> 0 | BE33: =VLOOKUP(B33,'Jan''26- Leave Bal'!$B$3:$E$83,4,0)+$BE$3 -> 1 | BF33: =VLOOKUP(B33,'Jan''26- Leave Bal'!$B$3:$F$83,5,0)+$BF$3 -> 1 | BG33: =VLOOKUP(B33,'Jan''26- Leave Bal'!$B$3:$G$83,6,0)+$BG$3 -> 12 | BH33: =VLOOKUP(B33,'Jan''26- Leave Bal'!$B$3:$H$83,7,0) -> 15 | BI33: =VLOOKUP(B33,'Jan''26- Leave Bal'!$B$3:$I$83,8,0)+$BI$3 -> 0.75 | BJ33: =IF((AP33+AQ33)<=BD33, (AP33+AQ33),BD33) -> 0 | BK33: =IF(((AP33+AQ33)-BJ33)>BE33,BE33,(AP33+AQ33)-BJ33) -> 1 | BL33: =IF((AP33+AQ33-BJ33-BK33)>=BF33,BF33,(AP33+AQ33-BJ33-BK33)) -> 0 | BM33: =IF((AP33+AQ33-BJ33-BK33-BL33)>=BG33,BG33,(AP33+AQ33-BJ33-BK33-BL33)) -> 0 | BN33: =AS33 -> 0 | BO33: =AP33+AQ33-BJ33-BK33-BL33-BM33 -> 0 | BP33: =BD33-BJ33 -> 0 | BQ33: =BE33-BK33 -> 0 | BR33: =BF33-BL33 -> 1 | BS33: =BG33-BM33 -> 12 | BT33: =BH33-BN33 -> 15 | BU33: =BI33 -> 0.75 | BW33: 0
A34: 31 | B34: JAI-173 | D34: Manappuram/Muthoot/Bajaj | E34: KYC | F34: OCR curation | G34: Uppal | H34: 7075587976 | I34: nisha.jabeen@jukshio.com | J34: 44131 | L34: P | M34: P | N34: P | O34: P | P34: P | Q34: P | R34: P | S34: W/O | T34: P | U34: P | V34: P | W34: P | X34: P | Y34: P | Z34: W/O | AA34: P | AB34: P | AC34: P | AD34: P | AE34: P | AF34: P | AG34: W/O | AH34: P | AI34: P | AJ34: P | AK34: P | AL34: W/O | AM34: P | AN34: =COUNTIF(L34:AM34,"P")+COUNTIF(L34:AM34,"HFL")/2 -> 24 | AO34: =COUNTIF(L34:AM34,"W/O") -> 4 | AP34: =COUNTIF(L34:AM34,"L") -> 0 | AQ34: =COUNTIF(L34:AM34,"HFL")/2 -> 0 | AR34: =COUNTIF(L34:AM34,"H") -> 0 | AS34: =COUNTIF(L34:AM34,"MG") -> 0 | AT34: =COUNTIF(L34:AM34,"ML") -> 0 | AU34: =COUNTIF(L34:AM34,"UL") -> 0 | AV34: =COUNTIF(L34:AM34,"MC") -> 0 | AW34: =COUNTIF(L34:AM34,"BL") -> 0 | AX34: =COUNTIF(L34:AM34,"MDL") -> 0 | AY34: =COUNTIF(L34:AM34,"LOP") -> 0 | AZ34: =SUM(AN34:AY34) -> 28 | BA34: =SUM(AP34:AQ34,AS34:AY34,AN34) -> 24 | BB34: =AZ34-(AU34+BO34) -> 28 | BC34: =AN34/BA34 -> 1 | BD34: =VLOOKUP(B34,'Jan''26- Leave Bal'!$B$3:$D$83,3,0) -> 0 | BE34: =VLOOKUP(B34,'Jan''26- Leave Bal'!$B$3:$E$83,4,0)+$BE$3 -> 1 | BF34: =VLOOKUP(B34,'Jan''26- Leave Bal'!$B$3:$F$83,5,0)+$BF$3 -> 1 | BG34: =VLOOKUP(B34,'Jan''26- Leave Bal'!$B$3:$G$83,6,0)+$BG$3 -> 7 | BH34: =VLOOKUP(B34,'Jan''26- Leave Bal'!$B$3:$H$83,7,0) -> 15 | BI34: =VLOOKUP(B34,'Jan''26- Leave Bal'!$B$3:$I$83,8,0)+$BI$3 -> 0.75 | BJ34: =IF((AP34+AQ34)<=BD34, (AP34+AQ34),BD34) -> 0 | BK34: =IF(((AP34+AQ34)-BJ34)>BE34,BE34,(AP34+AQ34)-BJ34) -> 0 | BL34: =IF((AP34+AQ34-BJ34-BK34)>=BF34,BF34,(AP34+AQ34-BJ34-BK34)) -> 0 | BM34: =IF((AP34+AQ34-BJ34-BK34-BL34)>=BG34,BG34,(AP34+AQ34-BJ34-BK34-BL34)) -> 0 | BN34: =AS34 -> 0 | BO34: =AP34+AQ34-BJ34-BK34-BL34-BM34 -> 0 | BP34: =BD34-BJ34 -> 0 | BQ34: =BE34-BK34 -> 1 | BR34: =BF34-BL34 -> 1 | BS34: =BG34-BM34 -> 7 | BT34: =BH34-BN34 -> 15 | BU34: =BI34 -> 0.75 | BW34: 0
A35: 32 | B35: JAI-1038 | D35: Retail | E35: Cartzy | F35: Testing (Training) | G35: Uppal | H35: 7780170122 | I35: banoth.soniya@jukshio.com | J35: 45033 | L35: W/O | M35: P | N35: P | O35: P | P35: P | Q35: P | R35: P | S35: W/O | T35: W/O | U35: P | V35: P | W35: P | X35: L | Y35: P | Z35: P | AA35: P | AB35: P | AC35: P | AD35: P | AE35: P | AF35: P | AG35: W/O | AH35: P | AI35: P | AJ35: L | AK35: L | AL35: P | AM35: P | AN35: =COUNTIF(L35:AM35,"P")+COUNTIF(L35:AM35,"HFL")/2 -> 21 | AO35: =COUNTIF(L35:AM35,"W/O") -> 4 | AP35: =COUNTIF(L35:AM35,"L") -> 3 | AQ35: =COUNTIF(L35:AM35,"HFL")/2 -> 0 | AR35: =COUNTIF(L35:AM35,"H") -> 0 | AS35: =COUNTIF(L35:AM35,"MG") -> 0 | AT35: =COUNTIF(L35:AM35,"ML") -> 0 | AU35: =COUNTIF(L35:AM35,"UL") -> 0 | AV35: =COUNTIF(L35:AM35,"MC") -> 0 | AW35: =COUNTIF(L35:AM35,"BL") -> 0 | AX35: =COUNTIF(L35:AM35,"MDL") -> 0 | AY35: =COUNTIF(L35:AM35,"LOP") -> 0 | AZ35: =SUM(AN35:AY35) -> 28 | BA35: =SUM(AP35:AQ35,AS35:AY35,AN35) -> 24 | BB35: =AZ35-(AU35+BO35) -> 28 | BC35: =AN35/BA35 -> 0.875 | BD35: =VLOOKUP(B35,'Jan''26- Leave Bal'!$B$3:$D$83,3,0) -> 0 | BE35: =VLOOKUP(B35,'Jan''26- Leave Bal'!$B$3:$E$83,4,0)+$BE$3 -> 0.5 | BF35: =VLOOKUP(B35,'Jan''26- Leave Bal'!$B$3:$F$83,5,0)+$BF$3 -> 0.5 | BG35: =VLOOKUP(B35,'Jan''26- Leave Bal'!$B$3:$G$83,6,0)+$BG$3 -> 4 | BH35: =VLOOKUP(B35,'Jan''26- Leave Bal'!$B$3:$H$83,7,0) -> 15 | BI35: =VLOOKUP(B35,'Jan''26- Leave Bal'!$B$3:$I$83,8,0)+$BI$3 -> 0.75 | BJ35: =IF((AP35+AQ35)<=BD35, (AP35+AQ35),BD35) -> 0 | BK35: =IF(((AP35+AQ35)-BJ35)>BE35,BE35,(AP35+AQ35)-BJ35) -> 0.5 | BL35: =IF((AP35+AQ35-BJ35-BK35)>=BF35,BF35,(AP35+AQ35-BJ35-BK35)) -> 0.5 | BM35: =IF((AP35+AQ35-BJ35-BK35-BL35)>=BG35,BG35,(AP35+AQ35-BJ35-BK35-BL35)) -> 2 | BN35: =AS35 -> 0 | BO35: =AP35+AQ35-BJ35-BK35-BL35-BM35 -> 0 | BP35: =BD35-BJ35 -> 0 | BQ35: =BE35-BK35 -> 0 | BR35: =BF35-BL35 -> 0 | BS35: =BG35-BM35 -> 2 | BT35: =BH35-BN35 -> 15 | BU35: =BI35 -> 0.75 | BW35: 0
A36: 33 | B36: JAI-1158 | D36: Retail | E36: Cartzy | F36: Testing (Training) | G36: Uppal | H36: 8074795436 | I36: hymavathi.jatangi@jukshio.com | J36: 45101 | L36: P | M36: P | N36: P | O36: P | P36: P | Q36: P | R36: P | S36: W/O | T36: P | U36: P | V36: P | W36: W/O | X36: L | Y36: HFL | Z36: P | AA36: W/O | AB36: P | AC36: P | AD36: P | AE36: L | AF36: P | AG36: L | AH36: L | AI36: P | AJ36: L | AK36: P | AL36: W/O | AM36: P | AN36: =COUNTIF(L36:AM36,"P")+COUNTIF(L36:AM36,"HFL")/2 -> 18.5 | AO36: =COUNTIF(L36:AM36,"W/O") -> 4 | AP36: =COUNTIF(L36:AM36,"L") -> 5 | AQ36: =COUNTIF(L36:AM36,"HFL")/2 -> 0.5 | AR36: =COUNTIF(L36:AM36,"H") -> 0 | AS36: =COUNTIF(L36:AM36,"MG") -> 0 | AT36: =COUNTIF(L36:AM36,"ML") -> 0 | AU36: =COUNTIF(L36:AM36,"UL") -> 0 | AV36: =COUNTIF(L36:AM36,"MC") -> 0 | AW36: =COUNTIF(L36:AM36,"BL") -> 0 | AX36: =COUNTIF(L36:AM36,"MDL") -> 0 | AY36: =COUNTIF(L36:AM36,"LOP") -> 0 | AZ36: =SUM(AN36:AY36) -> 28 | BA36: =SUM(AP36:AQ36,AS36:AY36,AN36) -> 24 | BB36: =AZ36-(AU36+BO36) -> 28 | BC36: =AN36/BA36 -> 0.77083333 | BD36: =VLOOKUP(B36,'Jan''26- Leave Bal'!$B$3:$D$83,3,0) -> 0 | BE36: =VLOOKUP(B36,'Jan''26- Leave Bal'!$B$3:$E$83,4,0)+$BE$3 -> 0.5 | BF36: =VLOOKUP(B36,'Jan''26- Leave Bal'!$B$3:$F$83,5,0)+$BF$3 -> 0.5 | BG36: =VLOOKUP(B36,'Jan''26- Leave Bal'!$B$3:$G$83,6,0)+$BG$3 -> 8.5 | BH36: =VLOOKUP(B36,'Jan''26- Leave Bal'!$B$3:$H$83,7,0) -> 15 | BI36: =VLOOKUP(B36,'Jan''26- Leave Bal'!$B$3:$I$83,8,0)+$BI$3 -> 0.75 | BJ36: =IF((AP36+AQ36)<=BD36, (AP36+AQ36),BD36) -> 0 | BK36: =IF(((AP36+AQ36)-BJ36)>BE36,BE36,(AP36+AQ36)-BJ36) -> 0.5 | BL36: =IF((AP36+AQ36-BJ36-BK36)>=BF36,BF36,(AP36+AQ36-BJ36-BK36)) -> 0.5 | BM36: =IF((AP36+AQ36-BJ36-BK36-BL36)>=BG36,BG36,(AP36+AQ36-BJ36-BK36-BL36)) -> 4.5 | BN36: =AS36 -> 0 | BO36: =AP36+AQ36-BJ36-BK36-BL36-BM36 -> 0 | BP36: =BD36-BJ36 -> 0 | BQ36: =BE36-BK36 -> 0 | BR36: =BF36-BL36 -> 0 | BS36: =BG36-BM36 -> 4 | BT36: =BH36-BN36 -> 15 | BU36: =BI36 -> 0.75 | BV36: 01st Mar weekoff taken in Feb Last week itself | BW36: 01st feb Weekoff taken early in Jan'26
A37: 34 | B37: JAI-542 | D37: Retail | E37: Cartzy | F37: HQA | G37: Suvali | H37: 6281188027 | I37: Saipriya.dandu@jukshio.com | J37: 44845 | L37: P | M37: W/O | N37: P | O37: P | P37: P | Q37: P | R37: P | S37: P | T37: P | U37: P | V37: P | W37: P | X37: W/O | Y37: P | Z37: P | AA37: P | AB37: W/O | AC37: P | AD37: P | AE37: P | AF37: P | AG37: P | AH37: P | AI37: P | AJ37: W/O | AK37: P | AL37: P | AM37: P | AN37: =COUNTIF(L37:AM37,"P")+COUNTIF(L37:AM37,"HFL")/2 -> 24 | AO37: =COUNTIF(L37:AM37,"W/O") -> 4 | AP37: =COUNTIF(L37:AM37,"L") -> 0 | AQ37: =COUNTIF(L37:AM37,"HFL")/2 -> 0 | AR37: =COUNTIF(L37:AM37,"H") -> 0 | AS37: =COUNTIF(L37:AM37,"MG") -> 0 | AT37: =COUNTIF(L37:AM37,"ML") -> 0 | AU37: =COUNTIF(L37:AM37,"UL") -> 0 | AV37: =COUNTIF(L37:AM37,"MC") -> 0 | AW37: =COUNTIF(L37:AM37,"BL") -> 0 | AX37: =COUNTIF(L37:AM37,"MDL") -> 0 | AY37: =COUNTIF(L37:AM37,"LOP") -> 0 | AZ37: =SUM(AN37:AY37) -> 28 | BA37: =SUM(AP37:AQ37,AS37:AY37,AN37) -> 24 | BB37: =AZ37-(AU37+BO37) -> 28 | BC37: =AN37/BA37 -> 1 | BD37: =VLOOKUP(B37,'Jan''26- Leave Bal'!$B$3:$D$83,3,0) -> 0 | BE37: =VLOOKUP(B37,'Jan''26- Leave Bal'!$B$3:$E$83,4,0)+$BE$3 -> 1 | BF37: =VLOOKUP(B37,'Jan''26- Leave Bal'!$B$3:$F$83,5,0)+$BF$3 -> 1 | BG37: =VLOOKUP(B37,'Jan''26- Leave Bal'!$B$3:$G$83,6,0)+$BG$3 -> 2 | BH37: =VLOOKUP(B37,'Jan''26- Leave Bal'!$B$3:$H$83,7,0) -> 15 | BI37: =VLOOKUP(B37,'Jan''26- Leave Bal'!$B$3:$I$83,8,0)+$BI$3 -> 0.75 | BJ37: =IF((AP37+AQ37)<=BD37, (AP37+AQ37),BD37) -> 0 | BK37: =IF(((AP37+AQ37)-BJ37)>BE37,BE37,(AP37+AQ37)-BJ37) -> 0 | BL37: =IF((AP37+AQ37-BJ37-BK37)>=BF37,BF37,(AP37+AQ37-BJ37-BK37)) -> 0 | BM37: =IF((AP37+AQ37-BJ37-BK37-BL37)>=BG37,BG37,(AP37+AQ37-BJ37-BK37-BL37)) -> 0 | BN37: =AS37 -> 0 | BO37: =AP37+AQ37-BJ37-BK37-BL37-BM37 -> 0 | BP37: =BD37-BJ37 -> 0 | BQ37: =BE37-BK37 -> 1 | BR37: =BF37-BL37 -> 1 | BS37: =BG37-BM37 -> 2 | BT37: =BH37-BN37 -> 15 | BU37: =BI37 -> 0.75 | BV37: 01st Mar weekoff taken in Feb Last week itself | BW37: 01st feb Weekoff taken early in Jan'26
A38: 35 | B38: JAI-1094 | D38: Retail | E38: Cartzy | F38: HQA | G38: Uppal | H38: 8374717290 | I38: srivani.busavaly@jukshio.com | J38: 45047 | L38: W/O | M38: W/O | N38: L | O38: P | P38: P | Q38: P | R38: P | S38: P | T38: P | U38: P | V38: P | W38: P | X38: P | Y38: W/O | Z38: MG | AA38: MG | AB38: MG | AC38: MG | AD38: MG | AE38: MG | AF38: MG | AG38: MG | AH38: MG | AI38: MG | AJ38: MG | AK38: MG | AL38: MG | AM38: MG | AN38: =COUNTIF(L38:AM38,"P")+COUNTIF(L38:AM38,"HFL")/2 -> 10 | AO38: =COUNTIF(L38:AM38,"W/O") -> 3 | AP38: =COUNTIF(L38:AM38,"L") -> 1 | AQ38: =COUNTIF(L38:AM38,"HFL")/2 -> 0 | AR38: =COUNTIF(L38:AM38,"H") -> 0 | AS38: =COUNTIF(L38:AM38,"MG") -> 14 | AT38: =COUNTIF(L38:AM38,"ML") -> 0 | AU38: =COUNTIF(L38:AM38,"UL") -> 0 | AV38: =COUNTIF(L38:AM38,"MC") -> 0 | AW38: =COUNTIF(L38:AM38,"BL") -> 0 | AX38: =COUNTIF(L38:AM38,"MDL") -> 0 | AY38: =COUNTIF(L38:AM38,"LOP") -> 0 | AZ38: =SUM(AN38:AY38) -> 28 | BA38: =SUM(AP38:AQ38,AS38:AY38,AN38) -> 25 | BB38: =AZ38-(AU38+BO38) -> 28 | BC38: =AN38/BA38 -> 0.4 | BD38: =VLOOKUP(B38,'Jan''26- Leave Bal'!$B$3:$D$83,3,0) -> 0 | BE38: =VLOOKUP(B38,'Jan''26- Leave Bal'!$B$3:$E$83,4,0)+$BE$3 -> 1 | BF38: =VLOOKUP(B38,'Jan''26- Leave Bal'!$B$3:$F$83,5,0)+$BF$3 -> 1 | BG38: =VLOOKUP(B38,'Jan''26- Leave Bal'!$B$3:$G$83,6,0)+$BG$3 -> 5.5 | BH38: =VLOOKUP(B38,'Jan''26- Leave Bal'!$B$3:$H$83,7,0) -> 15 | BI38: =VLOOKUP(B38,'Jan''26- Leave Bal'!$B$3:$I$83,8,0)+$BI$3 -> 0.75 | BJ38: =IF((AP38+AQ38)<=BD38, (AP38+AQ38),BD38) -> 0 | BK38: =IF(((AP38+AQ38)-BJ38)>BE38,BE38,(AP38+AQ38)-BJ38) -> 1 | BL38: =IF((AP38+AQ38-BJ38-BK38)>=BF38,BF38,(AP38+AQ38-BJ38-BK38)) -> 0 | BM38: =IF((AP38+AQ38-BJ38-BK38-BL38)>=BG38,BG38,(AP38+AQ38-BJ38-BK38-BL38)) -> 0 | BN38: =AS38 -> 14 | BO38: =AP38+AQ38-BJ38-BK38-BL38-BM38 -> 0 | BP38: =BD38-BJ38 -> 0 | BQ38: =BE38-BK38 -> 0 | BR38: =BF38-BL38 -> 1 | BS38: =BG38-BM38 -> 5.5 | BT38: =BH38-BN38 -> 1 | BU38: =BI38 -> 0.75 | BW38: 0
A39: 36 | B39: JAI-1246 | D39: Retail | E39: Cartzy | F39: HQA | G39: Uppal | H39: 7989605125 | I39: kalpana.gurram@jukshio.com | J39: 45159 | L39: P | M39: P | N39: P | O39: P | P39: P | Q39: P | R39: W/O | S39: P | T39: P | U39: P | V39: P | W39: P | X39: W/O | Y39: P | Z39: P | AA39: L | AB39: W/O | AC39: L | AD39: L | AE39: L | AF39: L | AG39: L | AH39: L | AI39: P | AJ39: P | AK39: P | AL39: P | AM39: P | AN39: =COUNTIF(L39:AM39,"P")+COUNTIF(L39:AM39,"HFL")/2 -> 18 | AO39: =COUNTIF(L39:AM39,"W/O") -> 3 | AP39: =COUNTIF(L39:AM39,"L") -> 7 | AQ39: =COUNTIF(L39:AM39,"HFL")/2 -> 0 | AR39: =COUNTIF(L39:AM39,"H") -> 0 | AS39: =COUNTIF(L39:AM39,"MG") -> 0 | AT39: =COUNTIF(L39:AM39,"ML") -> 0 | AU39: =COUNTIF(L39:AM39,"UL") -> 0 | AV39: =COUNTIF(L39:AM39,"MC") -> 0 | AW39: =COUNTIF(L39:AM39,"BL") -> 0 | AX39: =COUNTIF(L39:AM39,"MDL") -> 0 | AY39: =COUNTIF(L39:AM39,"LOP") -> 0 | AZ39: =SUM(AN39:AY39) -> 28 | BA39: =SUM(AP39:AQ39,AS39:AY39,AN39) -> 25 | BB39: =AZ39-(AU39+BO39) -> 26 | BC39: =AN39/BA39 -> 0.72 | BD39: =VLOOKUP(B39,'Jan''26- Leave Bal'!$B$3:$D$83,3,0) -> 0 | BE39: =VLOOKUP(B39,'Jan''26- Leave Bal'!$B$3:$E$83,4,0)+$BE$3 -> 0.5 | BF39: =VLOOKUP(B39,'Jan''26- Leave Bal'!$B$3:$F$83,5,0)+$BF$3 -> 1.5 | BG39: =VLOOKUP(B39,'Jan''26- Leave Bal'!$B$3:$G$83,6,0)+$BG$3 -> 3 | BH39: =VLOOKUP(B39,'Jan''26- Leave Bal'!$B$3:$H$83,7,0) -> 0 | BI39: =VLOOKUP(B39,'Jan''26- Leave Bal'!$B$3:$I$83,8,0)+$BI$3 -> 0.75 | BJ39: =IF((AP39+AQ39)<=BD39, (AP39+AQ39),BD39) -> 0 | BK39: =IF(((AP39+AQ39)-BJ39)>BE39,BE39,(AP39+AQ39)-BJ39) -> 0.5 | BL39: =IF((AP39+AQ39-BJ39-BK39)>=BF39,BF39,(AP39+AQ39-BJ39-BK39)) -> 1.5 | BM39: =IF((AP39+AQ39-BJ39-BK39-BL39)>=BG39,BG39,(AP39+AQ39-BJ39-BK39-BL39)) -> 3 | BN39: =AS39 -> 0 | BO39: =AP39+AQ39-BJ39-BK39-BL39-BM39 -> 2 | BP39: =BD39-BJ39 -> 0 | BQ39: =BE39-BK39 -> 0 | BR39: =BF39-BL39 -> 0 | BS39: =BG39-BM39 -> 0 | BT39: =BH39-BN39 -> 0 | BU39: =BI39 -> 0.75 | BW39: 0
A40: 37 | B40: JAI-1251 | D40: Retail | E40: Cartzy | F40: HQA | G40: Suvali | H40: 9014562381 | I40: kavya.gonela@jukshio.com | J40: 45159 | L40: P | M40: P | N40: P | O40: P | P40: P | Q40: P | R40: P | S40: W/O | T40: P | U40: P | V40: P | W40: P | X40: P | Y40: W/O | Z40: P | AA40: P | AB40: P | AC40: P | AD40: P | AE40: P | AF40: W/O | AG40: P | AH40: P | AI40: P | AJ40: P | AK40: P | AL40: W/O | AM40: L | AN40: =COUNTIF(L40:AM40,"P")+COUNTIF(L40:AM40,"HFL")/2 -> 23 | AO40: =COUNTIF(L40:AM40,"W/O") -> 4 | AP40: =COUNTIF(L40:AM40,"L") -> 1 | AQ40: =COUNTIF(L40:AM40,"HFL")/2 -> 0 | AR40: =COUNTIF(L40:AM40,"H") -> 0 | AS40: =COUNTIF(L40:AM40,"MG") -> 0 | AT40: =COUNTIF(L40:AM40,"ML") -> 0 | AU40: =COUNTIF(L40:AM40,"UL") -> 0 | AV40: =COUNTIF(L40:AM40,"MC") -> 0 | AW40: =COUNTIF(L40:AM40,"BL") -> 0 | AX40: =COUNTIF(L40:AM40,"MDL") -> 0 | AY40: =COUNTIF(L40:AM40,"LOP") -> 0 | AZ40: =SUM(AN40:AY40) -> 28 | BA40: =SUM(AP40:AQ40,AS40:AY40,AN40) -> 24 | BB40: =AZ40-(AU40+BO40) -> 28 | BC40: =AN40/BA40 -> 0.95833333 | BD40: =VLOOKUP(B40,'Jan''26- Leave Bal'!$B$3:$D$83,3,0) -> 2 | BE40: =VLOOKUP(B40,'Jan''26- Leave Bal'!$B$3:$E$83,4,0)+$BE$3 -> 5.5 | BF40: =VLOOKUP(B40,'Jan''26- Leave Bal'!$B$3:$F$83,5,0)+$BF$3 -> 5.5 | BG40: =VLOOKUP(B40,'Jan''26- Leave Bal'!$B$3:$G$83,6,0)+$BG$3 -> 13 | BH40: =VLOOKUP(B40,'Jan''26- Leave Bal'!$B$3:$H$83,7,0) -> 15 | BI40: =VLOOKUP(B40,'Jan''26- Leave Bal'!$B$3:$I$83,8,0)+$BI$3 -> 0.75 | BJ40: =IF((AP40+AQ40)<=BD40, (AP40+AQ40),BD40) -> 1 | BK40: =IF(((AP40+AQ40)-BJ40)>BE40,BE40,(AP40+AQ40)-BJ40) -> 0 | BL40: =IF((AP40+AQ40-BJ40-BK40)>=BF40,BF40,(AP40+AQ40-BJ40-BK40)) -> 0 | BM40: =IF((AP40+AQ40-BJ40-BK40-BL40)>=BG40,BG40,(AP40+AQ40-BJ40-BK40-BL40)) -> 0 | BN40: =AS40 -> 0 | BO40: =AP40+AQ40-BJ40-BK40-BL40-BM40 -> 0 | BP40: =BD40-BJ40 -> 1 | BQ40: =BE40-BK40 -> 5.5 | BR40: =BF40-BL40 -> 5.5 | BS40: =BG40-BM40 -> 13 | BT40: =BH40-BN40 -> 15 | BU40: =BI40 -> 0.75 | BV40: 01st Mar weekoff taken in Feb Last week itself | BW40: 01st feb Weekoff taken early in Jan'26
A41: 38 | B41: JAI-1259 | D41: Retail | E41: Cartzy | F41: Birdman | G41: Uppal | H41: 7794903282 | I41: mounika.khola@jukshio.com | J41: 45159 | L41: W/O | M41: P | N41: W/O | O41: P | P41: L | Q41: L | R41: L | S41: P | T41: L | U41: L | V41: P | W41: W/O | X41: P | Y41: P | Z41: P | AA41: W/O | AB41: L | AC41: P | AD41: P | AE41: P | AF41: P | AG41: P | AH41: P | AI41: P | AJ41: P | AK41: P | AL41: P | AM41: P | AN41: =COUNTIF(L41:AM41,"P")+COUNTIF(L41:AM41,"HFL")/2 -> 18 | AO41: =COUNTIF(L41:AM41,"W/O") -> 4 | AP41: =COUNTIF(L41:AM41,"L") -> 6 | AQ41: =COUNTIF(L41:AM41,"HFL")/2 -> 0 | AR41: =COUNTIF(L41:AM41,"H") -> 0 | AS41: =COUNTIF(L41:AM41,"MG") -> 0 | AT41: =COUNTIF(L41:AM41,"ML") -> 0 | AU41: =COUNTIF(L41:AM41,"UL") -> 0 | AV41: =COUNTIF(L41:AM41,"MC") -> 0 | AW41: =COUNTIF(L41:AM41,"BL") -> 0 | AX41: =COUNTIF(L41:AM41,"MDL") -> 0 | AY41: =COUNTIF(L41:AM41,"LOP") -> 0 | AZ41: =SUM(AN41:AY41) -> 28 | BA41: =SUM(AP41:AQ41,AS41:AY41,AN41) -> 24 | BB41: =AZ41-(AU41+BO41) -> 28 | BC41: =AN41/BA41 -> 0.75 | BD41: =VLOOKUP(B41,'Jan''26- Leave Bal'!$B$3:$D$83,3,0) -> 0 | BE41: =VLOOKUP(B41,'Jan''26- Leave Bal'!$B$3:$E$83,4,0)+$BE$3 -> 1 | BF41: =VLOOKUP(B41,'Jan''26- Leave Bal'!$B$3:$F$83,5,0)+$BF$3 -> 1 | BG41: =VLOOKUP(B41,'Jan''26- Leave Bal'!$B$3:$G$83,6,0)+$BG$3 -> 8 | BH41: =VLOOKUP(B41,'Jan''26- Leave Bal'!$B$3:$H$83,7,0) -> 15 | BI41: =VLOOKUP(B41,'Jan''26- Leave Bal'!$B$3:$I$83,8,0)+$BI$3 -> 0.75 | BJ41: =IF((AP41+AQ41)<=BD41, (AP41+AQ41),BD41) -> 0 | BK41: =IF(((AP41+AQ41)-BJ41)>BE41,BE41,(AP41+AQ41)-BJ41) -> 1 | BL41: =IF((AP41+AQ41-BJ41-BK41)>=BF41,BF41,(AP41+AQ41-BJ41-BK41)) -> 1 | BM41: =IF((AP41+AQ41-BJ41-BK41-BL41)>=BG41,BG41,(AP41+AQ41-BJ41-BK41-BL41)) -> 4 | BN41: =AS41 -> 0 | BO41: =AP41+AQ41-BJ41-BK41-BL41-BM41 -> 0 | BP41: =BD41-BJ41 -> 0 | BQ41: =BE41-BK41 -> 0 | BR41: =BF41-BL41 -> 0 | BS41: =BG41-BM41 -> 4 | BT41: =BH41-BN41 -> 15 | BU41: =BI41 -> 0.75 | BW41: 0
A42: 39 | B42: JAI-1226 | D42: Retail | E42: Cartzy | F42: Birdman | G42: Uppal | H42: 8367714643 | I42: hemalatha.chilumula@jukshio.com | J42: 45139 | L42: P | M42: P | N42: P | O42: P | P42: P | Q42: P | R42: P | S42: W/O | T42: P | U42: P | V42: P | W42: P | X42: P | Y42: P | Z42: W/O | AA42: P | AB42: P | AC42: P | AD42: P | AE42: P | AF42: P | AG42: W/O | AH42: L | AI42: P | AJ42: P | AK42: P | AL42: P | AM42: W/O | AN42: =COUNTIF(L42:AM42,"P")+COUNTIF(L42:AM42,"HFL")/2 -> 23 | AO42: =COUNTIF(L42:AM42,"W/O") -> 4 | AP42: =COUNTIF(L42:AM42,"L") -> 1 | AQ42: =COUNTIF(N42:AM42,"HFL")/2 -> 0 | AR42: =COUNTIF(L42:AM42,"H") -> 0 | AS42: =COUNTIF(N42:AM42,"MG") -> 0 | AT42: =COUNTIF(N42:AM42,"ML") -> 0 | AU42: =COUNTIF(N42:AM42,"UL") -> 0 | AV42: =COUNTIF(N42:AM42,"MC") -> 0 | AW42: =COUNTIF(N42:AM42,"BL") -> 0 | AX42: =COUNTIF(N42:AM42,"MDL") -> 0 | AY42: =COUNTIF(N42:AM42,"LOP") -> 0 | AZ42: =SUM(AN42:AY42) -> 28 | BA42: =SUM(AP42:AQ42,AS42:AY42,AN42) -> 24 | BB42: =AZ42-(AU42+BO42) -> 28 | BC42: =AN42/BA42 -> 0.95833333 | BD42: =VLOOKUP(B42,'Jan''26- Leave Bal'!$B$3:$D$83,3,0) -> 0 | BE42: =VLOOKUP(B42,'Jan''26- Leave Bal'!$B$3:$E$83,4,0)+$BE$3 -> 0.5 | BF42: =VLOOKUP(B42,'Jan''26- Leave Bal'!$B$3:$F$83,5,0)+$BF$3 -> 0.5 | BG42: =VLOOKUP(B42,'Jan''26- Leave Bal'!$B$3:$G$83,6,0)+$BG$3 -> 1 | BH42: =VLOOKUP(B42,'Jan''26- Leave Bal'!$B$3:$H$83,7,0) -> 15 | BI42: =VLOOKUP(B42,'Jan''26- Leave Bal'!$B$3:$I$83,8,0)+$BI$3 -> 0.75 | BJ42: =IF((AP42+AQ42)<=BD42, (AP42+AQ42),BD42) -> 0 | BK42: =IF(((AP42+AQ42)-BJ42)>BE42,BE42,(AP42+AQ42)-BJ42) -> 0.5 | BL42: =IF((AP42+AQ42-BJ42-BK42)>=BF42,BF42,(AP42+AQ42-BJ42-BK42)) -> 0.5 | BM42: =IF((AP42+AQ42-BJ42-BK42-BL42)>=BG42,BG42,(AP42+AQ42-BJ42-BK42-BL42)) -> 0 | BN42: =AS42 -> 0 | BO42: =AP42+AQ42-BJ42-BK42-BL42-BM42 -> 0 | BP42: =BD42-BJ42 -> 0 | BQ42: =BE42-BK42 -> 0 | BR42: =BF42-BL42 -> 0 | BS42: =BG42-BM42 -> 1 | BT42: =BH42-BN42 -> 15 | BU42: =BI42 -> 0.75 | BV42: 01st Mar weekoff taken in Feb Last week itself | BW42: 01st feb Weekoff taken early in Jan'26
A43: 40 | B43: JAI-486 | D43: Retail | E43: Cartzy | F43: Birdman | G43: Uppal | H43: 7093672179 | I43: sandhya.katkam@jukshio.com | J43: 44845 | L43: P | M43: P | N43: P | O43: P | P43: P | Q43: P | R43: W/O | S43: P | T43: P | U43: P | V43: P | W43: W/O | X43: P | Y43: P | Z43: P | AA43: P | AB43: P | AC43: P | AD43: P | AE43: P | AF43: P | AG43: W/O | AH43: P | AI43: P | AJ43: P | AK43: W/O | AL43: L | AM43: P | AN43: =COUNTIF(L43:AM43,"P")+COUNTIF(L43:AM43,"HFL")/2 -> 23 | AO43: =COUNTIF(L43:AM43,"W/O") -> 4 | AP43: =COUNTIF(L43:AM43,"L") -> 1 | AQ43: =COUNTIF(L43:AM43,"HFL")/2 -> 0 | AR43: =COUNTIF(L43:AM43,"H") -> 0 | AS43: =COUNTIF(L43:AM43,"MG") -> 0 | AT43: =COUNTIF(L43:AM43,"ML") -> 0 | AU43: =COUNTIF(L43:AM43,"UL") -> 0 | AV43: =COUNTIF(L43:AM43,"MC") -> 0 | AW43: =COUNTIF(L43:AM43,"BL") -> 0 | AX43: =COUNTIF(L43:AM43,"MDL") -> 0 | AY43: =COUNTIF(L43:AM43,"LOP") -> 0 | AZ43: =SUM(AN43:AY43) -> 28 | BA43: =SUM(AP43:AQ43,AS43:AY43,AN43) -> 24 | BB43: =AZ43-(AU43+BO43) -> 28 | BC43: =AN43/BA43 -> 0.95833333 | BD43: =VLOOKUP(B43,'Jan''26- Leave Bal'!$B$3:$D$83,3,0) -> 0 | BE43: =VLOOKUP(B43,'Jan''26- Leave Bal'!$B$3:$E$83,4,0)+$BE$3 -> 0.5 | BF43: =VLOOKUP(B43,'Jan''26- Leave Bal'!$B$3:$F$83,5,0)+$BF$3 -> 0.5 | BG43: =VLOOKUP(B43,'Jan''26- Leave Bal'!$B$3:$G$83,6,0)+$BG$3 -> 6.5 | BH43: =VLOOKUP(B43,'Jan''26- Leave Bal'!$B$3:$H$83,7,0) -> 15 | BI43: =VLOOKUP(B43,'Jan''26- Leave Bal'!$B$3:$I$83,8,0)+$BI$3 -> 0.75 | BJ43: =IF((AP43+AQ43)<=BD43, (AP43+AQ43),BD43) -> 0 | BK43: =IF(((AP43+AQ43)-BJ43)>BE43,BE43,(AP43+AQ43)-BJ43) -> 0.5 | BL43: =IF((AP43+AQ43-BJ43-BK43)>=BF43,BF43,(AP43+AQ43-BJ43-BK43)) -> 0.5 | BM43: =IF((AP43+AQ43-BJ43-BK43-BL43)>=BG43,BG43,(AP43+AQ43-BJ43-BK43-BL43)) -> 0 | BN43: =AS43 -> 0 | BO43: =AP43+AQ43-BJ43-BK43-BL43-BM43 -> 0 | BP43: =BD43-BJ43 -> 0 | BQ43: =BE43-BK43 -> 0 | BR43: =BF43-BL43 -> 0 | BS43: =BG43-BM43 -> 6.5 | BT43: =BH43-BN43 -> 15 | BU43: =BI43 -> 0.75 | BV43: 01st Mar weekoff taken in Feb Last week itself | BW43: 01st feb Weekoff taken early in Jan'26
A44: 41 | B44: JAI-906 | D44: Retail | E44: Cartzy | F44: Aisle curation | G44: Uppal | H44: 9398134097 | I44: akhila.maya@jukshio.com | J44: 45033 | L44: W/O | M44: P | N44: P | O44: P | P44: P | Q44: P | R44: P | S44: W/O | T44: P | U44: W/O | V44: P | W44: P | X44: P | Y44: P | Z44: P | AA44: HFL | AB44: P | AC44: P | AD44: P | AE44: P | AF44: P | AG44: W/O | AH44: P | AI44: P | AJ44: P | AK44: P | AL44: P | AM44: P | AN44: =COUNTIF(L44:AM44,"P")+COUNTIF(L44:AM44,"HFL")/2 -> 23.5 | AO44: =COUNTIF(L44:AM44,"W/O") -> 4 | AP44: =COUNTIF(L44:AM44,"L") -> 0 | AQ44: =COUNTIF(L44:AM44,"HFL")/2 -> 0.5 | AR44: =COUNTIF(L44:AM44,"H") -> 0 | AS44: =COUNTIF(L44:AM44,"MG") -> 0 | AT44: =COUNTIF(L44:AM44,"ML") -> 0 | AU44: =COUNTIF(L44:AM44,"UL") -> 0 | AV44: =COUNTIF(L44:AM44,"MC") -> 0 | AW44: =COUNTIF(L44:AM44,"BL") -> 0 | AX44: =COUNTIF(L44:AM44,"MDL") -> 0 | AY44: =COUNTIF(L44:AM44,"LOP") -> 0 | AZ44: =SUM(AN44:AY44) -> 28 | BA44: =SUM(AP44:AQ44,AS44:AY44,AN44) -> 24 | BB44: =AZ44-(AU44+BO44) -> 28 | BC44: =AN44/BA44 -> 0.97916667 | BD44: =VLOOKUP(B44,'Jan''26- Leave Bal'!$B$3:$D$83,3,0) -> 0 | BE44: =VLOOKUP(B44,'Jan''26- Leave Bal'!$B$3:$E$83,4,0)+$BE$3 -> 0.5 | BF44: =VLOOKUP(B44,'Jan''26- Leave Bal'!$B$3:$F$83,5,0)+$BF$3 -> 2.5 | BG44: =VLOOKUP(B44,'Jan''26- Leave Bal'!$B$3:$G$83,6,0)+$BG$3 -> 13 | BH44: =VLOOKUP(B44,'Jan''26- Leave Bal'!$B$3:$H$83,7,0) -> 15 | BI44: =VLOOKUP(B44,'Jan''26- Leave Bal'!$B$3:$I$83,8,0)+$BI$3 -> 0.75 | BJ44: =IF((AP44+AQ44)<=BD44, (AP44+AQ44),BD44) -> 0 | BK44: =IF(((AP44+AQ44)-BJ44)>BE44,BE44,(AP44+AQ44)-BJ44) -> 0.5 | BL44: =IF((AP44+AQ44-BJ44-BK44)>=BF44,BF44,(AP44+AQ44-BJ44-BK44)) -> 0 | BM44: =IF((AP44+AQ44-BJ44-BK44-BL44)>=BG44,BG44,(AP44+AQ44-BJ44-BK44-BL44)) -> 0 | BN44: =AS44 -> 0 | BO44: =AP44+AQ44-BJ44-BK44-BL44-BM44 -> 0 | BP44: =BD44-BJ44 -> 0 | BQ44: =BE44-BK44 -> 0 | BR44: =BF44-BL44 -> 2.5 | BS44: =BG44-BM44 -> 13 | BT44: =BH44-BN44 -> 15 | BU44: =BI44 -> 0.75 | BW44: 0
A45: 42 | B45: JAI-469 | D45: Retail | E45: Cartzy | F45: Birdman | G45: Uppal | H45: 8978001708 | I45: divya.akula@jukshio.com | J45: 44845 | L45: L | M45: P | N45: W/O | O45: P | P45: P | Q45: P | R45: P | S45: P | T45: P | U45: P | V45: P | W45: P | X45: W/O | Y45: P | Z45: P | AA45: P | AB45: W/O | AC45: P | AD45: P | AE45: P | AF45: P | AG45: L | AH45: P | AI45: P | AJ45: P | AK45: P | AL45: P | AM45: W/O | AN45: =COUNTIF(L45:AM45,"P")+COUNTIF(L45:AM45,"HFL")/2 -> 22 | AO45: =COUNTIF(L45:AM45,"W/O") -> 4 | AP45: =COUNTIF(L45:AM45,"L") -> 2 | AQ45: =COUNTIF(L45:AM45,"HFL")/2 -> 0 | AR45: =COUNTIF(L45:AM45,"H") -> 0 | AS45: =COUNTIF(L45:AM45,"MG") -> 0 | AT45: =COUNTIF(L45:AM45,"ML") -> 0 | AU45: =COUNTIF(L45:AM45,"UL") -> 0 | AV45: =COUNTIF(L45:AM45,"MC") -> 0 | AW45: =COUNTIF(L45:AM45,"BL") -> 0 | AX45: =COUNTIF(L45:AM45,"MDL") -> 0 | AY45: =COUNTIF(L45:AM45,"LOP") -> 0 | AZ45: =SUM(AN45:AY45) -> 28 | BA45: =SUM(AP45:AQ45,AS45:AY45,AN45) -> 24 | BB45: =AZ45-(AU45+BO45) -> 28 | BC45: =AN45/BA45 -> 0.91666667 | BD45: =VLOOKUP(B45,'Jan''26- Leave Bal'!$B$3:$D$83,3,0) -> 0 | BE45: =VLOOKUP(B45,'Jan''26- Leave Bal'!$B$3:$E$83,4,0)+$BE$3 -> 0.5 | BF45: =VLOOKUP(B45,'Jan''26- Leave Bal'!$B$3:$F$83,5,0)+$BF$3 -> 0.5 | BG45: =VLOOKUP(B45,'Jan''26- Leave Bal'!$B$3:$G$83,6,0)+$BG$3 -> 4 | BH45: =VLOOKUP(B45,'Jan''26- Leave Bal'!$B$3:$H$83,7,0) -> 15 | BI45: =VLOOKUP(B45,'Jan''26- Leave Bal'!$B$3:$I$83,8,0)+$BI$3 -> 0.75 | BJ45: =IF((AP45+AQ45)<=BD45, (AP45+AQ45),BD45) -> 0 | BK45: =IF(((AP45+AQ45)-BJ45)>BE45,BE45,(AP45+AQ45)-BJ45) -> 0.5 | BL45: =IF((AP45+AQ45-BJ45-BK45)>=BF45,BF45,(AP45+AQ45-BJ45-BK45)) -> 0.5 | BM45: =IF((AP45+AQ45-BJ45-BK45-BL45)>=BG45,BG45,(AP45+AQ45-BJ45-BK45-BL45)) -> 1 | BN45: =AS45 -> 0 | BO45: =AP45+AQ45-BJ45-BK45-BL45-BM45 -> 0 | BP45: =BD45-BJ45 -> 0 | BQ45: =BE45-BK45 -> 0 | BR45: =BF45-BL45 -> 0 | BS45: =BG45-BM45 -> 3 | BT45: =BH45-BN45 -> 15 | BU45: =BI45 -> 0.75 | BV45: 01st Mar weekoff taken in Feb Last week itself | BW45: 01st feb Weekoff taken early in Jan'26
A46: 43 | B46: JAI-464 | D46: Retail | E46: Cartzy | F46: Birdman | G46: Uppal | H46: 7801044213 | I46: anusha.yenugula@jukshio.com | J46: 44845 | L46: P | M46: P | N46: P | O46: P | P46: W/O | Q46: P | R46: P | S46: P | T46: P | U46: P | V46: P | W46: W/O | X46: L | Y46: P | Z46: P | AA46: W/O | AB46: P | AC46: P | AD46: P | AE46: L | AF46: L | AG46: L | AH46: L | AI46: W/O | AJ46: L | AK46: HFL | AL46: P | AM46: P | AN46: =COUNTIF(L46:AM46,"P")+COUNTIF(L46:AM46,"HFL")/2 -> 17.5 | AO46: =COUNTIF(L46:AM46,"W/O") -> 4 | AP46: =COUNTIF(L46:AM46,"L") -> 6 | AQ46: =COUNTIF(L46:AM46,"HFL")/2 -> 0.5 | AR46: =COUNTIF(L46:AM46,"H") -> 0 | AS46: =COUNTIF(L46:AM46,"MG") -> 0 | AT46: =COUNTIF(L46:AM46,"ML") -> 0 | AU46: =COUNTIF(L46:AM46,"UL") -> 0 | AV46: =COUNTIF(L46:AM46,"MC") -> 0 | AW46: =COUNTIF(L46:AM46,"BL") -> 0 | AX46: =COUNTIF(L46:AM46,"MDL") -> 0 | AY46: =COUNTIF(L46:AM46,"LOP") -> 0 | AZ46: =SUM(AN46:AY46) -> 28 | BA46: =SUM(AP46:AQ46,AS46:AY46,AN46) -> 24 | BB46: =AZ46-(AU46+BO46) -> 25.5 | BC46: =AN46/BA46 -> 0.72916667 | BD46: =VLOOKUP(B46,'Jan''26- Leave Bal'!$B$3:$D$83,3,0) -> 0 | BE46: =VLOOKUP(B46,'Jan''26- Leave Bal'!$B$3:$E$83,4,0)+$BE$3 -> 0.5 | BF46: =VLOOKUP(B46,'Jan''26- Leave Bal'!$B$3:$F$83,5,0)+$BF$3 -> 0.5 | BG46: =VLOOKUP(B46,'Jan''26- Leave Bal'!$B$3:$G$83,6,0)+$BG$3 -> 3 | BH46: =VLOOKUP(B46,'Jan''26- Leave Bal'!$B$3:$H$83,7,0) -> 15 | BI46: =VLOOKUP(B46,'Jan''26- Leave Bal'!$B$3:$I$83,8,0)+$BI$3 -> 0.75 | BJ46: =IF((AP46+AQ46)<=BD46, (AP46+AQ46),BD46) -> 0 | BK46: =IF(((AP46+AQ46)-BJ46)>BE46,BE46,(AP46+AQ46)-BJ46) -> 0.5 | BL46: =IF((AP46+AQ46-BJ46-BK46)>=BF46,BF46,(AP46+AQ46-BJ46-BK46)) -> 0.5 | BM46: =IF((AP46+AQ46-BJ46-BK46-BL46)>=BG46,BG46,(AP46+AQ46-BJ46-BK46-BL46)) -> 3 | BN46: =AS46 -> 0 | BO46: =AP46+AQ46-BJ46-BK46-BL46-BM46 -> 2.5 | BP46: =BD46-BJ46 -> 0 | BQ46: =BE46-BK46 -> 0 | BR46: =BF46-BL46 -> 0 | BS46: =BG46-BM46 -> 0 | BT46: =BH46-BN46 -> 15 | BU46: =BI46 -> 0.75 | BV46: 01st Mar weekoff taken in Feb Last week itself | BW46: 01st feb Weekoff taken early in Jan'26
A47: 44 | B47: JAI-1316 | D47: Retail | E47: Cartzy | F47: Birdman | G47: Uppal | H47: 7396558650 | I47: jangili.lavanya@jukshio.com | J47: 45217 | L47: P | M47: W/O | N47: P | O47: P | P47: P | Q47: P | R47: P | S47: P | T47: P | U47: W/O | V47: P | W47: P | X47: L | Y47: L | Z47: L | AA47: P | AB47: W/O | AC47: L | AD47: P | AE47: P | AF47: P | AG47: P | AH47: P | AI47: P | AJ47: P | AK47: P | AL47: W/O | AM47: P | AN47: =COUNTIF(L47:AM47,"P")+COUNTIF(L47:AM47,"HFL")/2 -> 20 | AO47: =COUNTIF(L47:AM47,"W/O") -> 4 | AP47: =COUNTIF(L47:AM47,"L") -> 4 | AQ47: =COUNTIF(L47:AM47,"HFL")/2 -> 0 | AR47: =COUNTIF(L47:AM47,"H") -> 0 | AS47: =COUNTIF(L47:AM47,"MG") -> 0 | AT47: =COUNTIF(L47:AM47,"ML") -> 0 | AU47: =COUNTIF(L47:AM47,"UL") -> 0 | AV47: =COUNTIF(L47:AM47,"MC") -> 0 | AW47: =COUNTIF(L47:AM47,"BL") -> 0 | AX47: =COUNTIF(L47:AM47,"MDL") -> 0 | AY47: =COUNTIF(L47:AM47,"LOP") -> 0 | AZ47: =SUM(AN47:AY47) -> 28 | BA47: =SUM(AP47:AQ47,AS47:AY47,AN47) -> 24 | BB47: =AZ47-(AU47+BO47) -> 28 | BC47: =AN47/BA47 -> 0.83333333 | BD47: =VLOOKUP(B47,'Jan''26- Leave Bal'!$B$3:$D$83,3,0) -> 0 | BE47: =VLOOKUP(B47,'Jan''26- Leave Bal'!$B$3:$E$83,4,0)+$BE$3 -> 0.5 | BF47: =VLOOKUP(B47,'Jan''26- Leave Bal'!$B$3:$F$83,5,0)+$BF$3 -> 0.5 | BG47: =VLOOKUP(B47,'Jan''26- Leave Bal'!$B$3:$G$83,6,0)+$BG$3 -> 6 | BH47: =VLOOKUP(B47,'Jan''26- Leave Bal'!$B$3:$H$83,7,0) -> 15 | BI47: =VLOOKUP(B47,'Jan''26- Leave Bal'!$B$3:$I$83,8,0)+$BI$3 -> 0.75 | BJ47: =IF((AP47+AQ47)<=BD47, (AP47+AQ47),BD47) -> 0 | BK47: =IF(((AP47+AQ47)-BJ47)>BE47,BE47,(AP47+AQ47)-BJ47) -> 0.5 | BL47: =IF((AP47+AQ47-BJ47-BK47)>=BF47,BF47,(AP47+AQ47-BJ47-BK47)) -> 0.5 | BM47: =IF((AP47+AQ47-BJ47-BK47-BL47)>=BG47,BG47,(AP47+AQ47-BJ47-BK47-BL47)) -> 3 | BN47: =AS47 -> 0 | BO47: =AP47+AQ47-BJ47-BK47-BL47-BM47 -> 0 | BP47: =BD47-BJ47 -> 0 | BQ47: =BE47-BK47 -> 0 | BR47: =BF47-BL47 -> 0 | BS47: =BG47-BM47 -> 3 | BT47: =BH47-BN47 -> 15 | BU47: =BI47 -> 0.75 | BW47: 0
A48: 45 | B48: JAI-317 | D48: Retail | E48: Cartzy | F48: Birdman | G48: Suvali | H48: 9390755670 | I48: maneesha.repaka@jukshio.com | J48: 44426 | L48: P | M48: P | N48: P | O48: P | P48: P | Q48: P | R48: P | S48: W/O | T48: P | U48: P | V48: P | W48: P | X48: W/O | Y48: P | Z48: P | AA48: W/O | AB48: P | AC48: P | AD48: P | AE48: P | AF48: P | AG48: P | AH48: P | AI48: P | AJ48: P | AK48: P | AL48: P | AM48: W/O | AN48: =COUNTIF(L48:AM48,"P")+COUNTIF(L48:AM48,"HFL")/2 -> 24 | AO48: =COUNTIF(L48:AM48,"W/O") -> 4 | AP48: =COUNTIF(L48:AM48,"L") -> 0 | AQ48: =COUNTIF(L48:AM48,"HFL")/2 -> 0 | AR48: =COUNTIF(L48:AM48,"H") -> 0 | AS48: =COUNTIF(L48:AM48,"MG") -> 0 | AT48: =COUNTIF(L48:AM48,"ML") -> 0 | AU48: =COUNTIF(L48:AM48,"UL") -> 0 | AV48: =COUNTIF(L48:AM48,"MC") -> 0 | AW48: =COUNTIF(L48:AM48,"BL") -> 0 | AX48: =COUNTIF(L48:AM48,"MDL") -> 0 | AY48: =COUNTIF(L48:AM48,"LOP") -> 0 | AZ48: =SUM(AN48:AY48) -> 28 | BA48: =SUM(AP48:AQ48,AS48:AY48,AN48) -> 24 | BB48: =AZ48-(AU48+BO48) -> 28 | BC48: =AN48/BA48 -> 1 | BD48: =VLOOKUP(B48,'Jan''26- Leave Bal'!$B$3:$D$83,3,0) -> 0 | BE48: =VLOOKUP(B48,'Jan''26- Leave Bal'!$B$3:$E$83,4,0)+$BE$3 -> 1 | BF48: =VLOOKUP(B48,'Jan''26- Leave Bal'!$B$3:$F$83,5,0)+$BF$3 -> 1 | BG48: =VLOOKUP(B48,'Jan''26- Leave Bal'!$B$3:$G$83,6,0)+$BG$3 -> 11.5 | BH48: =VLOOKUP(B48,'Jan''26- Leave Bal'!$B$3:$H$83,7,0) -> 15 | BI48: =VLOOKUP(B48,'Jan''26- Leave Bal'!$B$3:$I$83,8,0)+$BI$3 -> 0.75 | BJ48: =IF((AP48+AQ48)<=BD48, (AP48+AQ48),BD48) -> 0 | BK48: =IF(((AP48+AQ48)-BJ48)>BE48,BE48,(AP48+AQ48)-BJ48) -> 0 | BL48: =IF((AP48+AQ48-BJ48-BK48)>=BF48,BF48,(AP48+AQ48-BJ48-BK48)) -> 0 | BM48: =IF((AP48+AQ48-BJ48-BK48-BL48)>=BG48,BG48,(AP48+AQ48-BJ48-BK48-BL48)) -> 0 | BN48: =AS48 -> 0 | BO48: =AP48+AQ48-BJ48-BK48-BL48-BM48 -> 0 | BP48: =BD48-BJ48 -> 0 | BQ48: =BE48-BK48 -> 1 | BR48: =BF48-BL48 -> 1 | BS48: =BG48-BM48 -> 11.5 | BT48: =BH48-BN48 -> 15 | BU48: =BI48 -> 0.75 | BV48: 01st Mar weekoff taken in Feb Last week itself | BW48: 01st feb Weekoff taken early in Jan'26
A49: 46 | B49: JAI-308 | D49: Retail | E49: Cartzy | F49: Birdman | G49: Suvali | H49: 93983 20542 | I49: geetha.bugga@jukshio.com | J49: 44426 | L49: W/O | M49: P | N49: P | O49: P | P49: P | Q49: P | R49: P | S49: W/O | T49: P | U49: P | V49: P | W49: P | X49: W/O | Y49: P | Z49: P | AA49: L | AB49: P | AC49: P | AD49: P | AE49: W/O | AF49: P | AG49: P | AH49: P | AI49: P | AJ49: P | AK49: W/O | AL49: P | AM49: P | AN49: =COUNTIF(L49:AM49,"P")+COUNTIF(L49:AM49,"HFL")/2 -> 22 | AO49: =COUNTIF(L49:AM49,"W/O") -> 5 | AP49: =COUNTIF(L49:AM49,"L") -> 1 | AQ49: =COUNTIF(L49:AM49,"HFL")/2 -> 0 | AR49: =COUNTIF(L49:AM49,"H") -> 0 | AS49: =COUNTIF(L49:AM49,"MG") -> 0 | AT49: =COUNTIF(L49:AM49,"ML") -> 0 | AU49: =COUNTIF(L49:AM49,"UL") -> 0 | AV49: =COUNTIF(L49:AM49,"MC") -> 0 | AW49: =COUNTIF(L49:AM49,"BL") -> 0 | AX49: =COUNTIF(L49:AM49,"MDL") -> 0 | AY49: =COUNTIF(L49:AM49,"LOP") -> 0 | AZ49: =SUM(AN49:AY49) -> 28 | BA49: =SUM(AP49:AQ49,AS49:AY49,AN49) -> 23 | BB49: =AZ49-(AU49+BO49) -> 28 | BC49: =AN49/BA49 -> 0.95652174 | BD49: =VLOOKUP(B49,'Jan''26- Leave Bal'!$B$3:$D$83,3,0) -> 0 | BE49: =VLOOKUP(B49,'Jan''26- Leave Bal'!$B$3:$E$83,4,0)+$BE$3 -> 0.5 | BF49: =VLOOKUP(B49,'Jan''26- Leave Bal'!$B$3:$F$83,5,0)+$BF$3 -> 1 | BG49: =VLOOKUP(B49,'Jan''26- Leave Bal'!$B$3:$G$83,6,0)+$BG$3 -> 11.5 | BH49: =VLOOKUP(B49,'Jan''26- Leave Bal'!$B$3:$H$83,7,0) -> 15 | BI49: =VLOOKUP(B49,'Jan''26- Leave Bal'!$B$3:$I$83,8,0)+$BI$3 -> 0.75 | BJ49: =IF((AP49+AQ49)<=BD49, (AP49+AQ49),BD49) -> 0 | BK49: =IF(((AP49+AQ49)-BJ49)>BE49,BE49,(AP49+AQ49)-BJ49) -> 0.5 | BL49: =IF((AP49+AQ49-BJ49-BK49)>=BF49,BF49,(AP49+AQ49-BJ49-BK49)) -> 0.5 | BM49: =IF((AP49+AQ49-BJ49-BK49-BL49)>=BG49,BG49,(AP49+AQ49-BJ49-BK49-BL49)) -> 0 | BN49: =AS49 -> 0 | BO49: =AP49+AQ49-BJ49-BK49-BL49-BM49 -> 0 | BP49: =BD49-BJ49 -> 0 | BQ49: =BE49-BK49 -> 0 | BR49: =BF49-BL49 -> 0.5 | BS49: =BG49-BM49 -> 11.5 | BT49: =BH49-BN49 -> 15 | BU49: =BI49 -> 0.75 | BV49: 01st Mar weekoff taken in Feb Last week itself | BW49: 0
A50: 47 | B50: JAI-471 | D50: Retail | E50: Cartzy | F50: Birdman | G50: Suvali | H50: 9381479466 | I50: harika.akula@jukshio.com | J50: 44845 | L50: P | M50: P | N50: P | O50: P | P50: P | Q50: P | R50: W/O | S50: L | T50: P | U50: P | V50: W/O | W50: P | X50: P | Y50: P | Z50: P | AA50: P | AB50: P | AC50: P | AD50: L | AE50: W/O | AF50: P | AG50: P | AH50: P | AI50: L | AJ50: P | AK50: P | AL50: W/O | AM50: P | AN50: =COUNTIF(L50:AM50,"P")+COUNTIF(L50:AM50,"HFL")/2 -> 21 | AO50: =COUNTIF(L50:AM50,"W/O") -> 4 | AP50: =COUNTIF(L50:AM50,"L") -> 3 | AQ50: =COUNTIF(L50:AM50,"HFL")/2 -> 0 | AR50: =COUNTIF(L50:AM50,"H") -> 0 | AS50: =COUNTIF(L50:AM50,"MG") -> 0 | AT50: =COUNTIF(L50:AM50,"ML") -> 0 | AU50: =COUNTIF(L50:AM50,"UL") -> 0 | AV50: =COUNTIF(L50:AM50,"MC") -> 0 | AW50: =COUNTIF(L50:AM50,"BL") -> 0 | AX50: =COUNTIF(L50:AM50,"MDL") -> 0 | AY50: =COUNTIF(L50:AM50,"LOP") -> 0 | AZ50: =SUM(AN50:AY50) -> 28 | BA50: =SUM(AP50:AQ50,AS50:AY50,AN50) -> 24 | BB50: =AZ50-(AU50+BO50) -> 28 | BC50: =AN50/BA50 -> 0.875 | BD50: =VLOOKUP(B50,'Jan''26- Leave Bal'!$B$3:$D$83,3,0) -> 0 | BE50: =VLOOKUP(B50,'Jan''26- Leave Bal'!$B$3:$E$83,4,0)+$BE$3 -> 0.5 | BF50: =VLOOKUP(B50,'Jan''26- Leave Bal'!$B$3:$F$83,5,0)+$BF$3 -> 0.5 | BG50: =VLOOKUP(B50,'Jan''26- Leave Bal'!$B$3:$G$83,6,0)+$BG$3 -> 9.5 | BH50: =VLOOKUP(B50,'Jan''26- Leave Bal'!$B$3:$H$83,7,0) -> 15 | BI50: =VLOOKUP(B50,'Jan''26- Leave Bal'!$B$3:$I$83,8,0)+$BI$3 -> 0.75 | BJ50: =IF((AP50+AQ50)<=BD50, (AP50+AQ50),BD50) -> 0 | BK50: =IF(((AP50+AQ50)-BJ50)>BE50,BE50,(AP50+AQ50)-BJ50) -> 0.5 | BL50: =IF((AP50+AQ50-BJ50-BK50)>=BF50,BF50,(AP50+AQ50-BJ50-BK50)) -> 0.5 | BM50: =IF((AP50+AQ50-BJ50-BK50-BL50)>=BG50,BG50,(AP50+AQ50-BJ50-BK50-BL50)) -> 2 | BN50: =AS50 -> 0 | BO50: =AP50+AQ50-BJ50-BK50-BL50-BM50 -> 0 | BP50: =BD50-BJ50 -> 0 | BQ50: =BE50-BK50 -> 0 | BR50: =BF50-BL50 -> 0 | BS50: =BG50-BM50 -> 7.5 | BT50: =BH50-BN50 -> 15 | BU50: =BI50 -> 0.75 | BV50: 01st Mar weekoff taken in Feb Last week itself | BW50: 01st feb Weekoff taken early in Jan'26
A51: 48 | B51: JAI-891 | D51: Retail | E51: Cartzy | F51: Birdman | G51: Suvali | H51: 6305996910 | I51: swetha.pasunoori@jukshio.com | J51: 45033 | L51: P | M51: P | N51: W/O | O51: P | P51: P | Q51: P | R51: P | S51: L | T51: P | U51: P | V51: P | W51: P | X51: P | Y51: W/O | Z51: P | AA51: P | AB51: P | AC51: P | AD51: W/O | AE51: P | AF51: P | AG51: P | AH51: P | AI51: P | AJ51: P | AK51: P | AL51: P | AM51: W/O | AN51: =COUNTIF(L51:AM51,"P")+COUNTIF(L51:AM51,"HFL")/2 -> 23 | AO51: =COUNTIF(L51:AM51,"W/O") -> 4 | AP51: =COUNTIF(L51:AM51,"L") -> 1 | AQ51: =COUNTIF(L51:AM51,"HFL")/2 -> 0 | AR51: =COUNTIF(L51:AM51,"H") -> 0 | AS51: =COUNTIF(L51:AM51,"MG") -> 0 | AT51: =COUNTIF(L51:AM51,"ML") -> 0 | AU51: =COUNTIF(L51:AM51,"UL") -> 0 | AV51: =COUNTIF(L51:AM51,"MC") -> 0 | AW51: =COUNTIF(L51:AM51,"BL") -> 0 | AX51: =COUNTIF(L51:AM51,"MDL") -> 0 | AY51: =COUNTIF(L51:AM51,"LOP") -> 0 | AZ51: =SUM(AN51:AY51) -> 28 | BA51: =SUM(AP51:AQ51,AS51:AY51,AN51) -> 24 | BB51: =AZ51-(AU51+BO51) -> 28 | BC51: =AN51/BA51 -> 0.95833333 | BD51: =VLOOKUP(B51,'Jan''26- Leave Bal'!$B$3:$D$83,3,0) -> 0 | BE51: =VLOOKUP(B51,'Jan''26- Leave Bal'!$B$3:$E$83,4,0)+$BE$3 -> 0.5 | BF51: =VLOOKUP(B51,'Jan''26- Leave Bal'!$B$3:$F$83,5,0)+$BF$3 -> 0.5 | BG51: =VLOOKUP(B51,'Jan''26- Leave Bal'!$B$3:$G$83,6,0)+$BG$3 -> 7 | BH51: =VLOOKUP(B51,'Jan''26- Leave Bal'!$B$3:$H$83,7,0) -> 15 | BI51: =VLOOKUP(B51,'Jan''26- Leave Bal'!$B$3:$I$83,8,0)+$BI$3 -> 0.75 | BJ51: =IF((AP51+AQ51)<=BD51, (AP51+AQ51),BD51) -> 0 | BK51: =IF(((AP51+AQ51)-BJ51)>BE51,BE51,(AP51+AQ51)-BJ51) -> 0.5 | BL51: =IF((AP51+AQ51-BJ51-BK51)>=BF51,BF51,(AP51+AQ51-BJ51-BK51)) -> 0.5 | BM51: =IF((AP51+AQ51-BJ51-BK51-BL51)>=BG51,BG51,(AP51+AQ51-BJ51-BK51-BL51)) -> 0 | BN51: =AS51 -> 0 | BO51: =AP51+AQ51-BJ51-BK51-BL51-BM51 -> 0 | BP51: =BD51-BJ51 -> 0 | BQ51: =BE51-BK51 -> 0 | BR51: =BF51-BL51 -> 0 | BS51: =BG51-BM51 -> 7 | BT51: =BH51-BN51 -> 15 | BU51: =BI51 -> 0.75 | BW51: 0
A52: 49 | B52: JAI-306 | D52: Retail | E52: Cartzy | F52: Birdman | G52: Suvali | H52: 8341143877 | I52: chandana.pasupunoori@jukshio.com | J52: 44426 | L52: P | M52: P | N52: P | O52: P | P52: P | Q52: P | R52: P | S52: W/O | T52: W/O | U52: P | V52: P | W52: P | X52: P | Y52: P | Z52: P | AA52: P | AB52: P | AC52: P | AD52: W/O | AE52: P | AF52: P | AG52: L | AH52: P | AI52: P | AJ52: P | AK52: P | AL52: P | AM52: W/O | AN52: =COUNTIF(L52:AM52,"P")+COUNTIF(L52:AM52,"HFL")/2 -> 23 | AO52: =COUNTIF(L52:AM52,"W/O") -> 4 | AP52: =COUNTIF(L52:AM52,"L") -> 1 | AQ52: =COUNTIF(L52:AM52,"HFL")/2 -> 0 | AR52: =COUNTIF(L52:AM52,"H") -> 0 | AS52: =COUNTIF(L52:AM52,"MG") -> 0 | AT52: =COUNTIF(L52:AM52,"ML") -> 0 | AU52: =COUNTIF(L52:AM52,"UL") -> 0 | AV52: =COUNTIF(L52:AM52,"MC") -> 0 | AW52: =COUNTIF(L52:AM52,"BL") -> 0 | AX52: =COUNTIF(L52:AM52,"MDL") -> 0 | AY52: =COUNTIF(L52:AM52,"LOP") -> 0 | AZ52: =SUM(AN52:AY52) -> 28 | BA52: =SUM(AP52:AQ52,AS52:AY52,AN52) -> 24 | BB52: =AZ52-(AU52+BO52) -> 28 | BC52: =AN52/BA52 -> 0.95833333 | BD52: =VLOOKUP(B52,'Jan''26- Leave Bal'!$B$3:$D$83,3,0) -> 0 | BE52: =VLOOKUP(B52,'Jan''26- Leave Bal'!$B$3:$E$83,4,0)+$BE$3 -> 1 | BF52: =VLOOKUP(B52,'Jan''26- Leave Bal'!$B$3:$F$83,5,0)+$BF$3 -> 3.5 | BG52: =VLOOKUP(B52,'Jan''26- Leave Bal'!$B$3:$G$83,6,0)+$BG$3 -> 12 | BH52: =VLOOKUP(B52,'Jan''26- Leave Bal'!$B$3:$H$83,7,0) -> 15 | BI52: =VLOOKUP(B52,'Jan''26- Leave Bal'!$B$3:$I$83,8,0)+$BI$3 -> 0.75 | BJ52: =IF((AP52+AQ52)<=BD52, (AP52+AQ52),BD52) -> 0 | BK52: =IF(((AP52+AQ52)-BJ52)>BE52,BE52,(AP52+AQ52)-BJ52) -> 1 | BL52: =IF((AP52+AQ52-BJ52-BK52)>=BF52,BF52,(AP52+AQ52-BJ52-BK52)) -> 0 | BM52: =IF((AP52+AQ52-BJ52-BK52-BL52)>=BG52,BG52,(AP52+AQ52-BJ52-BK52-BL52)) -> 0 | BN52: =AS52 -> 0 | BO52: =AP52+AQ52-BJ52-BK52-BL52-BM52 -> 0 | BP52: =BD52-BJ52 -> 0 | BQ52: =BE52-BK52 -> 0 | BR52: =BF52-BL52 -> 3.5 | BS52: =BG52-BM52 -> 12 | BT52: =BH52-BN52 -> 15 | BU52: =BI52 -> 0.75 | BV52: 01st Mar weekoff taken in Feb Last week itself | BW52: 01st feb Weekoff taken early in Jan'26
A53: 50 | B53: JAI-926 | D53: Retail | E53: Cartzy | F53: Birdman | G53: Suvali | H53: 9381278392 | I53: charanya.basani@jukshio.com | J53: 45033 | L53: W/O | M53: P | N53: P | O53: P | P53: P | Q53: P | R53: W/O | S53: L | T53: P | U53: P | V53: P | W53: P | X53: P | Y53: W/O | Z53: P | AA53: W/O | AB53: P | AC53: P | AD53: L | AE53: P | AF53: P | AG53: P | AH53: P | AI53: P | AJ53: P | AK53: P | AL53: P | AM53: W/O | AN53: =COUNTIF(L53:AM53,"P")+COUNTIF(L53:AM53,"HFL")/2 -> 21 | AO53: =COUNTIF(L53:AM53,"W/O") -> 5 | AP53: =COUNTIF(L53:AM53,"L") -> 2 | AQ53: =COUNTIF(L53:AM53,"HFL")/2 -> 0 | AR53: =COUNTIF(L53:AM53,"H") -> 0 | AS53: =COUNTIF(L53:AM53,"MG") -> 0 | AT53: =COUNTIF(L53:AM53,"ML") -> 0 | AU53: =COUNTIF(L53:AM53,"UL") -> 0 | AV53: =COUNTIF(L53:AM53,"MC") -> 0 | AW53: =COUNTIF(L53:AM53,"BL") -> 0 | AX53: =COUNTIF(L53:AM53,"MDL") -> 0 | AY53: =COUNTIF(L53:AM53,"LOP") -> 0 | AZ53: =SUM(AN53:AY53) -> 28 | BA53: =SUM(AP53:AQ53,AS53:AY53,AN53) -> 23 | BB53: =AZ53-(AU53+BO53) -> 28 | BC53: =AN53/BA53 -> 0.91304348 | BD53: =VLOOKUP(B53,'Jan''26- Leave Bal'!$B$3:$D$83,3,0) -> 0 | BE53: =VLOOKUP(B53,'Jan''26- Leave Bal'!$B$3:$E$83,4,0)+$BE$3 -> 4.5 | BF53: =VLOOKUP(B53,'Jan''26- Leave Bal'!$B$3:$F$83,5,0)+$BF$3 -> 5.5 | BG53: =VLOOKUP(B53,'Jan''26- Leave Bal'!$B$3:$G$83,6,0)+$BG$3 -> 13 | BH53: =VLOOKUP(B53,'Jan''26- Leave Bal'!$B$3:$H$83,7,0) -> 15 | BI53: =VLOOKUP(B53,'Jan''26- Leave Bal'!$B$3:$I$83,8,0)+$BI$3 -> 0.75 | BJ53: =IF((AP53+AQ53)<=BD53, (AP53+AQ53),BD53) -> 0 | BK53: =IF(((AP53+AQ53)-BJ53)>BE53,BE53,(AP53+AQ53)-BJ53) -> 2 | BL53: =IF((AP53+AQ53-BJ53-BK53)>=BF53,BF53,(AP53+AQ53-BJ53-BK53)) -> 0 | BM53: =IF((AP53+AQ53-BJ53-BK53-BL53)>=BG53,BG53,(AP53+AQ53-BJ53-BK53-BL53)) -> 0 | BN53: =AS53 -> 0 | BO53: =AP53+AQ53-BJ53-BK53-BL53-BM53 -> 0 | BP53: =BD53-BJ53 -> 0 | BQ53: =BE53-BK53 -> 2.5 | BR53: =BF53-BL53 -> 5.5 | BS53: =BG53-BM53 -> 13 | BT53: =BH53-BN53 -> 15 | BU53: =BI53 -> 0.75 | BV53: 01st Mar weekoff taken in Feb Last week itself | BW53: 0
A54: 51 | B54: JAI-1015 | D54: Retail | E54: Cartzy | F54: Birdman | G54: Suvali | H54: 8096818851 | I54: sandhya.muthyala@jukshio.com | J54: 45033 | L54: P | M54: P | N54: P | O54: P | P54: P | Q54: P | R54: W/O | S54: L | T54: P | U54: P | V54: P | W54: W/O | X54: P | Y54: P | Z54: P | AA54: P | AB54: P | AC54: P | AD54: W/O | AE54: P | AF54: P | AG54: P | AH54: P | AI54: W/O | AJ54: P | AK54: P | AL54: P | AM54: P | AN54: =COUNTIF(L54:AM54,"P")+COUNTIF(L54:AM54,"HFL")/2 -> 23 | AO54: =COUNTIF(L54:AM54,"W/O") -> 4 | AP54: =COUNTIF(L54:AM54,"L") -> 1 | AQ54: =COUNTIF(L54:AM54,"HFL")/2 -> 0 | AR54: =COUNTIF(L54:AM54,"H") -> 0 | AS54: =COUNTIF(L54:AM54,"MG") -> 0 | AT54: =COUNTIF(L54:AM54,"ML") -> 0 | AU54: =COUNTIF(L54:AM54,"UL") -> 0 | AV54: =COUNTIF(L54:AM54,"MC") -> 0 | AW54: =COUNTIF(L54:AM54,"BL") -> 0 | AX54: =COUNTIF(L54:AM54,"MDL") -> 0 | AY54: =COUNTIF(L54:AM54,"LOP") -> 0 | AZ54: =SUM(AN54:AY54) -> 28 | BA54: =SUM(AP54:AQ54,AS54:AY54,AN54) -> 24 | BB54: =AZ54-(AU54+BO54) -> 28 | BC54: =AN54/BA54 -> 0.95833333 | BD54: =VLOOKUP(B54,'Jan''26- Leave Bal'!$B$3:$D$83,3,0) -> 0 | BE54: =VLOOKUP(B54,'Jan''26- Leave Bal'!$B$3:$E$83,4,0)+$BE$3 -> 0.5 | BF54: =VLOOKUP(B54,'Jan''26- Leave Bal'!$B$3:$F$83,5,0)+$BF$3 -> 4.5 | BG54: =VLOOKUP(B54,'Jan''26- Leave Bal'!$B$3:$G$83,6,0)+$BG$3 -> 13 | BH54: =VLOOKUP(B54,'Jan''26- Leave Bal'!$B$3:$H$83,7,0) -> 15 | BI54: =VLOOKUP(B54,'Jan''26- Leave Bal'!$B$3:$I$83,8,0)+$BI$3 -> 0.75 | BJ54: =IF((AP54+AQ54)<=BD54, (AP54+AQ54),BD54) -> 0 | BK54: =IF(((AP54+AQ54)-BJ54)>BE54,BE54,(AP54+AQ54)-BJ54) -> 0.5 | BL54: =IF((AP54+AQ54-BJ54-BK54)>=BF54,BF54,(AP54+AQ54-BJ54-BK54)) -> 0.5 | BM54: =IF((AP54+AQ54-BJ54-BK54-BL54)>=BG54,BG54,(AP54+AQ54-BJ54-BK54-BL54)) -> 0 | BN54: =AS54 -> 0 | BO54: =AP54+AQ54-BJ54-BK54-BL54-BM54 -> 0 | BP54: =BD54-BJ54 -> 0 | BQ54: =BE54-BK54 -> 0 | BR54: =BF54-BL54 -> 4 | BS54: =BG54-BM54 -> 13 | BT54: =BH54-BN54 -> 15 | BU54: =BI54 -> 0.75 | BW54: 0
A55: 52 | B55: JAI-564 | D55: Retail | E55: Cartzy | F55: Birdman | G55: Suvali | H55: 9951499221 | I55: umamaheshwari.gajji@jukshio.com | J55: 44845 | L55: P | M55: P | N55: P | O55: P | P55: P | Q55: P | R55: P | S55: W/O | T55: W/O | U55: P | V55: P | W55: P | X55: P | Y55: P | Z55: P | AA55: P | AB55: P | AC55: P | AD55: P | AE55: W/O | AF55: P | AG55: P | AH55: P | AI55: P | AJ55: P | AK55: W/O | AL55: P | AM55: P | AN55: =COUNTIF(L55:AM55,"P")+COUNTIF(L55:AM55,"HFL")/2 -> 24 | AO55: =COUNTIF(L55:AM55,"W/O") -> 4 | AP55: =COUNTIF(L55:AM55,"L") -> 0 | AQ55: =COUNTIF(L55:AM55,"HFL")/2 -> 0 | AR55: =COUNTIF(L55:AM55,"H") -> 0 | AS55: =COUNTIF(L55:AM55,"MG") -> 0 | AT55: =COUNTIF(L55:AM55,"ML") -> 0 | AU55: =COUNTIF(L55:AM55,"UL") -> 0 | AV55: =COUNTIF(L55:AM55,"MC") -> 0 | AW55: =COUNTIF(L55:AM55,"BL") -> 0 | AX55: =COUNTIF(L55:AM55,"MDL") -> 0 | AY55: =COUNTIF(L55:AM55,"LOP") -> 0 | AZ55: =SUM(AN55:AY55) -> 28 | BA55: =SUM(AP55:AQ55,AS55:AY55,AN55) -> 24 | BB55: =AZ55-(AU55+BO55) -> 28 | BC55: =AN55/BA55 -> 1 | BD55: =VLOOKUP(B55,'Jan''26- Leave Bal'!$B$3:$D$83,3,0) -> 0 | BE55: =VLOOKUP(B55,'Jan''26- Leave Bal'!$B$3:$E$83,4,0)+$BE$3 -> 0.5 | BF55: =VLOOKUP(B55,'Jan''26- Leave Bal'!$B$3:$F$83,5,0)+$BF$3 -> 4 | BG55: =VLOOKUP(B55,'Jan''26- Leave Bal'!$B$3:$G$83,6,0)+$BG$3 -> 13 | BH55: =VLOOKUP(B55,'Jan''26- Leave Bal'!$B$3:$H$83,7,0) -> 15 | BI55: =VLOOKUP(B55,'Jan''26- Leave Bal'!$B$3:$I$83,8,0)+$BI$3 -> 0.75 | BJ55: =IF((AP55+AQ55)<=BD55, (AP55+AQ55),BD55) -> 0 | BK55: =IF(((AP55+AQ55)-BJ55)>BE55,BE55,(AP55+AQ55)-BJ55) -> 0 | BL55: =IF((AP55+AQ55-BJ55-BK55)>=BF55,BF55,(AP55+AQ55-BJ55-BK55)) -> 0 | BM55: =IF((AP55+AQ55-BJ55-BK55-BL55)>=BG55,BG55,(AP55+AQ55-BJ55-BK55-BL55)) -> 0 | BN55: =AS55 -> 0 | BO55: =AP55+AQ55-BJ55-BK55-BL55-BM55 -> 0 | BP55: =BD55-BJ55 -> 0 | BQ55: =BE55-BK55 -> 0.5 | BR55: =BF55-BL55 -> 4 | BS55: =BG55-BM55 -> 13 | BT55: =BH55-BN55 -> 15 | BU55: =BI55 -> 0.75 | BV55: 01st Mar weekoff taken in Feb Last week itself | BW55: 01st feb Weekoff taken early in Jan'26
A56: 53 | B56: JAI-1264 | D56: CCTV | E56: CCTV | F56: CCTV | G56: Suvali | H56: 9347453906 | I56: navya.palle@jukshio.com | J56: 45159 | L56: P | M56: P | N56: P | O56: P | P56: P | Q56: P | R56: P | S56: W/O | T56: P | U56: P | V56: P | W56: P | X56: P | Y56: P | Z56: W/O | AA56: P | AB56: P | AC56: P | AD56: P | AE56: P | AF56: P | AG56: W/O | AH56: P | AI56: P | AJ56: P | AK56: P | AL56: P | AM56: W/O | AN56: =COUNTIF(L56:AM56,"P")+COUNTIF(L56:AM56,"HFL")/2 -> 24 | AO56: =COUNTIF(L56:AM56,"W/O") -> 4 | AP56: =COUNTIF(L56:AM56,"L") -> 0 | AQ56: =COUNTIF(L56:AM56,"HFL")/2 -> 0 | AR56: =COUNTIF(L56:AM56,"H") -> 0 | AS56: =COUNTIF(L56:AM56,"MG") -> 0 | AT56: =COUNTIF(L56:AM56,"ML") -> 0 | AU56: =COUNTIF(L56:AM56,"UL") -> 0 | AV56: =COUNTIF(L56:AM56,"MC") -> 0 | AW56: =COUNTIF(L56:AM56,"BL") -> 0 | AX56: =COUNTIF(L56:AM56,"MDL") -> 0 | AY56: =COUNTIF(L56:AM56,"LOP") -> 0 | AZ56: =SUM(AN56:AY56) -> 28 | BA56: =SUM(AP56:AQ56,AS56:AY56,AN56) -> 24 | BB56: =AZ56-(AU56+BO56) -> 28 | BC56: =AN56/BA56 -> 1 | BD56: =VLOOKUP(B56,'Jan''26- Leave Bal'!$B$3:$D$83,3,0) -> 0 | BE56: =VLOOKUP(B56,'Jan''26- Leave Bal'!$B$3:$E$83,4,0)+$BE$3 -> 1 | BF56: =VLOOKUP(B56,'Jan''26- Leave Bal'!$B$3:$F$83,5,0)+$BF$3 -> 1.5 | BG56: =VLOOKUP(B56,'Jan''26- Leave Bal'!$B$3:$G$83,6,0)+$BG$3 -> 8 | BH56: =VLOOKUP(B56,'Jan''26- Leave Bal'!$B$3:$H$83,7,0) -> 15 | BI56: =VLOOKUP(B56,'Jan''26- Leave Bal'!$B$3:$I$83,8,0)+$BI$3 -> 0.75 | BJ56: =IF((AP56+AQ56)<=BD56, (AP56+AQ56),BD56) -> 0 | BK56: =IF(((AP56+AQ56)-BJ56)>BE56,BE56,(AP56+AQ56)-BJ56) -> 0 | BL56: =IF((AP56+AQ56-BJ56-BK56)>=BF56,BF56,(AP56+AQ56-BJ56-BK56)) -> 0 | BM56: =IF((AP56+AQ56-BJ56-BK56-BL56)>=BG56,BG56,(AP56+AQ56-BJ56-BK56-BL56)) -> 0 | BN56: =AS56 -> 0 | BO56: =AP56+AQ56-BJ56-BK56-BL56-BM56 -> 0 | BP56: =BD56-BJ56 -> 0 | BQ56: =BE56-BK56 -> 1 | BR56: =BF56-BL56 -> 1.5 | BS56: =BG56-BM56 -> 8 | BT56: =BH56-BN56 -> 15 | BU56: =BI56 -> 0.75 | BV56: 01st Mar weekoff taken in Feb Last week itself | BW56: 01st feb Weekoff taken early in Jan'26
A57: 54 | B57: JAI-1287 | D57: CCTV | E57: CCTV | F57: CCTV | G57: Uppal | H57: 6300386376 | I57: shireesha.kamuni@jukshio.com | J57: 45159 | L57: W/O | M57: L | N57: P | O57: P | P57: P | Q57: P | R57: W/O | S57: P | T57: P | U57: P | V57: P | W57: P | X57: P | Y57: P | Z57: W/O | AA57: P | AB57: P | AC57: P | AD57: P | AE57: P | AF57: L | AG57: W/O | AH57: P | AI57: P | AJ57: P | AK57: W/O | AL57: P | AM57: P | AN57: =COUNTIF(L57:AM57,"P")+COUNTIF(L57:AM57,"HFL")/2 -> 21 | AO57: =COUNTIF(L57:AM57,"W/O") -> 5 | AP57: =COUNTIF(L57:AM57,"L") -> 2 | AQ57: =COUNTIF(L57:AM57,"HFL")/2 -> 0 | AR57: =COUNTIF(L57:AM57,"H") -> 0 | AS57: =COUNTIF(L57:AM57,"MG") -> 0 | AT57: =COUNTIF(L57:AM57,"ML") -> 0 | AU57: =COUNTIF(L57:AM57,"UL") -> 0 | AV57: =COUNTIF(L57:AM57,"MC") -> 0 | AW57: =COUNTIF(L57:AM57,"BL") -> 0 | AX57: =COUNTIF(L57:AM57,"MDL") -> 0 | AY57: =COUNTIF(L57:AM57,"LOP") -> 0 | AZ57: =SUM(AN57:AY57) -> 28 | BA57: =SUM(AP57:AQ57,AS57:AY57,AN57) -> 23 | BB57: =AZ57-(AU57+BO57) -> 28 | BC57: =AN57/BA57 -> 0.91304348 | BD57: =VLOOKUP(B57,'Jan''26- Leave Bal'!$B$3:$D$83,3,0) -> 0 | BE57: =VLOOKUP(B57,'Jan''26- Leave Bal'!$B$3:$E$83,4,0)+$BE$3 -> 0.5 | BF57: =VLOOKUP(B57,'Jan''26- Leave Bal'!$B$3:$F$83,5,0)+$BF$3 -> 0.5 | BG57: =VLOOKUP(B57,'Jan''26- Leave Bal'!$B$3:$G$83,6,0)+$BG$3 -> 10 | BH57: =VLOOKUP(B57,'Jan''26- Leave Bal'!$B$3:$H$83,7,0) -> 15 | BI57: =VLOOKUP(B57,'Jan''26- Leave Bal'!$B$3:$I$83,8,0)+$BI$3 -> 0.75 | BJ57: =IF((AP57+AQ57)<=BD57, (AP57+AQ57),BD57) -> 0 | BK57: =IF(((AP57+AQ57)-BJ57)>BE57,BE57,(AP57+AQ57)-BJ57) -> 0.5 | BL57: =IF((AP57+AQ57-BJ57-BK57)>=BF57,BF57,(AP57+AQ57-BJ57-BK57)) -> 0.5 | BM57: =IF((AP57+AQ57-BJ57-BK57-BL57)>=BG57,BG57,(AP57+AQ57-BJ57-BK57-BL57)) -> 1 | BN57: =AS57 -> 0 | BO57: =AP57+AQ57-BJ57-BK57-BL57-BM57 -> 0 | BP57: =BD57-BJ57 -> 0 | BQ57: =BE57-BK57 -> 0 | BR57: =BF57-BL57 -> 0 | BS57: =BG57-BM57 -> 9 | BT57: =BH57-BN57 -> 15 | BU57: =BI57 -> 0.75 | BV57: 01st Mar weekoff taken in Feb Last week itself | BW57: 0
A58: 55 | B58: JAI-1121 | D58: SOC | E58: SOC | F58: SOC | G58: Uppal | H58: 9704986433 | I58: mounika.billa@jukshio.com | J58: 45086 | L58: W/O | M58: P | N58: P | O58: P | P58: P | Q58: P | R58: P | S58: W/O | T58: P | U58: P | V58: P | W58: P | X58: P | Y58: P | Z58: W/O | AA58: P | AB58: P | AC58: P | AD58: L | AE58: P | AF58: P | AG58: W/O | AH58: P | AI58: P | AJ58: L | AK58: P | AL58: P | AM58: P | AN58: =COUNTIF(L58:AM58,"P")+COUNTIF(L58:AM58,"HFL")/2 -> 22 | AO58: =COUNTIF(L58:AM58,"W/O") -> 4 | AP58: =COUNTIF(L58:AM58,"L") -> 2 | AQ58: =COUNTIF(L58:AM58,"HFL")/2 -> 0 | AR58: =COUNTIF(L58:AM58,"H") -> 0 | AS58: =COUNTIF(L58:AM58,"MG") -> 0 | AT58: =COUNTIF(L58:AM58,"ML") -> 0 | AU58: =COUNTIF(L58:AM58,"UL") -> 0 | AV58: =COUNTIF(L58:AM58,"MC") -> 0 | AW58: =COUNTIF(L58:AM58,"BL") -> 0 | AX58: =COUNTIF(L58:AM58,"MDL") -> 0 | AY58: =COUNTIF(L58:AM58,"LOP") -> 0 | AZ58: =SUM(AN58:AY58) -> 28 | BA58: =SUM(AP58:AQ58,AS58:AY58,AN58) -> 24 | BB58: =AZ58-(AU58+BO58) -> 28 | BC58: =AN58/BA58 -> 0.91666667 | BD58: =VLOOKUP(B58,'Jan''26- Leave Bal'!$B$3:$D$83,3,0) -> 0 | BE58: =VLOOKUP(B58,'Jan''26- Leave Bal'!$B$3:$E$83,4,0)+$BE$3 -> 0.5 | BF58: =VLOOKUP(B58,'Jan''26- Leave Bal'!$B$3:$F$83,5,0)+$BF$3 -> 0.5 | BG58: =VLOOKUP(B58,'Jan''26- Leave Bal'!$B$3:$G$83,6,0)+$BG$3 -> 1 | BH58: =VLOOKUP(B58,'Jan''26- Leave Bal'!$B$3:$H$83,7,0) -> 15 | BI58: =VLOOKUP(B58,'Jan''26- Leave Bal'!$B$3:$I$83,8,0)+$BI$3 -> 0.75 | BJ58: =IF((AP58+AQ58)<=BD58, (AP58+AQ58),BD58) -> 0 | BK58: =IF(((AP58+AQ58)-BJ58)>BE58,BE58,(AP58+AQ58)-BJ58) -> 0.5 | BL58: =IF((AP58+AQ58-BJ58-BK58)>=BF58,BF58,(AP58+AQ58-BJ58-BK58)) -> 0.5 | BM58: =IF((AP58+AQ58-BJ58-BK58-BL58)>=BG58,BG58,(AP58+AQ58-BJ58-BK58-BL58)) -> 1 | BN58: =AS58 -> 0 | BO58: =AP58+AQ58-BJ58-BK58-BL58-BM58 -> 0 | BP58: =BD58-BJ58 -> 0 | BQ58: =BE58-BK58 -> 0 | BR58: =BF58-BL58 -> 0 | BS58: =BG58-BM58 -> 0 | BT58: =BH58-BN58 -> 15 | BU58: =BI58 -> 0.75 | BW58: 0
A59: 56 | B59: JAI-1139 | D59: SOC | E59: SOC | F59: SOC | G59: Uppal | H59: 8331843591 | I59: sandhya.gadhe@jukshio.com | J59: 45086 | L59: W/O | M59: P | N59: P | O59: P | P59: P | Q59: P | R59: P | S59: W/O | T59: P | U59: P | V59: P | W59: P | X59: L | Y59: P | Z59: W/O | AA59: L | AB59: P | AC59: P | AD59: P | AE59: P | AF59: P | AG59: W/O | AH59: P | AI59: P | AJ59: P | AK59: P | AL59: P | AM59: P | AN59: =COUNTIF(L59:AM59,"P")+COUNTIF(L59:AM59,"HFL")/2 -> 22 | AO59: =COUNTIF(L59:AM59,"W/O") -> 4 | AP59: =COUNTIF(L59:AM59,"L") -> 2 | AQ59: =COUNTIF(L59:AM59,"HFL")/2 -> 0 | AR59: =COUNTIF(L59:AM59,"H") -> 0 | AS59: =COUNTIF(L59:AM59,"MG") -> 0 | AT59: =COUNTIF(L59:AM59,"ML") -> 0 | AU59: =COUNTIF(L59:AM59,"UL") -> 0 | AV59: =COUNTIF(L59:AM59,"MC") -> 0 | AW59: =COUNTIF(L59:AM59,"BL") -> 0 | AX59: =COUNTIF(L59:AM59,"MDL") -> 0 | AY59: =COUNTIF(L59:AM59,"LOP") -> 0 | AZ59: =SUM(AN59:AY59) -> 28 | BA59: =SUM(AP59:AQ59,AS59:AY59,AN59) -> 24 | BB59: =AZ59-(AU59+BO59) -> 28 | BC59: =AN59/BA59 -> 0.91666667 | BD59: =VLOOKUP(B59,'Jan''26- Leave Bal'!$B$3:$D$83,3,0) -> 0 | BE59: =VLOOKUP(B59,'Jan''26- Leave Bal'!$B$3:$E$83,4,0)+$BE$3 -> 0.5 | BF59: =VLOOKUP(B59,'Jan''26- Leave Bal'!$B$3:$F$83,5,0)+$BF$3 -> 0.5 | BG59: =VLOOKUP(B59,'Jan''26- Leave Bal'!$B$3:$G$83,6,0)+$BG$3 -> 1 | BH59: =VLOOKUP(B59,'Jan''26- Leave Bal'!$B$3:$H$83,7,0) -> 15 | BI59: =VLOOKUP(B59,'Jan''26- Leave Bal'!$B$3:$I$83,8,0)+$BI$3 -> 0.75 | BJ59: =IF((AP59+AQ59)<=BD59, (AP59+AQ59),BD59) -> 0 | BK59: =IF(((AP59+AQ59)-BJ59)>BE59,BE59,(AP59+AQ59)-BJ59) -> 0.5 | BL59: =IF((AP59+AQ59-BJ59-BK59)>=BF59,BF59,(AP59+AQ59-BJ59-BK59)) -> 0.5 | BM59: =IF((AP59+AQ59-BJ59-BK59-BL59)>=BG59,BG59,(AP59+AQ59-BJ59-BK59-BL59)) -> 1 | BN59: =AS59 -> 0 | BO59: =AP59+AQ59-BJ59-BK59-BL59-BM59 -> 0 | BP59: =BD59-BJ59 -> 0 | BQ59: =BE59-BK59 -> 0 | BR59: =BF59-BL59 -> 0 | BS59: =BG59-BM59 -> 0 | BT59: =BH59-BN59 -> 15 | BU59: =BI59 -> 0.75 | BW59: 0
A60: 57 | B60: JAI-1136 | D60: SOC | E60: SOC | F60: SOC | G60: Uppal | H60: 8247453216 | I60: rishika.mudavath@jukshio.com | J60: 45086 | L60: W/O | M60: L | N60: P | O60: P | P60: P | Q60: P | R60: P | S60: W/O | T60: P | U60: P | V60: P | W60: P | X60: P | Y60: P | Z60: W/O | AA60: HFL | AB60: P | AC60: P | AD60: L | AE60: P | AF60: P | AG60: W/O | AH60: P | AI60: L | AJ60: P | AK60: P | AL60: P | AM60: P | AN60: =COUNTIF(L60:AM60,"P")+COUNTIF(L60:AM60,"HFL")/2 -> 20.5 | AO60: =COUNTIF(L60:AM60,"W/O") -> 4 | AP60: =COUNTIF(L60:AM60,"L") -> 3 | AQ60: =COUNTIF(L60:AM60,"HFL")/2 -> 0.5 | AR60: =COUNTIF(L60:AM60,"H") -> 0 | AS60: =COUNTIF(L60:AM60,"MG") -> 0 | AT60: =COUNTIF(L60:AM60,"ML") -> 0 | AU60: =COUNTIF(L60:AM60,"UL") -> 0 | AV60: =COUNTIF(L60:AM60,"MC") -> 0 | AW60: =COUNTIF(L60:AM60,"BL") -> 0 | AX60: =COUNTIF(L60:AM60,"MDL") -> 0 | AY60: =COUNTIF(L60:AM60,"LOP") -> 0 | AZ60: =SUM(AN60:AY60) -> 28 | BA60: =SUM(AP60:AQ60,AS60:AY60,AN60) -> 24 | BB60: =AZ60-(AU60+BO60) -> 27.5 | BC60: =AN60/BA60 -> 0.85416667 | BD60: =VLOOKUP(B60,'Jan''26- Leave Bal'!$B$3:$D$83,3,0) -> 0 | BE60: =VLOOKUP(B60,'Jan''26- Leave Bal'!$B$3:$E$83,4,0)+$BE$3 -> 0.5 | BF60: =VLOOKUP(B60,'Jan''26- Leave Bal'!$B$3:$F$83,5,0)+$BF$3 -> 0.5 | BG60: =VLOOKUP(B60,'Jan''26- Leave Bal'!$B$3:$G$83,6,0)+$BG$3 -> 2 | BH60: =VLOOKUP(B60,'Jan''26- Leave Bal'!$B$3:$H$83,7,0) -> 15 | BI60: =VLOOKUP(B60,'Jan''26- Leave Bal'!$B$3:$I$83,8,0)+$BI$3 -> 0.75 | BJ60: =IF((AP60+AQ60)<=BD60, (AP60+AQ60),BD60) -> 0 | BK60: =IF(((AP60+AQ60)-BJ60)>BE60,BE60,(AP60+AQ60)-BJ60) -> 0.5 | BL60: =IF((AP60+AQ60-BJ60-BK60)>=BF60,BF60,(AP60+AQ60-BJ60-BK60)) -> 0.5 | BM60: =IF((AP60+AQ60-BJ60-BK60-BL60)>=BG60,BG60,(AP60+AQ60-BJ60-BK60-BL60)) -> 2 | BN60: =AS60 -> 0 | BO60: =AP60+AQ60-BJ60-BK60-BL60-BM60 -> 0.5 | BP60: =BD60-BJ60 -> 0 | BQ60: =BE60-BK60 -> 0 | BR60: =BF60-BL60 -> 0 | BS60: =BG60-BM60 -> 0 | BT60: =BH60-BN60 -> 15 | BU60: =BI60 -> 0.75 | BW60: 0
A61: 58 | B61: JAI-081 | D61: SOC | E61: SOC | F61: SOC | G61: Uppal | H61: 7671000540 | I61: divyakumari.kolluri@jukshio.com | J61: 43983 | L61: W/O | M61: P | N61: P | O61: P | P61: P | Q61: L | R61: P | S61: W/O | T61: P | U61: P | V61: P | W61: P | X61: P | Y61: P | Z61: W/O | AA61: P | AB61: P | AC61: P | AD61: L | AE61: P | AF61: P | AG61: W/O | AH61: P | AI61: P | AJ61: P | AK61: P | AL61: P | AM61: P | AN61: =COUNTIF(L61:AM61,"P")+COUNTIF(L61:AM61,"HFL")/2 -> 22 | AO61: =COUNTIF(L61:AM61,"W/O") -> 4 | AP61: =COUNTIF(L61:AM61,"L") -> 2 | AQ61: =COUNTIF(L61:AM61,"HFL")/2 -> 0 | AR61: =COUNTIF(L61:AM61,"H") -> 0 | AS61: =COUNTIF(L61:AM61,"MG") -> 0 | AT61: =COUNTIF(L61:AM61,"ML") -> 0 | AU61: =COUNTIF(L61:AM61,"UL") -> 0 | AV61: =COUNTIF(L61:AM61,"MC") -> 0 | AW61: =COUNTIF(L61:AM61,"BL") -> 0 | AX61: =COUNTIF(L61:AM61,"MDL") -> 0 | AY61: =COUNTIF(L61:AM61,"LOP") -> 0 | AZ61: =SUM(AN61:AY61) -> 28 | BA61: =SUM(AP61:AQ61,AS61:AY61,AN61) -> 24 | BB61: =AZ61-(AU61+BO61) -> 28 | BC61: =AN61/BA61 -> 0.91666667 | BD61: =VLOOKUP(B61,'Jan''26- Leave Bal'!$B$3:$D$83,3,0) -> 0 | BE61: =VLOOKUP(B61,'Jan''26- Leave Bal'!$B$3:$E$83,4,0)+$BE$3 -> 0.5 | BF61: =VLOOKUP(B61,'Jan''26- Leave Bal'!$B$3:$F$83,5,0)+$BF$3 -> 4 | BG61: =VLOOKUP(B61,'Jan''26- Leave Bal'!$B$3:$G$83,6,0)+$BG$3 -> 13 | BH61: =VLOOKUP(B61,'Jan''26- Leave Bal'!$B$3:$H$83,7,0) -> 15 | BI61: =VLOOKUP(B61,'Jan''26- Leave Bal'!$B$3:$I$83,8,0)+$BI$3 -> 0.75 | BJ61: =IF((AP61+AQ61)<=BD61, (AP61+AQ61),BD61) -> 0 | BK61: =IF(((AP61+AQ61)-BJ61)>BE61,BE61,(AP61+AQ61)-BJ61) -> 0.5 | BL61: =IF((AP61+AQ61-BJ61-BK61)>=BF61,BF61,(AP61+AQ61-BJ61-BK61)) -> 1.5 | BM61: =IF((AP61+AQ61-BJ61-BK61-BL61)>=BG61,BG61,(AP61+AQ61-BJ61-BK61-BL61)) -> 0 | BN61: =AS61 -> 0 | BO61: =AP61+AQ61-BJ61-BK61-BL61-BM61 -> 0 | BP61: =BD61-BJ61 -> 0 | BQ61: =BE61-BK61 -> 0 | BR61: =BF61-BL61 -> 2.5 | BS61: =BG61-BM61 -> 13 | BT61: =BH61-BN61 -> 15 | BU61: =BI61 -> 0.75 | BW61: 0
